Workbook

Sheet T00
A1: INDEX
A2: Cloud ERP – Steelstone IT | Master index of all form specification sheets | Jurisdiction: Pakistan
A4: Sr. No | B4: Page No | C4: Form / Document | D4: Module | E4: DUMMY ENTRIES
A5: 1 | B5: 01 | C5: ENTERPRISE REGISTRATION | D5: Operations | E5: 1
A6: 2 | B6: 02 | C6: MANUFACTURER (SUPPLIER) REGISTRATION | D6: Sales | E6: 3
A7: 3 | B7: 03 | C7: DISTRIBUTOR REGISTRATION | D7: Sales | E7: 5
A8: 4 | B8: 04 | C8: CUSTOMER REGISTRATION - END USER | D8: Sales | E8: 5
A9: 5 | B9: 05 | C9: TRANSPORTER REGISTRATION | D9: Operations | E9: 3
A10: 6 | B10: 06 | C10: VEHICLE REGISTRATION | D10: Operations | E10: 20
A11: 7 | B11: 07 | C11: MANPOWER / HR - EMPLOYEE REGISTRATION | D11: Operations | E11: 25
A12: 8 | B12: 08 | C12: BILL (SUPPLIER / VENDOR BILL BOOKING) | D12: Operations | E12: 150
A13: 9 | B13: 09 | C13: QUOTATION (SALES QUOTE) | D13: Sales | E13: 50
A14: 10 | B14: 10 | C14: PAYMENT VOUCHER | D14: Finance | E14: 75
A15: 11 | B15: 11 | C15: SALES TAX INVOICE | D15: Sales | E15: 40
A16: 12 | B16: 12 | C16: PAYROLL | D16: Operations | E16: 5
... A19: 15 | B19: 15 | C19: PAYMENT RECEIPT (CUSTOMER RECEIPT) | D19: Finance | E19: 60

Sheet T01
A1: SECTION 1 - BUSINESS REGISTRATION | E1: SECTION 2 - REGISTERED OFFICE & OTHER ADDRESSES | P1: SECTION 3 - POINTS OF CONTACT | S1: SECTION 4 - BANKING DETAILS - multiple options
A2: 1.1 Business name (Title) | B2: 1.2 Legal status | C2: 1.3 NTN / CNIC number | D2: 1.4 Filer status | E2: 2.1 Registered office - address line 1 | F2: 2.2 Registered office - address line 2 | G2: 2.3 City | H2: 2.4 District / Tehsil | I2: 2.5 Province / Territory | J2: 2.6 Country | K2: 2.7 Is the registered office the same as the main business address? | L2: 2.8 Correspondence / mailing address (if different) | M2: 2.9 Branch / factory / warehouse address(es) | N2: 2.10 Landline number | O2: 2.11 Geo-coordinates of main business address (lat, long) | P2: 3.1 Primary POC - full name | Q2: 3.2 Primary POC - designation | R2: 3.3 Primary POC - mobile | S2: 4.1 Bank name | T2: 4.2 Title of account | U2: 4.3 Account number
A3: Steelstone Building Materials (Pvt) Ltd | B3: Private Limited Company | C3: 4521789-3 | D3: Active Filer | E3: Office 12, 3rd Floor, Siddiq Trade Centre | F3: Main Boulevard, Gulberg III | G3: Lahore | H3: Lahore City | I3: Punjab | J3: Pakistan | K3: Yes | L3: Same as registered office | M3: Warehouse: Plot 45, Sundar Industrial Estate, Raiwind Road, Lahore | N3: 042-35781234 | O3: 31.5165, 74.3487 | P3: Usman Tariq | Q3: Chief Executive Officer | R3: 0300-4567812 | S3: Meezan Bank Ltd | T3: Steelstone Building Materials (Pvt) Ltd | U3: 0211-0104567890

Sheet T02
A1: SECTION 1 - BUSINESS REGISTRATION | E1: SECTION 2 - PLANTS / PRODUCTION FACILITIES | R1: SECTION 3 - POINTS OF CONTACT | U1: SECTION 4 - BANK ACCOUNT DETAILS | X1: SECTION 5 - WORKING CALENDAR, SHIFTS & DISPATCH WINDOWS | AK1: SECTION 6 - PRODUCT PRICING | AP1: SECTION 7 - WITHHOLDING TAX EXEMPTION
A2: 1.1 Business name (Title) | B2: 1.2 Legal status | C2: 1.3 NTN / CNIC number | D2: 1.4 Filer status | E2: 2.1 Plant serial no. | F2: 2.2 Plant name | G2: 2.3 Plant code | H2: 2.4 Plant address (full) | I2: 2.5 Plant city / province | J2: 2.6 Plant geo-coordinates (lat, long) | K2: 2.7 Plant Manager - full name & designation | L2: 2.8 Plant Manager - mobile | M2: 2.9 Production Manager - full name & designation | N2: 2.10 Production Manager - mobile | O2: 2.11 Plant landline / control room number | P2: 2.12 Products manufactured at this plant | Q2: 2.13 Plant operational status | R2: 3.1 Full name | S2: 3.2 Designation | T2: 3.3 Mobile number | U2: 4.1 Bank name | V2: 4.2 Title of account | W2: 4.3 Account number | X2: 5.1 Working days per week | Y2: 5.2 Weekly off day(s) | Z2: 5.3 Plant operating pattern | AA2: 5.4 Shift timings | AB2: 5.5 Dispatch / loading hours | AC2: 5.6 Order cut-off time for same-day dispatch | AD2: 5.7 Office / commercial working hours | AE2: 5.8 Annual maintenance shutdown period | AF2: 5.9 Public / religious holidays observed | AG2: 5.10 Ramadan / seasonal timing changes | AH2: 5.11 Emergency / after-hours dispatch available? | AI2: 5.12 Calendar applies to (plant) | AJ2: 5.13 Calendar effective from / to | AK2: 6.1 Name of product | AL2: 6.2 Unit of measure (UoM) | AM2: 6.3 Price per UoM (PKR) | AN2: 6.4 Discount | AO2: 6.5 Discount validity (from / to) | AP2: 7.1 Exemption availed? | AQ2: 7.2 Exemption validity (from / to) | AR2: 7.3 Withholding tax rate during exemption (%)
A3: Margalla Cement Ltd | B3: Public Limited Company (Listed) | C3: 0712345-6 | D3: Active Filer | E3: 1 | F3: Margalla Cement - Chakwal Plant | G3: MCL-CHK | H3: Kallar Kahar Road, Mouza Dhudial, Tehsil Choa Saidan Shah | I3: Chakwal / Punjab | J3: 32.7802, 72.8531 | K3: Engr. Kamran Haider - General Manager Plant | L3: 0333-5412780 | M3: Faisal Mehmood - Production Manager | N3: 0321-5098122 | O3: 0543-661200 | P3: OPC 53 (bag & bulk), SRC (bag & bulk) | Q3: Operational | R3: Shahid Iqbal | S3: Regional Sales Manager - Central Punjab | T3: 0300-8451290 | U3: Habib Bank Ltd | V3: Margalla Cement Ltd - Collection A/c | W3: 1234-79001122-03 | X3: 6 | Y3: Sunday | Z3: 24x7 continuous kiln; 3 shifts | AA3: A 06:00-14:00; B 14:00-22:00; C 22:00-06:00 | AB3: 07:00-23:00 | AC3: 0.58333333 | AD3: 09:00-17:30 (Mon-Sat) | AE3: 15-Jan to 05-Feb (kiln relining) | AF3: Eid-ul-Fitr (3 days), Eid-ul-Adha (3 days), 14-Aug, 9/10 Muharram | AG3: Ramadan dispatch 08:00-16:00 & 21:00-02:00 | AH3: Yes - with 12 hours notice | AI3: Margalla Cement - Chakwal Plant | AJ3: 01-Jan-2026 to 31-Dec-2026 | AK3: OPC Cement Grade 53 - 50 kg bag | AL3: Bag | AM3: 1290 | AN3: PKR 10 per bag on > 5,000 bags/month | AO3: 01-Jul-2026 to 31-Dec-2026 | AP3: No | AQ3: N/A | AR3: N/A
A4: Indus Valley Cement (Pvt) Ltd | B4: Private Limited Company | C4: 3398761-2 | D4: Active Filer | E4: 1 | F4: Indus Valley Cement - D.G. Khan Plant | G4: IVC-DGK | H4: Sakhi Sarwar Road, 22 km west of D.G. Khan | I4: Dera Ghazi Khan / Punjab | J4: 30.0512, 70.4471 | K4: Tariq Mahmood - Plant Head | L4: 0301-7745120 | M4: Adnan Qureshi - Production Manager | N4: 0345-6612398 | O4: 064-2461550 | P4: Slag, PPC, OPC jumbo, Rapid hardening | Q4: Operational | R4: Rizwan Akhtar | S4: Key Account Manager | T4: 0302-4418823 | U4: MCB Bank Ltd | V4: Indus Valley Cement (Pvt) Ltd | W4: 0876-5501234401 | X4: 6 | Y4: Sunday | Z4: 24x7 continuous kiln; 3 shifts | AA4: A 06:00-14:00; B 14:00-22:00; C 22:00-06:00 | AB4: 07:00-23:00 | AC4: 0.58333333 | AD4: 09:00-17:30 (Mon-Sat) | AE4: 15-Jan to 05-Feb (kiln relining) | AF4: Eid-ul-Fitr (3 days), Eid-ul-Adha (3 days), 14-Aug, 9/10 Muharram | AG4: Ramadan dispatch 08:00-16:00 & 21:00-02:00 | AH4: Yes - with 12 hours notice | AI4: Indus Valley Cement - D.G. Khan Plant | AJ4: 01-Jan-2026 to 31-Dec-2026 | AK4: Slag Cement - 50 kg bag | AL4: Bag | AM4: 1240 | AN4: 2% on advance payment | AO4: 01-Apr-2026 to 30-Sep-2026 | AP4: Yes | AQ4: 01-Jul-2025 to 30-Jun-2026 | AR4: 0.01
A5: Salt Range White Cement Ltd | B5: Public Limited Company (Unlisted) | C5: 2276540-9 | D5: Active Filer | E5: 1 | F5: Salt Range - Khewra White Cement Plant | G5: SRW-KHW | H5: Khewra-Pind Dadan Khan Road, Khewra | I5: Jhelum / Punjab | J5: 32.6479, 73.0105 | K5: Dr. Naveed Anjum - Plant Director | L5: 0300-5567431 | M5: Salman Javed - Production Manager | N5: 0331-2289014 | O5: 0544-211875 | P5: White cement, Low heat cement, OPC bag | Q5: Under maintenance | R5: Ayesha Siddiqui | S5: Sales Coordinator | T5: 0333-4290176 | U5: Bank Alfalah Ltd | V5: Salt Range White Cement Ltd | W5: 5501-1004-0098712 | X5: 6 | Y5: Sunday | Z5: Single shift (white cement mill) | AA5: 08:00-17:00 | AB5: 09:00-17:00 | AC5: 0.58333333 | AD5: 09:00-17:30 (Mon-Sat) | AE5: 01-Sep to 15-Oct-2026 (mill upgrade) | AF5: Eid-ul-Fitr (3 days), Eid-ul-Adha (3 days), 14-Aug, 9/10 Muharram | AG5: Ramadan dispatch 08:00-16:00 & 21:00-02:00 | AH5: Yes - with 12 hours notice | AI5: Salt Range - Khewra White Cement Plant | AJ5: 01-Jan-2026 to 31-Dec-2026 | AK5: White Cement - 40 kg bag | AL5: Bag | AM5: 2350 | AN5: None | AO5: N/A | AP5: No | AQ5: N/A | AR5: N/A

Sheet T03
A1: SECTION 1 - BUSINESS REGISTRATION | E1: SECTION 2 - POINTS OF CONTACT | H1: SECTION 3 - BANK ACCOUNT DETAILS | K1: SECTION 4 - PAYMENT TERMS
A2: 1.1 Business name (Title) | B2: 1.2 Legal status | C2: 1.3 NTN / CNIC number | D2: 1.4 Filer status | E2: 2.1 Full name | F2: 2.2 Designation | G2: 2.3 Mobile number | H2: 3.1 Bank name | I2: 3.2 Title of account | J2: 3.3 Account number | K2: 4.1 Payment terms | L2: 4.2 Early payment / prompt settlement discount
A3: Gujranwala Cement Traders | B3: Sole Proprietorship | C3: 34101-2567891-3 (CNIC) | D3: Active Filer | E3: Haji Muhammad Rafiq | F3: Proprietor | G3: 0300-6421785 | H3: Allied Bank Ltd | I3: Gujranwala Cement Traders | J3: 0010-0045678-9012 | K3: Credit 30 days | L3: 1% if paid within 7 days
A4: Sheikhupura Building Stores (AOP) | B4: Association of Persons (Partnership) | C4: 5123987-1 | D4: Active Filer | E4: Imran Bashir | F4: Managing Partner | G4: 0321-4150992 | H4: United Bank Ltd | I4: Sheikhupura Building Stores | J4: 0415-2280117 | K4: Credit 15 days | L4: 0.5% if paid within 5 days
A5: Kasur Construction Supplies | B5: Sole Proprietorship | C5: 35102-9087612-5 (CNIC) | D5: Inactive / Non-filer | E5: Nadeem Akram | F5: Proprietor | G5: 0345-7719034 | H5: Bank Al Habib Ltd | I5: Nadeem Akram | J5: 1002-0981-012233-01 | K5: Advance payment | L5: None
A6: Lyallpur Cement House (Pvt) Ltd | B6: Private Limited Company | C6: 4410982-6 | D6: Active Filer | E6: Zahid Hussain | F6: Director Sales | G6: 0300-7651123 | H6: Meezan Bank Ltd | I6: Lyallpur Cement House (Pvt) Ltd | J6: 0301-0100998877 | K6: Credit 30 days | L6: 1% if paid within 10 days
A7: Sahiwal Traders & Co (AOP) | B7: Association of Persons (Partnership) | C7: 6021345-8 | D7: Active Filer | E7: Asif Mehmood | F7: Partner | G7: 0333-6908812 | H7: Faysal Bank Ltd | I7: Sahiwal Traders & Co | J7: 3321-3010-0005566 | K7: Credit 7 days | L7: None

Sheet T04
A1: SECTION 1 - BUSINESS REGISTRATION | E1: SECTION 2 - DELIVERY MODE SELECTION | O1: SECTION 3 - BAG DELIVERY POINTS | AC1: SECTION 4 - BULKER DELIVERY POINTS | AG1: SECTION 5 - POINTS OF CONTACT | AJ1: SECTION 6 - BANK ACCOUNT DETAILS | AM1: SECTION 7 - EXEMPTION CERTIFICATES
A2: 1.1 Business name (Title) | B2: 1.2 Legal status | C2: 1.3 NTN / CNIC number | D2: 1.4 Filer status | E2: 2.1 Delivery mode required (DELIVERY-TYPE CHECK) | F2: 2.2 Number of bag delivery points | G2: 2.3 Number of bulker delivery points | H2: 2.4 Delivery basis / Incoterm | I2: 2.5 Transport arrangement | J2: 2.6 Preferred delivery days | K2: 2.7 Preferred delivery time window | L2: 2.8 Advance notice required before delivery (hours) | M2: 2.9 Site access constraints | N2: 2.10 Delivery documentation required at gate | O2: 3.1 Bag delivery point serial no. | P2: 3.2 Delivery point name / code | Q2: 3.3 Address line 1 | R2: 3.4 Address line 2 / landmark | S2: 3.5 City / District | T2: 3.6 Province | U2: 3.7 Geo-coordinates (lat, long) | V2: 3.8 Site contact - name & mobile | W2: 3.9 Receiving hours at this point | X2: 3.10 Covered storage available & capacity (bags) | Y2: 3.11 Unloading labour provided by | Z2: 3.12 Largest vehicle that can access the site | AA2: 3.13 Is this the default bag delivery point? | AB2: 3.14 Delivery point status | AC2: 4.1 Delivery point name | AD2: 4.2 Address | AE2: 4.3 POC name | AF2: 4.4 Mobile number | AG2: 5.1 Full name | AH2: 5.2 Designation | AI2: 5.3 Mobile number | AJ2: 6.1 Bank name | AK2: 6.2 Title of account | AL2: 6.3 Account number | AM2: 7.1 Certificate number | AN2: 7.2 Issuing authority / tax office | AO2: 7.3 Section / statutory reference | AP2: 7.4 Applicable tax type & normal rate | AQ2: 7.5 Exempted / reduced rate granted | AR2: 7.6 Valid from | AS2: 7.7 Valid until | AT2: 7.8 Renewal reminder lead time (days) | AU2: 7.9 Certificate copy attached | AV2: 7.10 Verified by & date (internal) | AW2: 7.11 Certificate status
A3: Bahria Heights Developers (Pvt) Ltd | B3: Private Limited Company | C3: 7712098-4 | D3: Active Filer | E3: Both (bag & bulker) | F3: 1 | G3: 1 | H3: Delivered at site (DAP) | I3: Arranged by Steelstone | J3: Mon-Sat | K3: 08:00-18:00 | L3: 24 | M3: Heavy vehicles allowed after 21:00 on main boulevard | N3: Delivery challan, weighbridge slip, gate pass | O3: 1 | P3: BHD-BAG-01 Tower Block C | Q3: Plot 7, Sector C, Bahria Heights | R3: Near Grand Mosque roundabout | S3: Lahore | T3: Punjab | U3: 31.3701, 74.1842 | V3: Waqas Ali - 0301-4412987 | W3: 08:00-18:00 | X3: Yes - 8,000 bags | Y3: Customer | Z3: 22-wheeler trailer | AA3: Yes | AB3: Active | AC3: BHD-BLK-01 Batching Plant | AD3: Batching plant, Sector F, Bahria Heights, Lahore | AE3: Engr. Hamza Rauf | AF3: 0322-4671203 | AG3: Faisal Rehman | AH3: Procurement Manager | AI3: 0300-4107765 | AJ3: Bank Alfalah Ltd | AK3: Bahria Heights Developers (Pvt) Ltd | AL3: 0099-1005-123987 | AM3: N/A | AN3: N/A | AO3: N/A | AP3: N/A | AQ3: N/A | AR3: N/A | AS3: N/A | AT3: N/A | AU3: No | AV3: N/A | AW3: Not applicable
A4: Crescent Builders & Contractors (AOP) | B4: Association of Persons (Partnership) | C4: 3087712-5 | D4: Active Filer | E4: Bag only | F4: 1 | G4: 0 | H4: Ex-warehouse (EXW) | I4: Customer's own transport | J4: Mon-Sat | K4: 09:00-17:00 | L4: 12 | M4: Narrow street - max 10-wheeler | N4: Delivery challan | O4: 1 | P4: CBC-BAG-01 Johar Town site | Q4: House 112, Block R-1, Johar Town | R4: Opp. Emporium Mall service lane | S4: Lahore | T4: Punjab | U4: 31.4677, 74.2663 | V4: Bilal Ahmad - 0333-4401298 | W4: 09:00-17:00 | X4: No | Y4: Steelstone | Z4: 10-wheeler truck | AA4: Yes | AB4: Active | AC4: N/A | AD4: N/A | AE4: N/A | AF4: N/A | AG4: Arshad Mahmood | AH4: Partner | AI4: 0321-8845120 | AJ4: Habib Bank Ltd | AK4: Crescent Builders & Contractors | AL4: 1478-79009876-01 | AM4: N/A | AN4: N/A | AO4: N/A | AP4: N/A | AQ4: N/A | AR4: N/A | AS4: N/A | AT4: N/A | AU4: No | AV4: N/A | AW4: Not applicable
A5: Punjab Highways Construction Co (Pvt) Ltd | B5: Private Limited Company | C5: 1190876-3 | D5: Active Filer | E5: Bulker only | F5: 0 | G5: 1 | H5: Delivered at site (DAP) | I5: Arranged by Steelstone | J5: All days | K5: 24 hours | L5: 48 | M5: Site on M-2 service road; escort needed | N5: Delivery challan, weighbridge slip, mill test certificate | O5: N/A | P5: N/A | Q5: N/A | R5: N/A | S5: N/A | T5: N/A | U5: N/A | V5: N/A | W5: N/A | X5: N/A | Y5: N/A | Z5: N/A | AA5: N/A | AB5: N/A | AC5: PHC-BLK-01 Sheikhupura Interchange camp | AD5: Km 28, Lahore-Sheikhupura Road, Camp Office | AE5: Engr. Saqib Nawaz | AF5: 0300-9412076 | AG5: Muhammad Ali Raza | AH5: Project Manager | AI5: 0345-4098213 | AJ5: National Bank of Pakistan | AK5: Punjab Highways Construction Co | AL5: 4012-3456-7890-12 | AM5: WHT-EX-2025/LTO-LHR/0457 | AN5: LTO Lahore | AO5: Sec. 159(1) Income Tax Ordinance 2001 | AP5: Income tax u/s 153(1)(a) - 5% | AQ5: 0.01 | AR5: 45839 | AS5: 46203 | AT5: 30 | AU5: Yes | AV5: Sana Iqbal - 05-Jul-2025 | AW5: Expired
A6: Ravi Riverfront Contractors (Pvt) Ltd | B6: Private Limited Company | C6: 8834521-0 | D6: Active Filer | E6: Both (bag & bulker) | F6: 1 | G6: 1 | H6: Delivered at site (DAP) | I6: Arranged by Steelstone | J6: Mon-Fri | K6: 07:00-19:00 | L6: 24 | M6: Security clearance at main gate | N6: Delivery challan, gate pass, MTC | O6: 1 | P6: RRC-BAG-01 Main store | Q6: Ravi City Phase 1, Store Yard 3 | R6: Near Shahdara flyover | S6: Lahore | T6: Punjab | U6: 31.6120, 74.2996 | V6: Usama Khalid - 0302-4455781 | W6: 07:00-19:00 | X6: Yes - 5,000 bags | Y6: Customer | Z6: 22-wheeler trailer | AA6: Yes | AB6: Active | AC6: RRC-BLK-01 Barrage batching plant | AD6: Ravi Barrage site, Phase 1, Lahore | AE6: Engr. Taimoor Aslam | AF6: 0331-4789021 | AG6: Sadia Noor | AH6: Head of Procurement | AI6: 0300-4981276 | AJ6: Standard Chartered Bank | AK6: Ravi Riverfront Contractors (Pvt) Ltd | AL6: 01-7654321-01 | AM6: WHT-EX-2026/RTO-LHR/1182 | AN6: RTO Lahore | AO6: Sec. 159(1) Income Tax Ordinance 2001 | AP6: Income tax u/s 153(1)(a) - 5% | AQ6: 0.02 | AR6: 46204 | AS6: 46568 | AT6: 30 | AU6: Yes | AV6: Sana Iqbal - 04-Jul-2026 | AW6: Valid
A7: Muhammad Aslam Construction | B7: Sole Proprietorship | C7: 35202-4412876-1 (CNIC) | D7: Active Filer | E7: Bag only | F7: 1 | G7: 0 | H7: Delivered at site (DAP) | I7: Arranged by Steelstone | J7: Mon-Sat | K7: 08:00-16:00 | L7: 12 | M7: None | N7: Delivery challan | O7: 1 | P7: MAC-BAG-01 DHA Phase 9 site | Q7: Plot 245, Block B, DHA Phase 9 Town | R7: Behind Commercial Area | S7: Lahore | T7: Punjab | U7: 31.4203, 74.4417 | V7: Muhammad Aslam - 0300-4219087 | W7: 08:00-16:00 | X7: Yes - 1,500 bags | Y7: Steelstone | Z7: 10-wheeler truck | AA7: Yes | AB7: Active | AC7: N/A | AD7: N/A | AE7: N/A | AF7: N/A | AG7: Muhammad Aslam | AH7: Proprietor | AI7: 0300-4219087 | AJ7: Askari Bank Ltd | AK7: Muhammad Aslam | AL7: 0512-0100334455 | AM7: N/A | AN7: N/A | AO7: N/A | AP7: N/A | AQ7: N/A | AR7: N/A | AS7: N/A | AT7: N/A | AU7: No | AV7: N/A | AW7: Not applicable

Sheet T05
A1: SECTION 1 - BUSINESS REGISTRATION | E1: SECTION 2 - POINTS OF CONTACT | H1: SECTION 3 - BANK ACCOUNT DETAILS | K1: SECTION 4 - WITHHOLDING TAX EXEMPTION
A2: 1.1 Business name (Title) | B2: 1.2 Legal status | C2: 1.3 NTN / CNIC number | D2: 1.4 Filer status | E2: 2.1 Full name | F2: 2.2 Designation | G2: 2.3 Mobile number | H2: 3.1 Bank name | I2: 3.2 Title of account | J2: 3.3 Account number | K2: 4.1 Exemption availed? | L2: 4.2 Exemption validity (from / to) | M2: 4.3 Withholding tax rate during exemption (%)
A3: Khan Goods Transport Co | B3: Sole Proprietorship | C3: 17301-5567812-9 (CNIC) | D3: Active Filer | E3: Gul Khan | F3: Owner | G3: 0300-5991287 | H3: Habib Bank Ltd | I3: Khan Goods Transport Co | J3: 2210-79004455-01 | K3: No | L3: N/A | M3: N/A
A4: Al-Madina Logistics (Pvt) Ltd | B4: Private Limited Company | C4: 5567123-4 | D4: Active Filer | E4: Tahir Mehmood | F4: Operations Manager | G4: 0321-4789012 | H4: MCB Bank Ltd | I4: Al-Madina Logistics (Pvt) Ltd | J4: 0654-7701122301 | K4: Yes | L4: 01-Jul-2026 to 30-Jun-2027 | M4: 0.02
A5: Punjab Bulk Carriers (AOP) | B5: Association of Persons (Partnership) | C5: 4098877-2 | D5: Inactive / Non-filer | E5: Sajjad Hussain | F5: Managing Partner | G5: 0333-4128876 | H5: United Bank Ltd | I5: Punjab Bulk Carriers | J5: 0900-2201456 | K5: No | L5: N/A | M5: N/A

Sheet T06
A1: SECTION 1 - VEHICLE IDENTIFICATION & REGISTRATION | Q1: SECTION 2 - VEHICLE STATUTORY DOCUMENTS & VALIDITY
A2: 1.1 Vehicle record code | B2: 1.2 Owning transporter | C2: 1.3 Ownership type | D2: 1.4 Registered owner name & NTN | E2: 1.5 Vehicle registration number | F2: 1.6 Registering authority & province | G2: 1.7 Date of registration | H2: 1.8 Registration book / smart card number | I2: 1.9 Vehicle category | J2: 1.10 Vehicle type | K2: 1.11 Make & model | L2: 1.12 Year of manufacture | M2: 1.13 Chassis number | N2: 1.14 Engine number | O2: 1.15 Colour | P2: 1.16 Registration status | Q2: 2.1 Route permit number | R2: 2.2 Route permit - valid until | S2: 2.3 Route permit - status (system-derived) | T2: 2.4 Fitness certificate number | U2: 2.5 Fitness certificate - valid until | V2: 2.6 Fitness certificate - status (system-derived) | W2: 2.7 Token tax - paid up to | X2: 2.8 Token tax - status (system-derived)
A3: VEH-001 | B3: TRN-001 - Khan Goods Transport Co | C3: Owned by transporter | D3: Khan Goods Transport Co / 17301-5567812-9 (CNIC) | E3: JLM-3574 | F3: Excise, Taxation & Narcotics Control Dept - Punjab | G3: 41934 | H3: PB-SC-5885652 | I3: Heavy transport vehicle (HTV) | J3: 22-wheeler trailer | K3: Hino 700 SH | L3: 2014 | M3: JH71606308K | N3: E13C-672323 | O3: Yellow | P3: Active | Q3: RTA-PB/31780/2014 | R3: 46467 | S3: =IF(R3<TODAY(),"Expired",IF(R3-TODAY()<=30,"Expiring soon","Valid")) -> Valid | T3: MVE-FC-436808 | U3: 46517 | V3: =IF(U3<TODAY(),"Expired",IF(U3-TODAY()<=30,"Expiring soon","Valid")) -> Valid | W3: 46568 | X3: =IF(W3<TODAY(),"Expired",IF(W3-TODAY()<=30,"Expiring soon","Valid")) -> Valid
A4: VEH-002 | B4: TRN-001 - Khan Goods Transport Co | C4: Owned by transporter | D4: Khan Goods Transport Co / 17301-5567812-9 (CNIC) | E4: FDA-1479 | F4: Excise, Taxation & Narcotics Control Dept - Punjab | G4: 44553 | H4: PB-SC-2105528 | I4: Heavy transport vehicle (HTV) | J4: 10-wheeler truck | K4: Hino 500 FM | L4: 2021 | M4: JH56174991K | N4: E13C-930851 | O4: Green | P4: Active | Q4: RTA-PB/67937/2021 | R4: 46644 | S4: =IF(R4<TODAY(),"Expired",IF(R4-TODAY()<=30,"Expiring soon","Valid")) -> Valid | T4: MVE-FC-619689 | U4: 46315 | V4: =IF(U4<TODAY(),"Expired",IF(U4-TODAY()<=30,"Expiring soon","Valid")) -> Expiring soon | W4: 46568 | X4: =IF(W4<TODAY(),"Expired",IF(W4-TODAY()<=30,"Expiring soon","Valid")) -> Valid
A5: VEH-003 | B5: TRN-001 - Khan Goods Transport Co | C5: Owned by transporter | D5: Khan Goods Transport Co / 17301-5567812-9 (CNIC) | E5: JLM-4312 | F5: Excise, Taxation & Narcotics Control Dept - Punjab | G5: 45021 | H5: PB-SC-3678756 | I5: Heavy transport vehicle (HTV) | J5: 10-wheeler truck | K5: Isuzu FVZ 34 | L5: 2023 | M5: JH48562297K | N5: E13C-365386 | O5: Yellow | P5: Active | Q5: RTA-PB/60163/2023 | R5: 46531 | S5: =IF(R5<TODAY(),"Expired",IF(R5-TODAY()<=30,"Expiring soon","Valid")) -> Valid | T5: MVE-FC-756344 | U5: 46280 | V5: =IF(U5<TODAY(),"Expired",IF(U5-TODAY()<=30,"Expiring soon","Valid")) -> Expired | W5: 46568 | X5: =IF(W5<TODAY(),"Expired",IF(W5-TODAY()<=30,"Expiring soon","Valid")) -> Valid
A6: VEH-004 | B6: TRN-001 - Khan Goods Transport Co | C6: Owned by transporter | D6: Khan Goods Transport Co / 17301-5567812-9 (CNIC) | E6: LES-3434 | F6: Excise, Taxation & Narcotics Control Dept - Punjab | G6: 44718 | H6: PB-SC-9180727 | I6: Light/medium goods vehicle (LTV) | J6: 6-wheeler truck | K6: Isuzu NPR | L6: 2022 | M6: JH14939185K | N6: E13C-428917 | O6: Red | P6: Active | Q6: RTA-PB/69797/2022 | R6: 46265 | S6: =IF(R6<TODAY(),"Expired",IF(R6-TODAY()<=30,"Expiring soon","Valid")) -> Expired | T6: MVE-FC-931913 | U6: 46553 | V6: =IF(U6<TODAY(),"Expired",IF(U6-TODAY()<=30,"Expiring soon","Valid")) -> Valid | W6: 46568 | X6: =IF(W6<TODAY(),"Expired",IF(W6-TODAY()<=30,"Expiring soon","Valid")) -> Valid
A7: VEH-005 | B7: TRN-001 - Khan Goods Transport Co | C7: Owned by transporter | D7: Khan Goods Transport Co / 17301-5567812-9 (CNIC) | E7: LEA-4610 | F7: Excise, Taxation & Narcotics Control Dept - Punjab | G7: 43664 | H7: PB-SC-3099075 | I7: Heavy transport vehicle (HTV) | J7: 22-wheeler trailer | K7: Hino 700 SH | L7: 2019 | M7: JH91584530K | N7: E13C-512053 | O7: Yellow | P7: Active | Q7: RTA-PB/67161/2019 | R7: 46488 | S7: =IF(R7<TODAY(),"Expired",IF(R7-TODAY()<=30,"Expiring soon","Valid")) -> Valid | T7: MVE-FC-670914 | U7: 46487 | V7: =IF(U7<TODAY(),"Expired",IF(U7-TODAY()<=30,"Expiring soon","Valid")) -> Valid | W7: 46203 | X7: =IF(W7<TODAY(),"Expired",IF(W7-TODAY()<=30,"Expiring soon","Valid")) -> Expired
A8: VEH-006 | B8: TRN-001 - Khan Goods Transport Co | C8: Attached (owner-driver) | D8: Owner-operator Munir Ahmad / 17301-5567812-9 (CNIC) | E8: MNB-7132 | F8: Excise, Taxation & Narcotics Control Dept - Punjab | G8: 43572 | H8: PB-SC-4155290 | I8: Heavy transport vehicle (HTV) | J8: 10-wheeler truck | K8: Hino 500 FM | L8: 2019 | M8: JH39753985K | N8: E13C-452288 | O8: Green | P8: Active | Q8: RTA-PB/88980/2019 | R8: 46307 | S8: =IF(R8<TODAY(),"Expired",IF(R8-TODAY()<=30,"Expiring soon","Valid")) -> Expiring soon | T8: MVE-FC-199966 | U8: 46642 | V8: =IF(U8<TODAY(),"Expired",IF(U8-TODAY()<=30,"Expiring soon","Valid")) -> Valid | W8: 46568 | X8: =IF(W8<TODAY(),"Expired",IF(W8-TODAY()<=30,"Expiring soon","Valid")) -> Valid
A9: VEH-007 | B9: TRN-001 - Khan Goods Transport Co | C9: Owned by transporter | D9: Khan Goods Transport Co / 17301-5567812-9 (CNIC) | E9: LES-4620 | F9: Excise, Taxation & Narcotics Control Dept - Punjab | G9: 44778 | H9: PB-SC-5113960 | I9: Heavy transport vehicle (HTV) | J9: 10-wheeler truck | K9: Isuzu FVZ 34 | L9: 2022 | M9: JH63362432K | N9: E13C-224015 | O9: Yellow | P9: Active | Q9: RTA-PB/89610/2022 | R9: 46421 | S9: =IF(R9<TODAY(),"Expired",IF(R9-TODAY()<=30,"Expiring soon","Valid")) -> Valid | T9: MVE-FC-901517 | U9: 46637 | V9: =IF(U9<TODAY(),"Expired",IF(U9-TODAY()<=30,"Expiring soon","Valid")) -> Valid | W9: 46568 | X9: =IF(W9<TODAY(),"Expired",IF(W9-TODAY()<=30,"Expiring soon","Valid")) -> Valid
A10: VEH-008 | B10: TRN-002 - Al-Madina Logistics (Pvt) Ltd | C10: Owned by transporter | D10: Al-Madina Logistics (Pvt) Ltd / 5567123-4 | E10: JLM-7774 | F10: Excise, Taxation & Narcotics Control Dept - Punjab | G10: 44579 | H10: PB-SC-3082386 | I10: Light/medium goods vehicle (LTV) | J10: 6-wheeler truck | K10: Isuzu NPR | L10: 2022 | M10: JH76703399K | N10: E13C-540424 | O10: Green | P10: Active | Q10: RTA-PB/31424/2022 | R10: 46478 | S10: =IF(R10<TODAY(),"Expired",IF(R10-TODAY()<=30,"Expiring soon","Valid")) -> Valid | T10: MVE-FC-893878 | U10: 46449 | V10: =IF(U10<TODAY(),"Expired",IF(U10-TODAY()<=30,"Expiring soon","Valid")) -> Valid | W10: 46568 | X10: =IF(W10<TODAY(),"Expired",IF(W10-TODAY()<=30,"Expiring soon","Valid")) -> Valid
A11: VEH-009 | B11: TRN-002 - Al-Madina Logistics (Pvt) Ltd | C11: Owned by transporter | D11: Al-Madina Logistics (Pvt) Ltd / 5567123-4 | E11: LEC-8959 | F11: Excise, Taxation & Narcotics Control Dept - Punjab | G11: 42395 | H11: PB-SC-6732391 | I11: Heavy transport vehicle (HTV) | J11: 22-wheeler trailer | K11: Hino 700 SH | L11: 2016 | M11: JH92990533K | N11: E13C-118897 | O11: Yellow | P11: Active | Q11: RTA-PB/26932/2016 | R11: 46432 | S11: =IF(R11<TODAY(),"Expired",IF(R11-TODAY()<=30,"Expiring soon","Valid")) -> Valid | T11: MVE-FC-971863 | U11: 46280 | V11: =IF(U11<TODAY(),"Expired",IF(U11-TODAY()<=30,"Expiring soon","Valid")) -> Expired | W11: 46568 | X11: =IF(W11<TODAY(),"Expired",IF(W11-TODAY()<=30,"Expiring soon","Valid")) -> Valid
A12: VEH-010 | B12: TRN-002 - Al-Madina Logistics (Pvt) Ltd | C12: Owned by transporter | D12: Al-Madina Logistics (Pvt) Ltd / 5567123-4 | E12: FDA-3369 | F12: Excise, Taxation & Narcotics Control Dept - Punjab | G12: 43648 | H12: PB-SC-7924811 | I12: Heavy transport vehicle (HTV) | J12: 10-wheeler truck | K12: Hino 500 FM | L12: 2019 | M12: JH73063263K | N12: E13C-742669 | O12: Blue | P12: Active | Q12: RTA-PB/12945/2019 | R12: 46452 | S12: =IF(R12<TODAY(),"Expired",IF(R12-TODAY()<=30,"Expiring soon","Valid")) -> Valid | T12: MVE-FC-199275 | U12: 46315 | V12: =IF(U12<TODAY(),"Expired",IF(U12-TODAY()<=30,"Expiring soon","Valid")) -> Expiring soon | W12: 46203 | X12: =IF(W12<TODAY(),"Expired",IF(W12-TODAY()<=30,"Expiring soon","Valid")) -> Expired
A13: VEH-011 | B13: TRN-002 - Al-Madina Logistics (Pvt) Ltd | C13: Owned by transporter | D13: Al-Madina Logistics (Pvt) Ltd / 5567123-4 | E13: LEA-7121 | F13: Excise, Taxation & Narcotics Control Dept - Punjab | G13: 45255 | H13: PB-SC-9934645 | I13: Heavy transport vehicle (HTV) | J13: 10-wheeler truck | K13: Isuzu FVZ 34 | L13: 2023 | M13: JH95886168K | N13: E13C-788396 | O13: Blue | P13: Active | Q13: RTA-PB/32339/2023 | R13: 46265 | S13: =IF(R13<TODAY(),"Expired",IF(R13-TODAY()<=30,"Expiring soon","Valid")) -> Expired | T13: MVE-FC-754899 | U13: 46632 | V13: =IF(U13<TODAY(),"Expired",IF(U13-TODAY()<=30,"Expiring soon","Valid")) -> Valid | W13: 46568 | X13: =IF(W13<TODAY(),"Expired",IF(W13-TODAY()<=30,"Expiring soon","Valid")) -> Valid
A14: VEH-012 | B14: TRN-002 - Al-Madina Logistics (Pvt) Ltd | C14: Attached (owner-driver) | D14: Owner-operator Shaukat Khan / 5567123-4 | E14: LEC-3089 | F14: Excise, Taxation & Narcotics Control Dept - Punjab | G14: 44814 | H14: PB-SC-7526792 | I14: Light/medium goods vehicle (LTV) | J14: 6-wheeler truck | K14: Isuzu NPR | L14: 2022 | M14: JH48047710K | N14: E13C-278763 | O14: Red | P14: Active | Q14: RTA-PB/98693/2022 | R14: 46532 | S14: =IF(R14<TODAY(),"Expired",IF(R14-TODAY()<=30,"Expiring soon","Valid")) -> Valid | T14: MVE-FC-994732 | U14: 46548 | V14: =IF(U14<TODAY(),"Expired",IF(U14-TODAY()<=30,"Expiring soon","Valid")) -> Valid | W14: 46568 | X14: =IF(W14<TODAY(),"Expired",IF(W14-TODAY()<=30,"Expiring soon","Valid")) -> Valid
... A22: VEH-020 | B22: TRN-003 - Punjab Bulk Carriers (AOP) | C22: Owned by transporter | D22: Punjab Bulk Carriers (AOP) / 4098877-2 | E22: TKR-6050 | F22: Excise, Taxation & Narcotics Control Dept - Punjab | G22: 43428 | H22: PB-SC-9894207 | I22: Heavy transport vehicle (HTV) | J22: Bulker 30 MT | K22: FAW J6P + bulker | L22: 2018 | M22: JH49425467K | N22: E13C-538350 | O22: Yellow | P22: Inactive | Q22: RTA-PB/97758/2018 | R22: 46649 | S22: =IF(R22<TODAY(),"Expired",IF(R22-TODAY()<=30,"Expiring soon","Valid")) -> Valid | T22: MVE-FC-421995 | U22: 46559 | V22: =IF(U22<TODAY(),"Expired",IF(U22-TODAY()<=30,"Expiring soon","Valid")) -> Valid | W22: 46203 | X22: =IF(W22<TODAY(),"Expired",IF(W22-TODAY()<=30,"Expiring soon","Valid")) -> Expired

Sheet T07
A1: SECTION 1 - EMPLOYEE IDENTIFICATION & PERSONAL DETAILS | M1: SECTION 2 - CONTACT, ADDRESS & NEXT OF KIN | V1: SECTION 3 - EMPLOYMENT & POSTING DETAILS | AE1: SECTION 4 - QUALIFICATION, EXPERIENCE & TRAINING | AL1: SECTION 5 - STATUTORY REGISTRATIONS & TAX | AR1: SECTION 6 - COMPENSATION & PAYROLL SETUP | AW1: SECTION 7 - BANK ACCOUNT DETAILS FOR SALARY | AZ1: SECTION 8 - LEAVE, ATTENDANCE & WORKING CALENDAR | BG1: SECTION 9 - DRIVER DETAILS - LICENCE, MEDICAL & STATUTORY VERIFICATION
A2: 1.1 Employee code | B2: 1.2 Registering enterprise / company | C2: 1.3 Employment category (GATING FIELD) | D2: 1.4 Full name | E2: 1.5 Passport number & nationality | F2: 1.6 Date of birth | G2: 1.7 Age (system-derived) | H2: 1.8 Gender | I2: 1.9 Marital status | J2: 1.10 Religion | K2: 1.11 Blood group | L2: 1.12 Photograph | M2: 2.1 Mobile number | N2: 2.2 Alternate mobile number | O2: 2.3 Present / residential address | P2: 2.4 Permanent address | Q2: 2.5 City / province of residence | R2: 2.6 Emergency contact - name & relation | S2: 2.7 Emergency contact - mobile number | T2: 2.8 Next of kin for benefits & gratuity | U2: 2.9 Dependants (name, relation, date of birth) | V2: 3.1 Date of joining | W2: 3.2 Designation / job title | X2: 3.3 Department / function | Y2: 3.4 Grade / pay scale | Z2: 3.5 Employment status | AA2: 3.6 Probation period (months) & confirmation due date | AB2: 3.7 Contract start date | AC2: 3.8 Contract end date | AD2: 3.9 Contract - status (system-derived) | AE2: 4.1 Highest qualification [Relevant Only] | AF2: 4.2 Degree / certification title & specialisation | AG2: 4.3 Institution & year of completion | AH2: 4.4 Professional licence / registration number | AI2: 4.5 Total years of prior experience | AJ2: 4.6 Previous employer(s) - name, designation & period | AK2: 4.7 Mandatory safety induction completed - date | AL2: 5.1 National Tax Number (NTN) of employee | AM2: 5.2 FBR filer status (Active Taxpayer List) | AN2: 5.3 EOBI registration number | AO2: 5.4 EOBI registration date | AP2: 5.5 Police verification / character certificate number | AQ2: 5.6 COMPLIANCE STATUS (system-derived) | AR2: 6.1 Gross monthly salary (PKR) | AS2: 6.2 Basic salary (PKR) | AT2: 6.3 House rent allowance (PKR) | AU2: 6.4 Income tax deduction method | AV2: 6.5 EOBI contribution - employee & employer share | AW2: 7.1 Bank name | AX2: 7.2 Title of account | AY2: 7.3 Account number | AZ2: 8.1 Annual (earned) leave entitlement - days | BA2: 8.2 Casual leave entitlement - days | BB2: 8.3 Sick leave entitlement - days | BC2: 8.4 Leave year basis | BD2: 8.5 Opening leave balance at registration | BE2: 8.6 Attendance capture method | BF2: 8.7 Overtime approval authority | BG2: 9.1 Is the employee a driver? (GATING FIELD) | BH2: 9.2 Driver dispatch code | BI2: 9.3 Driving licence number | BJ2: 9.4 Licence class / type | BK2: 9.5 Licence - valid until | BL2: 9.6 Licence - status (system-derived) | BM2: 9.7 Driver medical fitness certificate number | BN2: 9.8 Driver medical fitness - valid until | BO2: 9.9 Police verification - valid until | BP2: 9.10 Police verification - status (system-derived) | BQ2: 9.11 DRIVER COMPLIANCE STATUS (system-derived)
A3: EMP-001 | B3: Steelstone Building Materials (Pvt) Ltd | C3: Management | D3: Usman Tariq | E3: Pakistani - Passport DR7375417 | F3: 31317 | G3: =DATEDIF(F3,TODAY(),"Y") -> 41 | H3: Male | I3: Married | J3: Islam | K3: B- | L3: Attached (EMP-001.jpg) | M3: 0312-8186347 | N3: 0309-8201625 | O3: House 286, Street 22, Shadbagh, Lahore | P3: Same as present | Q3: Lahore / Punjab | R3: Nasreen - Mother | S3: 0328-3435246 | T3: Spouse / parent (as per emergency contact) | U3: 2 children - Ayesha (daughter, 2015), Hamza (son, 2018) | V3: 45577 | W3: Chief Executive Officer | X3: Management | Y3: M-1 | Z3: Confirmed | AA3: 3 months - confirmation due Q1 2025 | AB3: N/A | AC3: N/A | AD3: =IF(ISNUMBER(AC3),IF(AC3<TODAY(),"Expired",IF(AC3-TODAY()<=30,"Expiring soon","Active")),"Not applicable") -> Not applicable | AE3: Master's | AF3: MBA (Finance) | AG3: LUMS, 2008 | AH3: N/A | AI3: 17 | AJ3: Lucky Cement - Officer - 3 yrs | AK3: 45593 | AL3: 6301486-2 | AM3: Active (ATL) | AN3: EOBI-908956973 | AO3: 45593 | AP3: Verified - Jan-2024 | AQ3: =IF(AND(LEFT(AP3,8)="Verified",AN3<>"Pending"),"Compliant","Non-compliant") -> Compliant | AR3: 1200000 | AS3: =ROUND(AR3*0.6,0) -> 720000 | AT3: =ROUND(AS3*0.45,0) -> 324000 | AU3: Monthly withholding u/s 149 (annualised) | AV3: Employee 1% / Employer 5% of minimum wage | AW3: MCB Bank Ltd | AX3: Usman Tariq | AY3: 4041-71457664-08 | AZ3: 14 | BA3: 10 | BB3: 8 | BC3: Calendar year (Jan-Dec) | BD3: 4 | BE3: Biometric | BF3: Management head | BG3: No | BH3: N/A | BI3: N/A | BJ3: N/A | BK3: N/A | BL3: Not applicable | BM3: N/A | BN3: N/A | BO3: N/A | BP3: Not applicable | BQ3: Not applicable
A4: EMP-002 | B4: Steelstone Building Materials (Pvt) Ltd | C4: Staff | D4: Kashif Nadeem | E4: Pakistani - no passport | F4: 36164 | G4: =DATEDIF(F4,TODAY(),"Y") -> 27 | H4: Male | I4: Single | J4: Islam | K4: A+ | L4: Attached (EMP-002.jpg) | M4: 0338-2556786 | N4: N/A | O4: House 96, Street 29, Wapda Town, Lahore | P4: Same as present | Q4: Lahore / Punjab | R4: Rukhsana - Wife | S4: 0330-8307093 | T4: Spouse / parent (as per emergency contact) | U4: None | V4: 45582 | W4: General Manager Sales | X4: Sales | Y4: M-2 | Z4: Confirmed | AA4: 3 months - confirmation due Q1 2025 | AB4: N/A | AC4: N/A | AD4: =IF(ISNUMBER(AC4),IF(AC4<TODAY(),"Expired",IF(AC4-TODAY()<=30,"Expiring soon","Active")),"Not applicable") -> Not applicable | AE4: Master's | AF4: MBA (Marketing) | AG4: IBA Karachi, 2010 | AH4: N/A | AI4: 3 | AJ4: Fresh graduate | AK4: 45593 | AL4: 2152554-3 | AM4: Active (ATL) | AN4: EOBI-743336677 | AO4: 45593 | AP4: Verified - Mar-2024 | AQ4: =IF(AND(LEFT(AP4,8)="Verified",AN4<>"Pending"),"Compliant","Non-compliant") -> Compliant | AR4: 650000 | AS4: =ROUND(AR4*0.6,0) -> 390000 | AT4: =ROUND(AS4*0.45,0) -> 175500 | AU4: Monthly withholding u/s 149 (annualised) | AV4: Employee 1% / Employer 5% of minimum wage | AW4: MCB Bank Ltd | AX4: Kashif Nadeem | AY4: 5930-62937464-07 | AZ4: 14 | BA4: 10 | BB4: 8 | BC4: Calendar year (Jan-Dec) | BD4: 10 | BE4: Biometric | BF4: Sales head | BG4: No | BH4: N/A | BI4: N/A | BJ4: N/A | BK4: N/A | BL4: Not applicable | BM4: N/A | BN4: N/A | BO4: N/A | BP4: Not applicable | BQ4: Not applicable
A5: EMP-003 | B5: Steelstone Building Materials (Pvt) Ltd | C5: Staff | D5: Sana Iqbal | E5: Pakistani - no passport | F5: 33271 | G5: =DATEDIF(F5,TODAY(),"Y") -> 35 | H5: Female | I5: Married | J5: Islam | K5: AB+ | L5: Attached (EMP-003.jpg) | M5: 0315-3258285 | N5: N/A | O5: House 101, Street 19, Wapda Town, Lahore | P5: Village Dhok Ratta, Okara | Q5: Mardan / KP | R5: Imran - Husband | S5: 0334-8127740 | T5: Spouse / parent (as per emergency contact) | U5: 2 children - Ayesha (daughter, 2015), Fatima (daughter, 2019) | V5: 45629 | W5: Finance Manager | X5: Finance | Y5: M-3 | Z5: Confirmed | AA5: 3 months - confirmation due Q1 2025 | AB5: N/A | AC5: N/A | AD5: =IF(ISNUMBER(AC5),IF(AC5<TODAY(),"Expired",IF(AC5-TODAY()<=30,"Expiring soon","Active")),"Not applicable") -> Not applicable | AE5: Professional | AF5: ACA (ICAP) | AG5: ICAP, 2014 | AH5: ICAP Member No. 11245 | AI5: 11 | AJ5: Fresh graduate | AK5: 45654 | AL5: 5507669-8 | AM5: Active (ATL) | AN5: EOBI-482440629 | AO5: 45654 | AP5: Verified - May-2024 | AQ5: =IF(AND(LEFT(AP5,8)="Verified",AN5<>"Pending"),"Compliant","Non-compliant") -> Compliant | AR5: 450000 | AS5: =ROUND(AR5*0.6,0) -> 270000 | AT5: =ROUND(AS5*0.45,0) -> 121500 | AU5: Monthly withholding u/s 149 (annualised) | AV5: Employee 1% / Employer 5% of minimum wage | AW5: MCB Bank Ltd | AX5: Sana Iqbal | AY5: 8115-75441881-09 | AZ5: 14 | BA5: 10 | BB5: 8 | BC5: Calendar year (Jan-Dec) | BD5: 11 | BE5: Biometric | BF5: Finance head | BG5: No | BH5: N/A | BI5: N/A | BJ5: N/A | BK5: N/A | BL5: Not applicable | BM5: N/A | BN5: N/A | BO5: N/A | BP5: Not applicable | BQ5: Not applicable
A6: EMP-004 | B6: Steelstone Building Materials (Pvt) Ltd | C6: Staff | D6: Hassan Raza | E6: Pakistani - Passport AB2127181 | F6: 34695 | G6: =DATEDIF(F6,TODAY(),"Y") -> 31 | H6: Male | I6: Single | J6: Islam | K6: A+ | L6: Attached (EMP-004.jpg) | M6: 0319-8827786 | N6: N/A | O6: House 431, Street 9, Township, Lahore | P6: Same as present | Q6: Lahore / Punjab | R6: Rukhsana - Wife | S6: 0321-3907974 | T6: Spouse / parent (as per emergency contact) | U6: None | V6: 45579 | W6: Accountant | X6: Finance | Y6: S-2 | Z6: Confirmed | AA6: 3 months - confirmation due Q1 2025 | AB6: N/A | AC6: N/A | AD6: =IF(ISNUMBER(AC6),IF(AC6<TODAY(),"Expired",IF(AC6-TODAY()<=30,"Expiring soon","Active")),"Not applicable") -> Not applicable | AE6: Bachelor's | AF6: B.Com (Hons) | AG6: Hailey College, 2016 | AH6: N/A | AI6: 8 | AJ6: Lucky Cement - Officer - 3 yrs | AK6: 45593 | AL6: 1494817-0 | AM6: Active (ATL) | AN6: EOBI-184159363 | AO6: 45593 | AP6: Verified - Aug-2024 | AQ6: =IF(AND(LEFT(AP6,8)="Verified",AN6<>"Pending"),"Compliant","Non-compliant") -> Compliant | AR6: 180000 | AS6: =ROUND(AR6*0.6,0) -> 108000 | AT6: =ROUND(AS6*0.45,0) -> 48600 | AU6: Monthly withholding u/s 149 (annualised) | AV6: Employee 1% / Employer 5% of minimum wage | AW6: Habib Bank Ltd | AX6: Hassan Raza | AY6: 5211-82734308-07 | AZ6: 14 | BA6: 10 | BB6: 8 | BC6: Calendar year (Jan-Dec) | BD6: 8 | BE6: Biometric | BF6: Finance head | BG6: No | BH6: N/A | BI6: N/A | BJ6: N/A | BK6: N/A | BL6: Not applicable | BM6: N/A | BN6: N/A | BO6: N/A | BP6: Not applicable | BQ6: Not applicable
A7: EMP-005 | B7: Steelstone Building Materials (Pvt) Ltd | C7: Staff | D7: Mariam Khalid | E7: Pakistani - no passport | F7: 31652 | G7: =DATEDIF(F7,TODAY(),"Y") -> 40 | H7: Female | I7: Married | J7: Islam | K7: B- | L7: Attached (EMP-005.jpg) | M7: 0347-6430310 | N7: 0341-1588893 | O7: House 327, Street 20, Shadbagh, Lahore | P7: Same as present | Q7: Lahore / Punjab | R7: Asad - Husband | S7: 0314-2097256 | T7: Spouse / parent (as per emergency contact) | U7: 2 children - Ahmed (son, 2012), Hamza (son, 2018) | V7: 45636 | W7: Accounts Officer | X7: Finance | Y7: S-3 | Z7: Confirmed | AA7: 3 months - confirmation due Q1 2025 | AB7: N/A | AC7: N/A | AD7: =IF(ISNUMBER(AC7),IF(AC7<TODAY(),"Expired",IF(AC7-TODAY()<=30,"Expiring soon","Active")),"Not applicable") -> Not applicable | AE7: Bachelor's | AF7: BBA (Accounting) | AG7: UCP Lahore, 2020 | AH7: N/A | AI7: 16 | AJ7: Maple Leaf Cement - Executive - 4 yrs | AK7: 45654 | AL7: Not registered | AM7: Non-filer | AN7: EOBI-280119945 | AO7: 45654 | AP7: Verified - Nov-2024 | AQ7: =IF(AND(LEFT(AP7,8)="Verified",AN7<>"Pending"),"Compliant","Non-compliant") -> Compliant | AR7: 120000 | AS7: =ROUND(AR7*0.6,0) -> 72000 | AT7: =ROUND(AS7*0.45,0) -> 32400 | AU7: Monthly withholding u/s 149 (annualised) | AV7: Employee 1% / Employer 5% of minimum wage | AW7: Habib Bank Ltd | AX7: Mariam Khalid | AY7: 2128-14696266-01 | AZ7: 14 | BA7: 10 | BB7: 8 | BC7: Calendar year (Jan-Dec) | BD7: 11 | BE7: Biometric | BF7: Finance head | BG7: No | BH7: N/A | BI7: N/A | BJ7: N/A | BK7: N/A | BL7: Not applicable | BM7: N/A | BN7: N/A | BO7: N/A | BP7: Not applicable | BQ7: Not applicable
A8: EMP-006 | B8: Steelstone Building Materials (Pvt) Ltd | C8: Staff | D8: Abdul Rehman | E8: Pakistani - no passport | F8: 29137 | G8: =DATEDIF(F8,TODAY(),"Y") -> 46 | H8: Male | I8: Married | J8: Islam | K8: O+ | L8: Attached (EMP-006.jpg) | M8: 0347-1104417 | N8: N/A | O8: House 448, Street 7, Wapda Town, Lahore | P8: Village Mouza Kot, Okara | Q8: Lahore / Punjab | R8: Shazia - Mother | S8: 0318-8321405 | T8: Spouse / parent (as per emergency contact) | U8: 2 children - Ahmed (son, 2012), Hamza (son, 2018) | V8: 45635 | W8: Cashier | X8: Finance | Y8: S-4 | Z8: Confirmed | AA8: 3 months - confirmation due Q1 2025 | AB8: N/A | AC8: N/A | AD8: =IF(ISNUMBER(AC8),IF(AC8<TODAY(),"Expired",IF(AC8-TODAY()<=30,"Expiring soon","Active")),"Not applicable") -> Not applicable | AE8: Intermediate | AF8: I.Com | AG8: Govt College Lahore, 2012 | AH8: N/A | AI8: 23 | AJ8: Maple Leaf Cement - Executive - 4 yrs | AK8: 45654 | AL8: 8933767-8 | AM8: Active (ATL) | AN8: EOBI-710379522 | AO8: 45654 | AP8: Verified - Jan-2024 | AQ8: =IF(AND(LEFT(AP8,8)="Verified",AN8<>"Pending"),"Compliant","Non-compliant") -> Compliant | AR8: 85000 | AS8: =ROUND(AR8*0.6,0) -> 51000 | AT8: =ROUND(AS8*0.45,0) -> 22950 | AU8: Monthly withholding u/s 149 (below taxable limit) | AV8: Employee 1% / Employer 5% of minimum wage | AW8: Habib Bank Ltd | AX8: Abdul Rehman | AY8: 8800-83778971-08 | AZ8: 14 | BA8: 10 | BB8: 8 | BC8: Calendar year (Jan-Dec) | BD8: 10 | BE8: Biometric | BF8: Finance head | BG8: No | BH8: N/A | BI8: N/A | BJ8: N/A | BK8: N/A | BL8: Not applicable | BM8: N/A | BN8: N/A | BO8: N/A | BP8: Not applicable | BQ8: Not applicable
A9: EMP-007 | B9: Steelstone Building Materials (Pvt) Ltd | C9: Staff | D9: Omer Farooq | E9: Pakistani - Passport BK7408931 | F9: 34084 | G9: =DATEDIF(F9,TODAY(),"Y") -> 33 | H9: Male | I9: Married | J9: Islam | K9: A+ | L9: Attached (EMP-007.jpg) | M9: 0346-8343975 | N9: N/A | O9: House 211, Street 24, Bund Road, Lahore | P9: Same as present | Q9: Lahore / Punjab | R9: Rukhsana - Wife | S9: 0300-6197912 | T9: Spouse / parent (as per emergency contact) | U9: 2 children - Ayesha (daughter, 2015), Fatima (daughter, 2019) | V9: 45650 | W9: Sales Manager | X9: Sales | Y9: M-3 | Z9: Confirmed | AA9: 3 months - confirmation due Q1 2025 | AB9: N/A | AC9: N/A | AD9: =IF(ISNUMBER(AC9),IF(AC9<TODAY(),"Expired",IF(AC9-TODAY()<=30,"Expiring soon","Active")),"Not applicable") -> Not applicable | AE9: Bachelor's | AF9: BBA (Marketing) | AG9: PU Lahore, 2011 | AH9: N/A | AI9: 9 | AJ9: Fresh graduate | AK9: 45654 | AL9: 8320810-2 | AM9: Active (ATL) | AN9: EOBI-606224414 | AO9: 45654 | AP9: Verified - Mar-2024 | AQ9: =IF(AND(LEFT(AP9,8)="Verified",AN9<>"Pending"),"Compliant","Non-compliant") -> Compliant | AR9: 300000 | AS9: =ROUND(AR9*0.6,0) -> 180000 | AT9: =ROUND(AS9*0.45,0) -> 81000 | AU9: Monthly withholding u/s 149 (annualised) | AV9: Employee 1% / Employer 5% of minimum wage | AW9: Habib Bank Ltd | AX9: Omer Farooq | AY9: 4474-58439197-07 | AZ9: 14 | BA9: 10 | BB9: 8 | BC9: Calendar year (Jan-Dec) | BD9: 8 | BE9: Biometric | BF9: Sales head | BG9: No | BH9: N/A | BI9: N/A | BJ9: N/A | BK9: N/A | BL9: Not applicable | BM9: N/A | BN9: N/A | BO9: N/A | BP9: Not applicable | BQ9: Not applicable
A10: EMP-008 | B10: Steelstone Building Materials (Pvt) Ltd | C10: Staff | D10: Ali Hamza | E10: Pakistani - no passport | F10: 32587 | G10: =DATEDIF(F10,TODAY(),"Y") -> 37 | H10: Male | I10: Married | J10: Islam | K10: B- | L10: Attached (EMP-008.jpg) | M10: 0312-6526028 | N10: N/A | O10: House 249, Street 29, Shadbagh, Lahore | P10: Same as present | Q10: Lahore / Punjab | R10: Rukhsana - Mother | S10: 0326-6139730 | T10: Spouse / parent (as per emergency contact) | U10: 2 children - Ahmed (son, 2012), Hamza (son, 2018) | V10: 45781 | W10: Sales Officer | X10: Sales | Y10: S-3 | Z10: Confirmed | AA10: 3 months - confirmation due within 2025 | AB10: N/A | AC10: N/A | AD10: =IF(ISNUMBER(AC10),IF(AC10<TODAY(),"Expired",IF(AC10-TODAY()<=30,"Expiring soon","Active")),"Not applicable") -> Not applicable | AE10: Bachelor's | AF10: BBA | AG10: Superior University, 2019 | AH10: N/A | AI10: 13 | AJ10: Maple Leaf Cement - Executive - 4 yrs | AK10: 45805 | AL10: 6705591-8 | AM10: Active (ATL) | AN10: EOBI-679690030 | AO10: 45805 | AP10: Verified - May-2025 | AQ10: =IF(AND(LEFT(AP10,8)="Verified",AN10<>"Pending"),"Compliant","Non-compliant") -> Compliant | AR10: 110000 | AS10: =ROUND(AR10*0.6,0) -> 66000 | AT10: =ROUND(AS10*0.45,0) -> 29700 | AU10: Monthly withholding u/s 149 (annualised) | AV10: Employee 1% / Employer 5% of minimum wage | AW10: Habib Bank Ltd | AX10: Ali Hamza | AY10: 4125-45835741-02 | AZ10: 14 | BA10: 10 | BB10: 8 | BC10: Calendar year (Jan-Dec) | BD10: 1 | BE10: Biometric | BF10: Sales head | BG10: No | BH10: N/A | BI10: N/A | BJ10: N/A | BK10: N/A | BL10: Not applicable | BM10: N/A | BN10: N/A | BO10: N/A | BP10: Not applicable | BQ10: Not applicable
A11: EMP-009 | B11: Steelstone Building Materials (Pvt) Ltd | C11: Staff | D11: Zeeshan Anwar | E11: Pakistani - no passport | F11: 32266 | G11: =DATEDIF(F11,TODAY(),"Y") -> 38 | H11: Male | I11: Married | J11: Islam | K11: AB+ | L11: Attached (EMP-009.jpg) | M11: 0324-1895791 | N11: 0342-3730534 | O11: House 55, Street 7, Shadbagh, Lahore | P11: Village Chak 45, Mardan | Q11: Sheikhupura / Punjab | R11: Shazia - Mother | S11: 0328-7159283 | T11: Spouse / parent (as per emergency contact) | U11: 2 children - Ahmed (son, 2012), Fatima (daughter, 2019) | V11: 45586 | W11: Sales Officer | X11: Sales | Y11: S-3 | Z11: Contract | AA11: 3 months - confirmation due Q1 2025 | AB11: 45566 | AC11: 46568 | AD11: =IF(ISNUMBER(AC11),IF(AC11<TODAY(),"Expired",IF(AC11-TODAY()<=30,"Expiring soon","Active")),"Not applicable") -> Active | AE11: Bachelor's | AF11: B.Sc Civil Technology | AG11: UET Lahore, 2021 | AH11: N/A | AI11: 14 | AJ11: DG Khan Cement - Officer - 2 yrs | AK11: 45593 | AL11: 9705099-2 | AM11: Active (ATL) | AN11: EOBI-995343231 | AO11: 45593 | AP11: Verified - Aug-2024 | AQ11: =IF(AND(LEFT(AP11,8)="Verified",AN11<>"Pending"),"Compliant","Non-compliant") -> Compliant | AR11: 110000 | AS11: =ROUND(AR11*0.6,0) -> 66000 | AT11: =ROUND(AS11*0.45,0) -> 29700 | AU11: Monthly withholding u/s 149 (annualised) | AV11: Employee 1% / Employer 5% of minimum wage | AW11: Meezan Bank Ltd | AX11: Zeeshan Anwar | AY11: 1928-37694832-08 | AZ11: 14 | BA11: 10 | BB11: 8 | BC11: Calendar year (Jan-Dec) | BD11: 11 | BE11: Biometric | BF11: Sales head | BG11: No | BH11: N/A | BI11: N/A | BJ11: N/A | BK11: N/A | BL11: Not applicable | BM11: N/A | BN11: N/A | BO11: N/A | BP11: Not applicable | BQ11: Not applicable
A12: EMP-010 | B12: Steelstone Building Materials (Pvt) Ltd | C12: Staff | D12: Naeem Akhtar | E12: Pakistani - Passport AB5811268 | F12: 33152 | G12: =DATEDIF(F12,TODAY(),"Y") -> 35 | H12: Male | I12: Married | J12: Islam | K12: B- | L12: Attached (EMP-010.jpg) | M12: 0335-9559454 | N12: N/A | O12: House 138, Street 1, Bund Road, Lahore | P12: Same as present | Q12: Lahore / Punjab | R12: Nasreen - Mother | S12: 0336-1409493 | T12: Spouse / parent (as per emergency contact) | U12: 2 children - Ayesha (daughter, 2015), Fatima (daughter, 2019) | V12: 45924 | W12: Logistics Manager | X12: Logistics | Y12: M-3 | Z12: Confirmed | AA12: 3 months - confirmation due within 2025 | AB12: N/A | AC12: N/A | AD12: =IF(ISNUMBER(AC12),IF(AC12<TODAY(),"Expired",IF(AC12-TODAY()<=30,"Expiring soon","Active")),"Not applicable") -> Not applicable | AE12: Master's | AF12: MS Supply Chain | AG12: NUST, 2013 | AH12: N/A | AI12: 12 | AJ12: DG Khan Cement - Officer - 2 yrs | AK12: 45928 | AL12: Not registered | AM12: Non-filer | AN12: EOBI-610334771 | AO12: 45928 | AP12: Verified - Nov-2025 | AQ12: =IF(AND(LEFT(AP12,8)="Verified",AN12<>"Pending"),"Compliant","Non-compliant") -> Compliant | AR12: 250000 | AS12: =ROUND(AR12*0.6,0) -> 150000 | AT12: =ROUND(AS12*0.45,0) -> 67500 | AU12: Monthly withholding u/s 149 (annualised) | AV12: Employee 1% / Employer 5% of minimum wage | AW12: Meezan Bank Ltd | AX12: Naeem Akhtar | AY12: 6670-61072145-04 | AZ12: 14 | BA12: 10 | BB12: 8 | BC12: Calendar year (Jan-Dec) | BD12: 0 | BE12: Biometric | BF12: Logistics head | BG12: No | BH12: N/A | BI12: N/A | BJ12: N/A | BK12: N/A | BL12: Not applicable | BM12: N/A | BN12: N/A | BO12: N/A | BP12: Not applicable | BQ12: Not applicable
A13: EMP-011 | B13: Steelstone Building Materials (Pvt) Ltd | C13: Staff | D13: Irfan Ali | E13: Pakistani - no passport | F13: 34312 | G13: =DATEDIF(F13,TODAY(),"Y") -> 32 | H13: Male | I13: Married | J13: Islam | K13: B- | L13: Attached (EMP-011.jpg) | M13: 0345-6600808 | N13: N/A | O13: House 90, Street 8, Shadbagh, Lahore | P13: Same as present | Q13: Lahore / Punjab | R13: Nasreen - Wife | S13: 0327-8563322 | T13: Spouse / parent (as per emergency contact) | U13: 2 children - Ahmed (son, 2012), Hamza (son, 2018) | V13: 45644 | W13: Dispatch Officer | X13: Logistics | Y13: S-4 | Z13: Confirmed | AA13: 3 months - confirmation due Q1 2025 | AB13: N/A | AC13: N/A | AD13: =IF(ISNUMBER(AC13),IF(AC13<TODAY(),"Expired",IF(AC13-TODAY()<=30,"Expiring soon","Active")),"Not applicable") -> Not applicable | AE13: Bachelor's | AF13: BA | AG13: PU Lahore, 2015 | AH13: N/A | AI13: 9 | AJ13: Maple Leaf Cement - Executive - 4 yrs | AK13: 45654 | AL13: 3856465-2 | AM13: Active (ATL) | AN13: EOBI-165885197 | AO13: 45654 | AP13: Verified - Jan-2024 | AQ13: =IF(AND(LEFT(AP13,8)="Verified",AN13<>"Pending"),"Compliant","Non-compliant") -> Compliant | AR13: 90000 | AS13: =ROUND(AR13*0.6,0) -> 54000 | AT13: =ROUND(AS13*0.45,0) -> 24300 | AU13: Monthly withholding u/s 149 (below taxable limit) | AV13: Employee 1% / Employer 5% of minimum wage | AW13: Habib Bank Ltd | AX13: Irfan Ali | AY13: 4889-67161026-05 | AZ13: 14 | BA13: 10 | BB13: 8 | BC13: Calendar year (Jan-Dec) | BD13: 8 | BE13: Biometric | BF13: Logistics head | BG13: No | BH13: N/A | BI13: N/A | BJ13: N/A | BK13: N/A | BL13: Not applicable | BM13: N/A | BN13: N/A | BO13: N/A | BP13: Not applicable | BQ13: Not applicable
A14: EMP-012 | B14: Steelstone Building Materials (Pvt) Ltd | C14: Staff | D14: Shakeel Ahmed | E14: Pakistani - no passport | F14: 33935 | G14: =DATEDIF(F14,TODAY(),"Y") -> 33 | H14: Male | I14: Married | J14: Islam | K14: O+ | L14: Attached (EMP-012.jpg) | M14: 0349-6837070 | N14: N/A | O14: House 183, Street 19, Samanabad, Lahore | P14: Village Chak 45, Okara | Q14: Mardan / KP | R14: Rukhsana - Wife | S14: 0332-3449947 | T14: Spouse / parent (as per emergency contact) | U14: 2 children - Ahmed (son, 2012), Fatima (daughter, 2019) | V14: 45817 | W14: Warehouse In-charge | X14: Warehouse | Y14: S-3 | Z14: Confirmed | AA14: 3 months - confirmation due within 2025 | AB14: N/A | AC14: N/A | AD14: =IF(ISNUMBER(AC14),IF(AC14<TODAY(),"Expired",IF(AC14-TODAY()<=30,"Expiring soon","Active")),"Not applicable") -> Not applicable | AE14: Intermediate | AF14: FA | AG14: BISE Lahore, 2009 | AH14: N/A | AI14: 10 | AJ14: DG Khan Cement - Officer - 2 yrs | AK14: 45836 | AL14: 7801280-0 | AM14: Active (ATL) | AN14: EOBI-842560846 | AO14: 45836 | AP14: Verified - Mar-2025 | AQ14: =IF(AND(LEFT(AP14,8)="Verified",AN14<>"Pending"),"Compliant","Non-compliant") -> Compliant | AR14: 95000 | AS14: =ROUND(AR14*0.6,0) -> 57000 | AT14: =ROUND(AS14*0.45,0) -> 25650 | AU14: Monthly withholding u/s 149 (below taxable limit) | AV14: Employee 1% / Employer 5% of minimum wage | AW14: MCB Bank Ltd | AX14: Shakeel Ahmed | AY14: 7915-95834267-01 | AZ14: 14 | BA14: 10 | BB14: 8 | BC14: Calendar year (Jan-Dec) | BD14: 1 | BE14: Biometric | BF14: Warehouse head | BG14: No | BH14: N/A | BI14: N/A | BJ14: N/A | BK14: N/A | BL14: Not applicable | BM14: N/A | BN14: N/A | BO14: N/A | BP14: Not applicable | BQ14: Not applicable
A15: EMP-013 | B15: Steelstone Building Materials (Pvt) Ltd | C15: Staff | D15: Babar Hussain | E15: Pakistani - Passport BK3488707 | F15: 36731 | G15: =DATEDIF(F15,TODAY(),"Y") -> 26 | H15: Male | I15: Married | J15: Islam | K15: B- | L15: Attached (EMP-013.jpg) | M15: 0301-6550767 | N15: 0330-3587710 | O15: House 183, Street 24, Wapda Town, Lahore | P15: Same as present | Q15: Lahore / Punjab | R15: Nasreen - Wife | S15: 0349-6565210 | T15: Spouse / parent (as per emergency contact) | U15: None | V15: 45586 | W15: Storekeeper | X15: Warehouse | Y15: S-5 | Z15: Confirmed | AA15: 3 months - confirmation due Q1 2025 | AB15: N/A | AC15: N/A | AD15: =IF(ISNUMBER(AC15),IF(AC15<TODAY(),"Expired",IF(AC15-TODAY()<=30,"Expiring soon","Active")),"Not applicable") -> Not applicable | AE15: Matric | AF15: SSC | AG15: BISE Lahore, 2011 | AH15: N/A | AI15: 2 | AJ15: Lucky Cement - Officer - 3 yrs | AK15: 45593 | AL15: 9003000-1 | AM15: Active (ATL) | AN15: EOBI-409497664 | AO15: 45593 | AP15: Verified - May-2024 | AQ15: =IF(AND(LEFT(AP15,8)="Verified",AN15<>"Pending"),"Compliant","Non-compliant") -> Compliant | AR15: 60000 | AS15: =ROUND(AR15*0.6,0) -> 36000 | AT15: =ROUND(AS15*0.45,0) -> 16200 | AU15: Monthly withholding u/s 149 (below taxable limit) | AV15: Employee 1% / Employer 5% of minimum wage | AW15: MCB Bank Ltd | AX15: Babar Hussain | AY15: 4789-51762875-09 | AZ15: 14 | BA15: 10 | BB15: 8 | BC15: Calendar year (Jan-Dec) | BD15: 7 | BE15: Biometric | BF15: Warehouse head | BG15: No | BH15: N/A | BI15: N/A | BJ15: N/A | BK15: N/A | BL15: Not applicable | BM15: N/A | BN15: N/A | BO15: N/A | BP15: Not applicable | BQ15: Not applicable
A16: EMP-014 | B16: Steelstone Building Materials (Pvt) Ltd | C16: Staff | D16: Hina Aslam | E16: Pakistani - no passport | F16: 34005 | G16: =DATEDIF(F16,TODAY(),"Y") -> 33 | H16: Female | I16: Married | J16: Islam | K16: B+ | L16: Attached (EMP-014.jpg) | M16: 0343-9962805 | N16: N/A | O16: House 244, Street 4, Shadbagh, Lahore | P16: Same as present | Q16: Lahore / Punjab | R16: Asad - Husband | S16: 0305-8369126 | T16: Spouse / parent (as per emergency contact) | U16: 2 children - Ahmed (son, 2012), Hamza (son, 2018) | V16: 45840 | W16: HR & Admin Officer | X16: HR & Admin | Y16: S-2 | Z16: Confirmed | AA16: 3 months - confirmation due within 2025 | AB16: N/A | AC16: N/A | AD16: =IF(ISNUMBER(AC16),IF(AC16<TODAY(),"Expired",IF(AC16-TODAY()<=30,"Expiring soon","Active")),"Not applicable") -> Not applicable | AE16: Master's | AF16: MBA (HRM) | AG16: UMT Lahore, 2017 | AH16: N/A | AI16: 9 | AJ16: DG Khan Cement - Officer - 2 yrs | AK16: 45866 | AL16: 4921471-1 | AM16: Active (ATL) | AN16: EOBI-849528081 | AO16: 45866 | AP16: Verified - Aug-2025 | AQ16: =IF(AND(LEFT(AP16,8)="Verified",AN16<>"Pending"),"Compliant","Non-compliant") -> Compliant | AR16: 140000 | AS16: =ROUND(AR16*0.6,0) -> 84000 | AT16: =ROUND(AS16*0.45,0) -> 37800 | AU16: Monthly withholding u/s 149 (annualised) | AV16: Employee 1% / Employer 5% of minimum wage | AW16: Meezan Bank Ltd | AX16: Hina Aslam | AY16: 9214-74799196-09 | AZ16: 14 | BA16: 10 | BB16: 8 | BC16: Calendar year (Jan-Dec) | BD16: 4 | BE16: Biometric | BF16: HR & Admin head | BG16: No | BH16: N/A | BI16: N/A | BJ16: N/A | BK16: N/A | BL16: Not applicable | BM16: N/A | BN16: N/A | BO16: N/A | BP16: Not applicable | BQ16: Not applicable
A17: EMP-015 | B17: Steelstone Building Materials (Pvt) Ltd | C17: Staff | D17: Fahad Saleem | E17: Pakistani - no passport | F17: 35539 | G17: =DATEDIF(F17,TODAY(),"Y") -> 29 | H17: Male | I17: Single | J17: Islam | K17: A+ | L17: Attached (EMP-015.jpg) | M17: 0300-1526664 | N17: N/A | O17: House 233, Street 4, Township, Lahore | P17: Village Mouza Kot, Mardan | Q17: Lahore / Punjab | R17: Rukhsana - Mother | S17: 0336-8765253 | T17: Spouse / parent (as per emergency contact) | U17: None | V17: 45632 | W17: IT Officer | X17: IT | Y17: S-2 | Z17: Contract | AA17: 3 months - confirmation due Q1 2025 | AB17: 45627 | AC17: 46448 | AD17: =IF(ISNUMBER(AC17),IF(AC17<TODAY(),"Expired",IF(AC17-TODAY()<=30,"Expiring soon","Active")),"Not applicable") -> Active | AE17: Bachelor's | AF17: BS Computer Science | AG17: FAST Lahore, 2018 | AH17: N/A | AI17: 5 | AJ17: DG Khan Cement - Officer - 2 yrs | AK17: 45654 | AL17: Not registered | AM17: Non-filer | AN17: EOBI-463790851 | AO17: 45654 | AP17: Verified - Nov-2024 | AQ17: =IF(AND(LEFT(AP17,8)="Verified",AN17<>"Pending"),"Compliant","Non-compliant") -> Compliant | AR17: 150000 | AS17: =ROUND(AR17*0.6,0) -> 90000 | AT17: =ROUND(AS17*0.45,0) -> 40500 | AU17: Monthly withholding u/s 149 (annualised) | AV17: Employee 1% / Employer 5% of minimum wage | AW17: Habib Bank Ltd | AX17: Fahad Saleem | AY17: 4660-59580478-08 | AZ17: 14 | BA17: 10 | BB17: 8 | BC17: Calendar year (Jan-Dec) | BD17: 11 | BE17: Biometric | BF17: IT head | BG17: No | BH17: N/A | BI17: N/A | BJ17: N/A | BK17: N/A | BL17: Not applicable | BM17: N/A | BN17: N/A | BO17: N/A | BP17: Not applicable | BQ17: Not applicable
A18: EMP-016 | B18: Steelstone Building Materials (Pvt) Ltd | C18: Staff | D18: Ghulam Mustafa | E18: Pakistani - Passport DR7654514 | F18: 31753 | G18: =DATEDIF(F18,TODAY(),"Y") -> 39 | H18: Male | I18: Married | J18: Islam | K18: O- | L18: Attached (EMP-016.jpg) | M18: 0347-6110003 | N18: N/A | O18: House 292, Street 27, Township, Lahore | P18: Same as present | Q18: Lahore / Punjab | R18: Nasreen - Wife | S18: 0337-7227018 | T18: Spouse / parent (as per emergency contact) | U18: 2 children - Ayesha (daughter, 2015), Hamza (son, 2018) | V18: 45786 | W18: Security Supervisor | X18: HR & Admin | Y18: S-5 | Z18: Confirmed | AA18: 3 months - confirmation due within 2025 | AB18: N/A | AC18: N/A | AD18: =IF(ISNUMBER(AC18),IF(AC18<TODAY(),"Expired",IF(AC18-TODAY()<=30,"Expiring soon","Active")),"Not applicable") -> Not applicable | AE18: Matric | AF18: SSC + Ex-Army | AG18: BISE Rawalpindi, 1998 | AH18: N/A | AI18: 16 | AJ18: Fresh graduate | AK18: 45805 | AL18: 6045415-0 | AM18: Active (ATL) | AN18: EOBI-596396425 | AO18: 45805 | AP18: Verified - Jan-2025 | AQ18: =IF(AND(LEFT(AP18,8)="Verified",AN18<>"Pending"),"Compliant","Non-compliant") -> Compliant | AR18: 55000 | AS18: =ROUND(AR18*0.6,0) -> 33000 | AT18: =ROUND(AS18*0.45,0) -> 14850 | AU18: Monthly withholding u/s 149 (below taxable limit) | AV18: Employee 1% / Employer 5% of minimum wage | AW18: MCB Bank Ltd | AX18: Ghulam Mustafa | AY18: 1102-95724997-07 | AZ18: 14 | BA18: 10 | BB18: 8 | BC18: Calendar year (Jan-Dec) | BD18: 3 | BE18: Biometric | BF18: HR & Admin head | BG18: No | BH18: N/A | BI18: N/A | BJ18: N/A | BK18: N/A | BL18: Not applicable | BM18: N/A | BN18: N/A | BO18: N/A | BP18: Not applicable | BQ18: Not applicable
A19: EMP-017 | B19: Steelstone Building Materials (Pvt) Ltd | C19: Staff | D19: Rashid Mehmood | E19: Pakistani - no passport | F19: 36496 | G19: =DATEDIF(F19,TODAY(),"Y") -> 26 | H19: Male | I19: Married | J19: Islam | K19: O+ | L19: Attached (EMP-017.jpg) | M19: 0330-4708318 | N19: 0303-4326104 | O19: House 142, Street 12, Samanabad, Lahore | P19: Same as present | Q19: Lahore / Punjab | R19: Nasreen - Wife | S19: 0348-1470398 | T19: Spouse / parent (as per emergency contact) | U19: None | V19: 45639 | W19: Office Assistant | X19: HR & Admin | Y19: S-6 | Z19: Resigned - notice period | AA19: 3 months - confirmation due Q1 2025 | AB19: 45627 | AC19: 46285 | AD19: =IF(ISNUMBER(AC19),IF(AC19<TODAY(),"Expired",IF(AC19-TODAY()<=30,"Expiring soon","Active")),"Not applicable") -> Expired | AE19: Matric | AF19: SSC | AG19: BISE Lahore, 2014 | AH19: N/A | AI19: 3 | AJ19: DG Khan Cement - Officer - 2 yrs | AK19: 45654 | AL19: 6709479-1 | AM19: Active (ATL) | AN19: EOBI-205352749 | AO19: 45654 | AP19: Verified - Mar-2024 | AQ19: =IF(AND(LEFT(AP19,8)="Verified",AN19<>"Pending"),"Compliant","Non-compliant") -> Compliant | AR19: 42000 | AS19: =ROUND(AR19*0.6,0) -> 25200 | AT19: =ROUND(AS19*0.45,0) -> 11340 | AU19: Monthly withholding u/s 149 (below taxable limit) | AV19: Employee 1% / Employer 5% of minimum wage | AW19: Habib Bank Ltd | AX19: Rashid Mehmood | AY19: 1402-34903896-06 | AZ19: 14 | BA19: 10 | BB19: 8 | BC19: Calendar year (Jan-Dec) | BD19: 4 | BE19: Biometric | BF19: HR & Admin head | BG19: No | BH19: N/A | BI19: N/A | BJ19: N/A | BK19: N/A | BL19: Not applicable | BM19: N/A | BN19: N/A | BO19: N/A | BP19: Not applicable | BQ19: Not applicable
A20: EMP-018 | B20: Steelstone Building Materials (Pvt) Ltd | C20: Driver | D20: Muhammad Riaz | E20: Pakistani - no passport | F20: 33059 | G20: =DATEDIF(F20,TODAY(),"Y") -> 36 | H20: Male | I20: Married | J20: Islam | K20: O+ | L20: Attached (EMP-018.jpg) | M20: 0332-4927992 | N20: N/A | O20: House 139, Street 12, Township, Lahore | P20: Village Chak 45, Okara | Q20: Kasur / Punjab | R20: Nasreen - Wife | S20: 0340-1972304 | T20: Spouse / parent (as per emergency contact) | U20: 2 children - Ayesha (daughter, 2015), Fatima (daughter, 2019) | V20: 46011 | W20: Driver (HTV) | X20: Logistics | Y20: D-1 | Z20: Confirmed | AA20: 3 months - confirmation due Q1 2026 | AB20: N/A | AC20: N/A | AD20: =IF(ISNUMBER(AC20),IF(AC20<TODAY(),"Expired",IF(AC20-TODAY()<=30,"Expiring soon","Active")),"Not applicable") -> Not applicable | AE20: Matric | AF20: SSC | AG20: BISE Sargodha, 2002 | AH20: N/A | AI20: 12 | AJ20: NLC - Driver - 2010-2024 | AK20: 46019 | AL20: 9462398-0 | AM20: Active (ATL) | AN20: EOBI-319613788 | AO20: 46019 | AP20: Verified - May-2025 | AQ20: =IF(AND(LEFT(AP20,8)="Verified",AN20<>"Pending"),"Compliant","Non-compliant") -> Compliant | AR20: 65000 | AS20: =ROUND(AR20*0.6,0) -> 39000 | AT20: =ROUND(AS20*0.45,0) -> 17550 | AU20: Monthly withholding u/s 149 (below taxable limit) | AV20: Employee 1% / Employer 5% of minimum wage | AW20: Meezan Bank Ltd | AX20: Muhammad Riaz | AY20: 4299-39415610-02 | AZ20: 14 | BA20: 10 | BB20: 8 | BC20: Calendar year (Jan-Dec) | BD20: 0 | BE20: Mobile app (GPS check-in) | BF20: Logistics head | BG20: Yes | BH20: DRV-01 | BI20: LHR-HTV-2010-55907 | BJ20: HTV | BK20: 46726 | BL20: =IF(BK20<TODAY(),"Expired",IF(BK20-TODAY()<=30,"Expiring soon","Valid")) -> Valid | BM20: MED-56409 | BN20: 46603 | BO20: 46740 | BP20: =IF(BO20<TODAY(),"Expired",IF(BO20-TODAY()<=30,"Expiring soon","Valid")) -> Valid | BQ20: =IF(OR(BL20="Expired",BP20="Expired",BN20<TODAY()),"Non-compliant",IF(OR(BL20="Expiring soon",BP20="Expiring soon",BN20-TODAY()<=30),"At risk","Compliant")) -> Compliant
A21: EMP-019 | B21: Steelstone Building Materials (Pvt) Ltd | C21: Driver | D21: Allah Ditta | E21: Pakistani - Passport CT2326082 | F21: 33371 | G21: =DATEDIF(F21,TODAY(),"Y") -> 35 | H21: Male | I21: Married | J21: Islam | K21: B+ | L21: Attached (EMP-019.jpg) | M21: 0304-8123447 | N21: N/A | O21: House 290, Street 21, Bund Road, Lahore | P21: Same as present | Q21: Lahore / Punjab | R21: Shazia - Mother | S21: 0303-9641042 | T21: Spouse / parent (as per emergency contact) | U21: 2 children - Ayesha (daughter, 2015), Fatima (daughter, 2019) | V21: 45650 | W21: Driver (HTV) | X21: Logistics | Y21: D-1 | Z21: Confirmed | AA21: 3 months - confirmation due Q1 2025 | AB21: N/A | AC21: N/A | AD21: =IF(ISNUMBER(AC21),IF(AC21<TODAY(),"Expired",IF(AC21-TODAY()<=30,"Expiring soon","Active")),"Not applicable") -> Not applicable | AE21: Middle | AF21: N/A | AG21: N/A | AH21: N/A | AI21: 11 | AJ21: NLC - Driver - 2010-2024 | AK21: 45654 | AL21: 7915526-3 | AM21: Active (ATL) | AN21: EOBI-583120904 | AO21: 45654 | AP21: Verified - Aug-2024 | AQ21: =IF(AND(LEFT(AP21,8)="Verified",AN21<>"Pending"),"Compliant","Non-compliant") -> Compliant | AR21: 62000 | AS21: =ROUND(AR21*0.6,0) -> 37200 | AT21: =ROUND(AS21*0.45,0) -> 16740 | AU21: Monthly withholding u/s 149 (below taxable limit) | AV21: Employee 1% / Employer 5% of minimum wage | AW21: Meezan Bank Ltd | AX21: Allah Ditta | AY21: 6039-10190177-05 | AZ21: 14 | BA21: 10 | BB21: 8 | BC21: Calendar year (Jan-Dec) | BD21: 7 | BE21: Mobile app (GPS check-in) | BF21: Logistics head | BG21: Yes | BH21: DRV-02 | BI21: LHR-HTV-2013-23962 | BJ21: HTV | BK21: 46910 | BL21: =IF(BK21<TODAY(),"Expired",IF(BK21-TODAY()<=30,"Expiring soon","Valid")) -> Valid | BM21: MED-57691 | BN21: 46419 | BO21: 46676 | BP21: =IF(BO21<TODAY(),"Expired",IF(BO21-TODAY()<=30,"Expiring soon","Valid")) -> Valid | BQ21: =IF(OR(BL21="Expired",BP21="Expired",BN21<TODAY()),"Non-compliant",IF(OR(BL21="Expiring soon",BP21="Expiring soon",BN21-TODAY()<=30),"At risk","Compliant")) -> Compliant
A22: EMP-020 | B22: Steelstone Building Materials (Pvt) Ltd | C22: Driver | D22: Sher Zaman | E22: Pakistani - no passport | F22: 33137 | G22: =DATEDIF(F22,TODAY(),"Y") -> 36 | H22: Male | I22: Married | J22: Islam | K22: O- | L22: Attached (EMP-020.jpg) | M22: 0319-4367368 | N22: N/A | O22: House 169, Street 1, Samanabad, Lahore | P22: Same as present | Q22: Lahore / Punjab | R22: Rukhsana - Wife | S22: 0326-2808357 | T22: Spouse / parent (as per emergency contact) | U22: 2 children - Ahmed (son, 2012), Hamza (son, 2018) | V22: 45950 | W22: Driver (HTV) | X22: Logistics | Y22: D-1 | Z22: Confirmed | AA22: 3 months - confirmation due Q1 2026 | AB22: N/A | AC22: N/A | AD22: =IF(ISNUMBER(AC22),IF(AC22<TODAY(),"Expired",IF(AC22-TODAY()<=30,"Expiring soon","Active")),"Not applicable") -> Not applicable | AE22: Matric | AF22: SSC | AG22: BISE Peshawar, 2005 | AH22: N/A | AI22: 12 | AJ22: Self-employed - Driver | AK22: 45958 | AL22: Not registered | AM22: Non-filer | AN22: EOBI-897818603 | AO22: 45958 | AP22: Verified - Nov-2025 | AQ22: =IF(AND(LEFT(AP22,8)="Verified",AN22<>"Pending"),"Compliant","Non-compliant") -> Compliant | AR22: 62000 | AS22: =ROUND(AR22*0.6,0) -> 37200 | AT22: =ROUND(AS22*0.45,0) -> 16740 | AU22: Monthly withholding u/s 149 (below taxable limit) | AV22: Employee 1% / Employer 5% of minimum wage | AW22: MCB Bank Ltd | AX22: Sher Zaman | AY22: 9504-76302125-05 | AZ22: 14 | BA22: 10 | BB22: 8 | BC22: Calendar year (Jan-Dec) | BD22: 4 | BE22: Mobile app (GPS check-in) | BF22: Logistics head | BG22: Yes | BH22: DRV-03 | BI22: LHR-HTV-2008-42260 | BJ22: HTV | BK22: 46234 | BL22: =IF(BK22<TODAY(),"Expired",IF(BK22-TODAY()<=30,"Expiring soon","Valid")) -> Expired | BM22: MED-52606 | BN22: 46583 | BO22: 46617 | BP22: =IF(BO22<TODAY(),"Expired",IF(BO22-TODAY()<=30,"Expiring soon","Valid")) -> Valid | BQ22: =IF(OR(BL22="Expired",BP22="Expired",BN22<TODAY()),"Non-compliant",IF(OR(BL22="Expiring soon",BP22="Expiring soon",BN22-TODAY()<=30),"At risk","Compliant")) -> Non-compliant
A23: EMP-021 | B23: Steelstone Building Materials (Pvt) Ltd | C23: Driver | D23: Nazir Ahmed | E23: Pakistani - no passport | F23: 32287 | G23: =DATEDIF(F23,TODAY(),"Y") -> 38 | H23: Male | I23: Married | J23: Islam | K23: A+ | L23: Attached (EMP-021.jpg) | M23: 0306-9825003 | N23: 0310-2941711 | O23: House 18, Street 14, Wapda Town, Lahore | P23: Village Mouza Kot, Sargodha | Q23: Mardan / KP | R23: Rukhsana - Mother | S23: 0344-4067939 | T23: Spouse / parent (as per emergency contact) | U23: 2 children - Ahmed (son, 2012), Fatima (daughter, 2019) | V23: 45841 | W23: Driver (HTV) | X23: Logistics | Y23: D-1 | Z23: Contract | AA23: 3 months - confirmation due within 2025 | AB23: 45839 | AC23: 46310 | AD23: =IF(ISNUMBER(AC23),IF(AC23<TODAY(),"Expired",IF(AC23-TODAY()<=30,"Expiring soon","Active")),"Not applicable") -> Expiring soon | AE23: Middle | AF23: N/A | AG23: N/A | AH23: N/A | AI23: 14 | AJ23: Daewoo Logistics - Driver - 2015-2024 | AK23: 45866 | AL23: 6956311-0 | AM23: Active (ATL) | AN23: EOBI-607748780 | AO23: 45866 | AP23: Verified - Jan-2025 | AQ23: =IF(AND(LEFT(AP23,8)="Verified",AN23<>"Pending"),"Compliant","Non-compliant") -> Compliant | AR23: 58000 | AS23: =ROUND(AR23*0.6,0) -> 34800 | AT23: =ROUND(AS23*0.45,0) -> 15660 | AU23: Monthly withholding u/s 149 (below taxable limit) | AV23: Employee 1% / Employer 5% of minimum wage | AW23: MCB Bank Ltd | AX23: Nazir Ahmed | AY23: 1185-91802938-03 | AZ23: 14 | BA23: 10 | BB23: 8 | BC23: Calendar year (Jan-Dec) | BD23: 4 | BE23: Mobile app (GPS check-in) | BF23: Logistics head | BG23: Yes | BH23: DRV-04 | BI23: LHR-HTV-2008-90487 | BJ23: HTV | BK23: 46607 | BL23: =IF(BK23<TODAY(),"Expired",IF(BK23-TODAY()<=30,"Expiring soon","Valid")) -> Valid | BM23: MED-65216 | BN23: 46522 | BO23: 46565 | BP23: =IF(BO23<TODAY(),"Expired",IF(BO23-TODAY()<=30,"Expiring soon","Valid")) -> Valid | BQ23: =IF(OR(BL23="Expired",BP23="Expired",BN23<TODAY()),"Non-compliant",IF(OR(BL23="Expiring soon",BP23="Expiring soon",BN23-TODAY()<=30),"At risk","Compliant")) -> Compliant
A24: EMP-022 | B24: Steelstone Building Materials (Pvt) Ltd | C24: Driver | D24: Javed Iqbal | E24: Pakistani - Passport DR1461737 | F24: 33709 | G24: =DATEDIF(F24,TODAY(),"Y") -> 34 | H24: Male | I24: Married | J24: Islam | K24: AB+ | L24: Attached (EMP-022.jpg) | M24: 0305-3172699 | N24: N/A | O24: House 178, Street 19, Bund Road, Lahore | P24: Same as present | Q24: Lahore / Punjab | R24: Nasreen - Wife | S24: 0302-1442806 | T24: Spouse / parent (as per emergency contact) | U24: 2 children - Ayesha (daughter, 2015), Fatima (daughter, 2019) | V24: 45645 | W24: Driver (HTV) | X24: Logistics | Y24: D-1 | Z24: Confirmed | AA24: 3 months - confirmation due Q1 2025 | AB24: N/A | AC24: N/A | AD24: =IF(ISNUMBER(AC24),IF(AC24<TODAY(),"Expired",IF(AC24-TODAY()<=30,"Expiring soon","Active")),"Not applicable") -> Not applicable | AE24: Matric | AF24: SSC | AG24: BISE Faisalabad, 2004 | AH24: N/A | AI24: 10 | AJ24: Self-employed - Driver | AK24: 45654 | AL24: 1620960-6 | AM24: Active (ATL) | AN24: EOBI-886804258 | AO24: 45654 | AP24: Verified - Mar-2024 | AQ24: =IF(AND(LEFT(AP24,8)="Verified",AN24<>"Pending"),"Compliant","Non-compliant") -> Compliant | AR24: 60000 | AS24: =ROUND(AR24*0.6,0) -> 36000 | AT24: =ROUND(AS24*0.45,0) -> 16200 | AU24: Monthly withholding u/s 149 (below taxable limit) | AV24: Employee 1% / Employer 5% of minimum wage | AW24: Meezan Bank Ltd | AX24: Javed Iqbal | AY24: 5052-42647686-07 | AZ24: 14 | BA24: 10 | BB24: 8 | BC24: Calendar year (Jan-Dec) | BD24: 9 | BE24: Mobile app (GPS check-in) | BF24: Logistics head | BG24: Yes | BH24: DRV-05 | BI24: LHR-HTV-2020-13470 | BJ24: HTV | BK24: 46808 | BL24: =IF(BK24<TODAY(),"Expired",IF(BK24-TODAY()<=30,"Expiring soon","Valid")) -> Valid | BM24: MED-85855 | BN24: 46603 | BO24: 46300 | BP24: =IF(BO24<TODAY(),"Expired",IF(BO24-TODAY()<=30,"Expiring soon","Valid")) -> Expiring soon | BQ24: =IF(OR(BL24="Expired",BP24="Expired",BN24<TODAY()),"Non-compliant",IF(OR(BL24="Expiring soon",BP24="Expiring soon",BN24-TODAY()<=30),"At risk","Compliant")) -> At risk
A25: EMP-023 | B25: Steelstone Building Materials (Pvt) Ltd | C25: Driver | D25: Khalid Mehmood | E25: Pakistani - no passport | F25: 30578 | G25: =DATEDIF(F25,TODAY(),"Y") -> 43 | H25: Male | I25: Married | J25: Islam | K25: B+ | L25: Attached (EMP-023.jpg) | M25: 0300-4831940 | N25: N/A | O25: House 422, Street 20, Bund Road, Lahore | P25: Same as present | Q25: Lahore / Punjab | R25: Shazia - Mother | S25: 0333-7149447 | T25: Spouse / parent (as per emergency contact) | U25: 2 children - Ayesha (daughter, 2015), Fatima (daughter, 2019) | V25: 45853 | W25: Driver (HTV) | X25: Logistics | Y25: D-1 | Z25: Confirmed | AA25: 3 months - confirmation due within 2025 | AB25: N/A | AC25: N/A | AD25: =IF(ISNUMBER(AC25),IF(AC25<TODAY(),"Expired",IF(AC25-TODAY()<=30,"Expiring soon","Active")),"Not applicable") -> Not applicable | AE25: Matric | AF25: SSC | AG25: BISE Gujranwala, 2006 | AH25: N/A | AI25: 19 | AJ25: NLC - Driver - 2010-2024 | AK25: 45866 | AL25: 7323395-5 | AM25: Active (ATL) | AN25: Pending | AO25: N/A | AP25: Verified - May-2025 | AQ25: =IF(AND(LEFT(AP25,8)="Verified",AN25<>"Pending"),"Compliant","Non-compliant") -> Non-compliant | AR25: 60000 | AS25: =ROUND(AR25*0.6,0) -> 36000 | AT25: =ROUND(AS25*0.45,0) -> 16200 | AU25: Monthly withholding u/s 149 (below taxable limit) | AV25: Employee 1% / Employer 5% of minimum wage | AW25: Meezan Bank Ltd | AX25: Khalid Mehmood | AY25: 8940-75593421-02 | AZ25: 14 | BA25: 10 | BB25: 8 | BC25: Calendar year (Jan-Dec) | BD25: 2 | BE25: Mobile app (GPS check-in) | BF25: Logistics head | BG25: Yes | BH25: DRV-06 | BI25: LHR-HTV-2009-86678 | BJ25: HTV | BK25: 46305 | BL25: =IF(BK25<TODAY(),"Expired",IF(BK25-TODAY()<=30,"Expiring soon","Valid")) -> Expiring soon | BM25: MED-29515 | BN25: 46532 | BO25: 46651 | BP25: =IF(BO25<TODAY(),"Expired",IF(BO25-TODAY()<=30,"Expiring soon","Valid")) -> Valid | BQ25: =IF(OR(BL25="Expired",BP25="Expired",BN25<TODAY()),"Non-compliant",IF(OR(BL25="Expiring soon",BP25="Expiring soon",BN25-TODAY()<=30),"At risk","Compliant")) -> At risk
A26: EMP-024 | B26: Steelstone Building Materials (Pvt) Ltd | C26: Driver | D26: Amjad Ali | E26: Pakistani - no passport | F26: 32051 | G26: =DATEDIF(F26,TODAY(),"Y") -> 38 | H26: Male | I26: Married | J26: Islam | K26: B- | L26: Attached (EMP-024.jpg) | M26: 0321-1183794 | N26: N/A | O26: House 102, Street 14, Green Town, Lahore | P26: Village Mouza Kot, Mardan | Q26: Lahore / Punjab | R26: Nasreen - Wife | S26: 0340-3114463 | T26: Spouse / parent (as per emergency contact) | U26: 2 children - Ayesha (daughter, 2015), Hamza (son, 2018) | V26: 45715 | W26: Driver (LTV) | X26: Logistics | Y26: D-2 | Z26: Contract | AA26: 3 months - confirmation due within 2025 | AB26: 45689 | AC26: 46417 | AD26: =IF(ISNUMBER(AC26),IF(AC26<TODAY(),"Expired",IF(AC26-TODAY()<=30,"Expiring soon","Active")),"Not applicable") -> Active | AE26: Matric | AF26: SSC | AG26: BISE Lahore, 2010 | AH26: N/A | AI26: 15 | AJ26: Daewoo Logistics - Driver - 2015-2024 | AK26: 45716 | AL26: 8528690-4 | AM26: Active (ATL) | AN26: EOBI-986841379 | AO26: 45716 | AP26: Pending | AQ26: =IF(AND(LEFT(AP26,8)="Verified",AN26<>"Pending"),"Compliant","Non-compliant") -> Non-compliant | AR26: 55000 | AS26: =ROUND(AR26*0.6,0) -> 33000 | AT26: =ROUND(AS26*0.45,0) -> 14850 | AU26: Monthly withholding u/s 149 (below taxable limit) | AV26: Employee 1% / Employer 5% of minimum wage | AW26: Meezan Bank Ltd | AX26: Amjad Ali | AY26: 1373-83814362-04 | AZ26: 14 | BA26: 10 | BB26: 8 | BC26: Calendar year (Jan-Dec) | BD26: 2 | BE26: Mobile app (GPS check-in) | BF26: Logistics head | BG26: Yes | BH26: DRV-07 | BI26: LHR-LTV-2019-66685 | BJ26: LTV | BK26: 46649 | BL26: =IF(BK26<TODAY(),"Expired",IF(BK26-TODAY()<=30,"Expiring soon","Valid")) -> Valid | BM26: MED-40479 | BN26: 46266 | BO26: 46712 | BP26: =IF(BO26<TODAY(),"Expired",IF(BO26-TODAY()<=30,"Expiring soon","Valid")) -> Valid | BQ26: =IF(OR(BL26="Expired",BP26="Expired",BN26<TODAY()),"Non-compliant",IF(OR(BL26="Expiring soon",BP26="Expiring soon",BN26-TODAY()<=30),"At risk","Compliant")) -> Non-compliant
A27: EMP-025 | B27: Steelstone Building Materials (Pvt) Ltd | C27: Driver | D27: Fazal Rabbi | E27: Pakistani - Passport AB5295899 | F27: 30823 | G27: =DATEDIF(F27,TODAY(),"Y") -> 42 | H27: Male | I27: Married | J27: Islam | K27: O+ | L27: Attached (EMP-025.jpg) | M27: 0309-9129704 | N27: 0335-6320926 | O27: House 241, Street 21, Bund Road, Lahore | P27: Same as present | Q27: Lahore / Punjab | R27: Rukhsana - Mother | S27: 0347-7664089 | T27: Spouse / parent (as per emergency contact) | U27: 2 children - Ayesha (daughter, 2015), Fatima (daughter, 2019) | V27: 45590 | W27: Driver (HTV) | X27: Logistics | Y27: D-1 | Z27: Confirmed | AA27: 3 months - confirmation due Q1 2025 | AB27: N/A | AC27: N/A | AD27: =IF(ISNUMBER(AC27),IF(AC27<TODAY(),"Expired",IF(AC27-TODAY()<=30,"Expiring soon","Active")),"Not applicable") -> Not applicable | AE27: Middle | AF27: N/A | AG27: N/A | AH27: N/A | AI27: 18 | AJ27: Daewoo Logistics - Driver - 2015-2024 | AK27: 45593 | AL27: Not registered | AM27: Non-filer | AN27: EOBI-582874258 | AO27: 45593 | AP27: Verified - Nov-2024 | AQ27: =IF(AND(LEFT(AP27,8)="Verified",AN27<>"Pending"),"Compliant","Non-compliant") -> Compliant | AR27: 62000 | AS27: =ROUND(AR27*0.6,0) -> 37200 | AT27: =ROUND(AS27*0.45,0) -> 16740 | AU27: Monthly withholding u/s 149 (below taxable limit) | AV27: Employee 1% / Employer 5% of minimum wage | AW27: Habib Bank Ltd | AX27: Fazal Rabbi | AY27: 9467-24210537-07 | AZ27: 14 | BA27: 10 | BB27: 8 | BC27: Calendar year (Jan-Dec) | BD27: 6 | BE27: Mobile app (GPS check-in) | BF27: Logistics head | BG27: Yes | BH27: DRV-08 | BI27: LHR-HTV-2014-51184 | BJ27: HTV | BK27: 46771 | BL27: =IF(BK27<TODAY(),"Expired",IF(BK27-TODAY()<=30,"Expiring soon","Valid")) -> Valid | BM27: MED-16010 | BN27: 46541 | BO27: 46393 | BP27: =IF(BO27<TODAY(),"Expired",IF(BO27-TODAY()<=30,"Expiring soon","Valid")) -> Valid | BQ27: =IF(OR(BL27="Expired",BP27="Expired",BN27<TODAY()),"Non-compliant",IF(OR(BL27="Expiring soon",BP27="Expiring soon",BN27-TODAY()<=30),"At risk","Compliant")) -> Compliant

Sheet T08
A1: SECTION 1 - BILL HEADER & IDENTIFICATION | T1: SECTION 2 - VENDOR DETAILS | AC1: SECTION 3 - REFERENCE DOCUMENTS | AF1: SECTION 4 - BILL LINE ITEMS | AQ1: SECTION 5 - TAXES, DUTIES & WITHHOLDING | AZ1: SECTION 6 - CHARGES, DEDUCTIONS & ADJUSTMENTS | BE1: SECTION 7 - BILL SUMMARY & AMOUNT PAYABLE | BP1: SECTION 8 - PAYMENT TERMS & SCHEDULING
A2: 1.1 Vendor identity (search) | B2: 1.2 Vendor bill / invoice number | C2: 1.3 System diary number | D2: 1.4 Diary date & time (system stamp) | E2: 1.5 Diary acknowledgement issued to vendor | F2: 1.6 Diary / completion status (system-derived) | G2: 1.7 Bill booking number | H2: 1.8 Bill type (GATING FIELD) | I2: 1.9 Booking date | J2: 1.10 Vendor bill date | K2: 1.11 Accounting period / posting month | L2: 1.12 Currency | M2: 1.13 Exchange rate to base currency | N2: 1.14 Enterprise entity / company | O2: 1.15 Business location / plant receiving the supply | P2: 1.16 Cost centre / department to be charged | Q2: 1.17 Project / job reference | R2: 1.18 Bill received date & mode | S2: 1.19 Bill status | T2: 2.1 Vendor type | U2: 2.2 Vendor code & registered name | V2: 2.3 Vendor NTN | W2: 2.5 Vendor filer status on the bill date | X2: 2.6 Vendor withholding exemption applied | Y2: 2.8 Vendor contact person & mobile | Z2: 2.9 Vendor bank account for payment | AA2: 2.10 Payment terms from vendor contract | AB2: 2.11 Vendor credit balance / advance held (PKR) | AC2: 3.1 Purchase order number | AD2: 3.2 Purchase order date & value | AE2: 3.3 Contract / supply agreement reference | AF2: 4.1 Line number | AG2: 4.2 Item / material code | AH2: 4.3 Item / service description | AI2: 4.4 Unit of measure | AJ2: 4.5 Quantity billed | AK2: 4.6 Quantity accepted | AL2: 4.7 Rate per unit (PKR) | AM2: 4.8 Gross line amount (PKR) | AN2: 4.9 Taxable value of the line (PKR) | AO2: 4.10 Sales tax rate | AP2: 4.11 Other Tax | AQ2: 5.1 Total taxable value (PKR) | AR2: 5.3 Other Tax | AS2: 5.4 Income tax withheld - section & rate | AT2: 5.5 Income tax withheld (PKR) | AU2: 5.6 Exemption or reduced rate applied | AV2: 5.7 Total tax charged by vendor (PKR) | AW2: 5.8 Total tax withheld by enterprise (PKR) | AX2: 5.9 WHT deposit due date & CPR reference | AY2: 5.10 Withholding tax certificate issued to vendor | AZ2: 6.1 Loading, unloading & handling charges (PKR) | BA2: 6.2 Penalty / late delivery deduction (PKR) | BB2: 6.3 Advance adjustment (PKR) | BC2: 6.4 Retention money withheld (PKR) | BD2: 6.5 Rounding adjustment (PKR) | BE2: 7.1 Gross bill value before tax (PKR) | BF2: 7.2 Add: total taxes charged by vendor (PKR) | BG2: 7.3 Add: freight and other charges (PKR) | BH2: 7.4 Bill gross total (PKR) | BI2: 7.5 Less: taxes withheld by enterprise (PKR) | BJ2: 7.6 Less: deductions and recoveries (PKR) | BK2: 7.7 Net amount payable to vendor (PKR) | BL2: 7.8 Amount in words | BM2: 7.9 Amount paid to date (PKR) | BN2: 7.10 Balance outstanding (PKR) | BO2: 7.11 Input tax claimed in which sales tax return | BP2: 8.1 Payment terms applied | BQ2: 8.2 Payment due date | BR2: 8.3 Planned payment date | BS2: 8.4 Payment method | BT2: 8.5 Payment priority | BU2: 8.6 Hold reason (if on hold) | BV2: 8.7 Part payment allowed | BW2: 8.8 Payment voucher reference(s) | BX2: 8.9 Verified by (accounts) & date | BY2: 8.10 Approved for payment by & date
A3: VEN-102 Lahore Electric Supply Co (LESCO) (NTN 1234567-0) | B3: 102/2410/9332 | C3: DRY-00001 | D3: 45571.625 | E3: Yes - SMS & email | F3: =IF(S3="Paid","Completed","Pending payment") -> Completed | G3: BB-0001 | H3: Utilities | I3: 45572 | J3: 45570 | K3: =TEXT(I3,"mmm-yyyy") -> Oct-2024 | L3: PKR | M3: 1 | N3: Steelstone Building Materials (Pvt) Ltd | O3: Head office - Lahore | P3: CC-ADMIN | Q3: N/A | R3: 06-Oct-2024 - Email | S3: =IF(BN3<1,"Paid",IF(BM3>0,"Partially paid",IF(ISNUMBER(SEARCH("hold",BU3)),"On hold",IF(BQ3<TODAY(),"Overdue","Approved - unpaid")))) -> Paid | T3: Other vendor - Utilities | U3: VEN-102 - Lahore Electric Supply Co (LESCO) | V3: 1234567-0 | W3: Active Filer | X3: No | Y3: Accounts desk - 042-35960143 | Z3: HBL - 5983-5300965 | AA3: Credit 10 days | AB3: 0 | AC3: N/A | AD3: N/A | AE3: N/A | AF3: 1 | AG3: SRV-UTL | AH3: Electricity - LESCO | AI3: Month | AJ3: 1 | AK3: 1 | AL3: 85000 | AM3: =AK3*AL3 -> 85000 | AN3: =AM3 -> 85000 | AO3: =_xlfn.XLOOKUP(AG3,'T13'!$A$3:$A$1500,'T13'!$O$3:$O$1500) -> 0.18 | AP3: 0 | AQ3: =SUMIFS($AN$3:$AN$1500,$G$3:$G$1500,G3) -> 85000 | AR3: =SUMIFS($AP$3:$AP$1500,$G$3:$G$1500,G3) -> 0 | AS3: N/A - tax collected in bill | AT3: =ROUND(BH3*0,0) -> 0 | AU3: No | AV3: {=SUMPRODUCT(($G$3:$G$1500=G3)*$AN$3:$AN$1500*$AO$3:$AO$1500)+AR3} -> 15300 | AW3: =AT3 -> 0 | AX3: =TEXT(EOMONTH(I3,0)+15,"dd-mmm-yyyy")&" / "&IF(BM3>0,"CPR-IT-"&TEXT(I3,"yymm")&"-"&RIGHT(G3,4),"Pending payment") -> 15-Nov-2024 / CPR-IT-2410-0001 | AY3: =IF(BM3>0,"Issued","Not yet") -> Issued | AZ3: 0 | BA3: 0 | BB3: 0 | BC3: 0 | BD3: 0 | BE3: =AQ3 -> 85000 | BF3: =AV3 -> 15300 | BG3: =AZ3 -> 0 | BH3: =BE3+BF3+BG3 -> 100300 | BI3: =AW3 -> 0 | BJ3: =BA3+BB3+BC3+BD3 -> 0 | BK3: =BH3-BI3-BJ3 -> 100300 | BL3: ="PKR "&TEXT(BK3,"#,##0")&" only" -> PKR 100,300 only | BM3: =SUMIFS('T10'!$AK$3:$AK$1500,'T10'!$V$3:$V$1500,G3) -> 100300 | BN3: =BK3-BM3 -> 0 | BO3: =IF(BF3>0,TEXT(I3,"mmm-yyyy")&" sales tax return","N/A") -> Oct-2024 sales tax return | BP3: Credit 10 days | BQ3: =J3+10 -> 45580 | BR3: =BQ3 -> 45580 | BS3: IBFT | BT3: Normal | BU3: N/A | BV3: No | BW3: {=_xlfn.TEXTJOIN(", ",TRUE,_xlfn.UNIQUE(_xlfn._xlws.FILTER('T10'!$A$3:$A$1500,'T10'!$V$3:$V$1500=G3,"None")))} -> PV-0006 | BX3: Hassan Raza - 08-Oct-2024 | BY3: Sana Iqbal - 09-Oct-2024
A4: VEN-101 Sundar Estate Properties (Pvt) Ltd (NTN 3345120-7) | B4: 101/2410/2595 | C4: DRY-00002 | D4: 45581.542 | E4: Yes - SMS & email | F4: =IF(S4="Paid","Completed","Pending payment") -> Completed | G4: BB-0002 | H4: Rent | I4: 45582 | J4: 45580 | K4: =TEXT(I4,"mmm-yyyy") -> Oct-2024 | L4: PKR | M4: 1 | N4: Steelstone Building Materials (Pvt) Ltd | O4: Raiwind Road warehouse | P4: CC-WH | Q4: N/A | R4: 16-Oct-2024 - Email | S4: =IF(BN4<1,"Paid",IF(BM4>0,"Partially paid",IF(ISNUMBER(SEARCH("hold",BU4)),"On hold",IF(BQ4<TODAY(),"Overdue","Approved - unpaid")))) -> Paid | T4: Other vendor - Rent | U4: VEN-101 - Sundar Estate Properties (Pvt) Ltd | V4: 3345120-7 | W4: Active Filer | X4: No | Y4: Accounts desk - 042-35006081 | Z4: HBL - 1948-4340372 | AA4: Advance (quarterly) | AB4: 0 | AC4: N/A | AD4: N/A | AE4: Lease LA-2024-07 | AF4: 1 | AG4: SRV-RENT | AH4: Warehouse rent - Sundar Estate | AI4: Month | AJ4: 3 | AK4: 3 | AL4: 350000 | AM4: =AK4*AL4 -> 1050000 | AN4: =AM4 -> 1050000 | AO4: =_xlfn.XLOOKUP(AG4,'T13'!$A$3:$A$1500,'T13'!$O$3:$O$1500) -> 0 | AP4: 0 | AQ4: =SUMIFS($AN$3:$AN$1500,$G$3:$G$1500,G4) -> 1050000 | AR4: =SUMIFS($AP$3:$AP$1500,$G$3:$G$1500,G4) -> 0 | AS4: 155 rent - 15% | AT4: =ROUND(BH4*0.15,0) -> 157500 | AU4: No | AV4: {=SUMPRODUCT(($G$3:$G$1500=G4)*$AN$3:$AN$1500*$AO$3:$AO$1500)+AR4} -> 0 | AW4: =AT4 -> 157500 | AX4: =TEXT(EOMONTH(I4,0)+15,"dd-mmm-yyyy")&" / "&IF(BM4>0,"CPR-IT-"&TEXT(I4,"yymm")&"-"&RIGHT(G4,4),"Pending payment") -> 15-Nov-2024 / CPR-IT-2410-0002 | AY4: =IF(BM4>0,"Issued","Not yet") -> Issued | AZ4: 0 | BA4: 0 | BB4: 0 | BC4: 0 | BD4: 0 | BE4: =AQ4 -> 1050000 | BF4: =AV4 -> 0 | BG4: =AZ4 -> 0 | BH4: =BE4+BF4+BG4 -> 1050000 | BI4: =AW4 -> 157500 | BJ4: =BA4+BB4+BC4+BD4 -> 0 | BK4: =BH4-BI4-BJ4 -> 892500 | BL4: ="PKR "&TEXT(BK4,"#,##0")&" only" -> PKR 892,500 only | BM4: =SUMIFS('T10'!$AK$3:$AK$1500,'T10'!$V$3:$V$1500,G4) -> 892500 | BN4: =BK4-BM4 -> 0 | BO4: =IF(BF4>0,TEXT(I4,"mmm-yyyy")&" sales tax return","N/A") -> N/A | BP4: Advance (quarterly) | BQ4: =J4+7 -> 45587 | BR4: =BQ4 -> 45587 | BS4: IBFT | BT4: Normal | BU4: N/A | BV4: No | BW4: {=_xlfn.TEXTJOIN(", ",TRUE,_xlfn.UNIQUE(_xlfn._xlws.FILTER('T10'!$A$3:$A$1500,'T10'!$V$3:$V$1500=G4,"None")))} -> PV-0025 | BX4: Hassan Raza - 18-Oct-2024 | BY4: Sana Iqbal - 19-Oct-2024
A5: VEN-103 Shield Security Services (Pvt) Ltd (NTN 4567812-3) | B5: 103/2410/2040 | C5: DRY-00003 | D5: 45589.625 | E5: Yes - SMS & email | F5: =IF(S5="Paid","Completed","Pending payment") -> Completed | G5: BB-0003 | H5: Services | I5: 45590 | J5: 45588 | K5: =TEXT(I5,"mmm-yyyy") -> Oct-2024 | L5: PKR | M5: 1 | N5: Steelstone Building Materials (Pvt) Ltd | O5: Head office - Lahore | P5: CC-ADMIN | Q5: N/A | R5: 24-Oct-2024 - Email | S5: =IF(BN5<1,"Paid",IF(BM5>0,"Partially paid",IF(ISNUMBER(SEARCH("hold",BU5)),"On hold",IF(BQ5<TODAY(),"Overdue","Approved - unpaid")))) -> Paid | T5: Other vendor - Services | U5: VEN-103 - Shield Security Services (Pvt) Ltd | V5: 4567812-3 | W5: Active Filer | X5: No | Y5: Accounts desk - 042-35813307 | Z5: MCB - 9830-6278689 | AA5: Credit 30 days | AB5: 0 | AC5: N/A | AD5: N/A | AE5: N/A | AF5: 1 | AG5: SRV-SEC | AH5: Security guard services | AI5: Month | AJ5: 1 | AK5: 1 | AL5: 180000 | AM5: =AK5*AL5 -> 180000 | AN5: =AM5 -> 180000 | AO5: =_xlfn.XLOOKUP(AG5,'T13'!$A$3:$A$1500,'T13'!$O$3:$O$1500) -> 0.16 | AP5: 0 | AQ5: =SUMIFS($AN$3:$AN$1500,$G$3:$G$1500,G5) -> 180000 | AR5: =SUMIFS($AP$3:$AP$1500,$G$3:$G$1500,G5) -> 0 | AS5: 153(1)(b) services - 11% | AT5: =ROUND(BH5*0.11,0) -> 22968 | AU5: No | AV5: {=SUMPRODUCT(($G$3:$G$1500=G5)*$AN$3:$AN$1500*$AO$3:$AO$1500)+AR5} -> 28800 | AW5: =AT5 -> 22968 | AX5: =TEXT(EOMONTH(I5,0)+15,"dd-mmm-yyyy")&" / "&IF(BM5>0,"CPR-IT-"&TEXT(I5,"yymm")&"-"&RIGHT(G5,4),"Pending payment") -> 15-Nov-2024 / CPR-IT-2410-0003 | AY5: =IF(BM5>0,"Issued","Not yet") -> Issued | AZ5: 0 | BA5: 0 | BB5: 0 | BC5: 0 | BD5: 0 | BE5: =AQ5 -> 180000 | BF5: =AV5 -> 28800 | BG5: =AZ5 -> 0 | BH5: =BE5+BF5+BG5 -> 208800 | BI5: =AW5 -> 22968 | BJ5: =BA5+BB5+BC5+BD5 -> 0 | BK5: =BH5-BI5-BJ5 -> 185832 | BL5: ="PKR "&TEXT(BK5,"#,##0")&" only" -> PKR 185,832 only | BM5: =SUMIFS('T10'!$AK$3:$AK$1500,'T10'!$V$3:$V$1500,G5) -> 185832 | BN5: =BK5-BM5 -> 0 | BO5: =IF(BF5>0,TEXT(I5,"mmm-yyyy")&" sales tax return","N/A") -> Oct-2024 sales tax return | BP5: Credit 30 days | BQ5: =J5+30 -> 45618 | BR5: =BQ5 -> 45618 | BS5: IBFT | BT5: Normal | BU5: N/A | BV5: No | BW5: {=_xlfn.TEXTJOIN(", ",TRUE,_xlfn.UNIQUE(_xlfn._xlws.FILTER('T10'!$A$3:$A$1500,'T10'!$V$3:$V$1500=G5,"None")))} -> PV-0007 | BX5: Hassan Raza - 26-Oct-2024 | BY5: Sana Iqbal - 27-Oct-2024
A6: SUP-001 Margalla Cement Ltd (NTN 0712345-6) | B6: MCL/INV/2410/556 | C6: DRY-00004 | D6: 45597.583 | E6: Yes - SMS & email | F6: =IF(S6="Paid","Completed","Pending payment") -> Completed | G6: BB-0004 | H6: Goods purchase (cement) | I6: 45596 | J6: 45596 | K6: =TEXT(I6,"mmm-yyyy") -> Oct-2024 | L6: PKR | M6: 1 | N6: Steelstone Building Materials (Pvt) Ltd | O6: Supplier plant - direct dispatch | P6: CC-SALES-LHR | Q6: N/A | R6: 01-Nov-2024 - Email | S6: =IF(BN6<1,"Paid",IF(BM6>0,"Partially paid",IF(ISNUMBER(SEARCH("hold",BU6)),"On hold",IF(BQ6<TODAY(),"Overdue","Approved - unpaid")))) -> Paid | T6: Manufacturer / supplier | U6: SUP-001 - Margalla Cement Ltd | V6: 0712345-6 | W6: Active Filer | X6: No | Y6: Shahid Iqbal - 0300-8451290 | Z6: Habib Bank Ltd - 1234-79001122-03 | AA6: Credit 15 days | AB6: 0 | AC6: PO-2410-1 | AD6: 07-Oct-2024 / PKR 11148000 (approx.) | AE6: SA-SUP-001-2024 | AF6: 1 | AG6: CEM-OPC-BLK | AH6: OPC Cement Grade 53 - bulk | AI6: MT | AJ6: 215 | AK6: 215 | AL6: 24800 | AM6: =AK6*AL6 -> 5332000 | AN6: =AM6 -> 5332000 | AO6: =_xlfn.XLOOKUP(AG6,'T13'!$A$3:$A$1500,'T13'!$O$3:$O$1500) -> 0.18 | AP6: =AK6*IF(AI6="MT",1000,IF(AI6="Jumbo bag (1.5 MT)",1500,IF(AI6="Bag (40 kg)",40,50)))*3 -> 645000 | AQ6: =SUMIFS($AN$3:$AN$1500,$G$3:$G$1500,G6) -> 8596000 | AR6: =SUMIFS($AP$3:$AP$1500,$G$3:$G$1500,G6) -> 1005000 | AS6: 153(1)(a) goods - 5% | AT6: =ROUND(BH6*0.05,0) -> 557414 | AU6: No | AV6: {=SUMPRODUCT(($G$3:$G$1500=G6)*$AN$3:$AN$1500*$AO$3:$AO$1500)+AR6} -> 2552280 | AW6: =AT6 -> 557414 | AX6: =TEXT(EOMONTH(I6,0)+15,"dd-mmm-yyyy")&" / "&IF(BM6>0,"CPR-IT-"&TEXT(I6,"yymm")&"-"&RIGHT(G6,4),"Pending payment") -> 15-Nov-2024 / CPR-IT-2410-0004 | AY6: =IF(BM6>0,"Issued","Not yet") -> Issued | AZ6: 0 | BA6: 0 | BB6: 0 | BC6: 0 | BD6: 0 | BE6: =AQ6 -> 8596000 | BF6: =AV6 -> 2552280 | BG6: =AZ6 -> 0 | BH6: =BE6+BF6+BG6 -> 11148280 | BI6: =AW6 -> 557414 | BJ6: =BA6+BB6+BC6+BD6 -> 0 | BK6: =BH6-BI6-BJ6 -> 10590866 | BL6: ="PKR "&TEXT(BK6,"#,##0")&" only" -> PKR 10,590,866 only | BM6: =SUMIFS('T10'!$AK$3:$AK$1500,'T10'!$V$3:$V$1500,G6) -> 10590866 | BN6: =BK6-BM6 -> 0 | BO6: =IF(BF6>0,TEXT(I6,"mmm-yyyy")&" sales tax return","N/A") -> Oct-2024 sales tax return | BP6: Credit 15 days | BQ6: =J6+15 -> 45611 | BR6: =BQ6 -> 45611 | BS6: IBFT | BT6: High | BU6: N/A | BV6: No | BW6: {=_xlfn.TEXTJOIN(", ",TRUE,_xlfn.UNIQUE(_xlfn._xlws.FILTER('T10'!$A$3:$A$1500,'T10'!$V$3:$V$1500=G6,"None")))} -> PV-0001 | BX6: Hassan Raza - 01-Nov-2024 | BY6: Sana Iqbal - 02-Nov-2024
A7: SUP-001 Margalla Cement Ltd (NTN 0712345-6) | B7: MCL/INV/2410/556 | C7: DRY-00004 | D7: 45597.583 | E7: Yes - SMS & email | F7: =IF(S7="Paid","Completed","Pending payment") -> Completed | G7: BB-0004 | H7: Goods purchase (cement) | I7: 45596 | J7: 45596 | K7: =TEXT(I7,"mmm-yyyy") -> Oct-2024 | L7: PKR | M7: 1 | N7: Steelstone Building Materials (Pvt) Ltd | O7: Supplier plant - direct dispatch | P7: CC-SALES-LHR | Q7: N/A | R7: 01-Nov-2024 - Email | S7: =IF(BN7<1,"Paid",IF(BM7>0,"Partially paid",IF(ISNUMBER(SEARCH("hold",BU7)),"On hold",IF(BQ7<TODAY(),"Overdue","Approved - unpaid")))) -> Paid | T7: Manufacturer / supplier | U7: SUP-001 - Margalla Cement Ltd | V7: 0712345-6 | W7: Active Filer | X7: No | Y7: Shahid Iqbal - 0300-8451290 | Z7: Habib Bank Ltd - 1234-79001122-03 | AA7: Credit 15 days | AB7: 0 | AC7: PO-2410-1 | AD7: 14-Oct-2024 / PKR 11148000 (approx.) | AE7: SA-SUP-001-2024 | AF7: 2 | AG7: CEM-SRC-B50 | AH7: Sulphate Resistant Cement - 50 kg bag | AI7: Bag (50 kg) | AJ7: 2400 | AK7: 2400 | AL7: 1360 | AM7: =AK7*AL7 -> 3264000 | AN7: =AM7 -> 3264000 | AO7: =_xlfn.XLOOKUP(AG7,'T13'!$A$3:$A$1500,'T13'!$O$3:$O$1500) -> 0.18 | AP7: =AK7*IF(AI7="MT",1000,IF(AI7="Jumbo bag (1.5 MT)",1500,IF(AI7="Bag (40 kg)",40,50)))*3 -> 360000 | AQ7: =SUMIFS($AN$3:$AN$1500,$G$3:$G$1500,G7) -> 8596000 | AR7: =SUMIFS($AP$3:$AP$1500,$G$3:$G$1500,G7) -> 1005000 | AS7: 153(1)(a) goods - 5% | AT7: =ROUND(BH7*0.05,0) -> 557414 | AU7: No | AV7: {=SUMPRODUCT(($G$3:$G$1500=G7)*$AN$3:$AN$1500*$AO$3:$AO$1500)+AR7} -> 2552280 | AW7: =AT7 -> 557414 | AX7: =TEXT(EOMONTH(I7,0)+15,"dd-mmm-yyyy")&" / "&IF(BM7>0,"CPR-IT-"&TEXT(I7,"yymm")&"-"&RIGHT(G7,4),"Pending payment") -> 15-Nov-2024 / CPR-IT-2410-0004 | AY7: =IF(BM7>0,"Issued","Not yet") -> Issued | AZ7: 0 | BA7: 0 | BB7: 0 | BC7: 0 | BD7: 0 | BE7: =AQ7 -> 8596000 | BF7: =AV7 -> 2552280 | BG7: =AZ7 -> 0 | BH7: =BE7+BF7+BG7 -> 11148280 | BI7: =AW7 -> 557414 | BJ7: =BA7+BB7+BC7+BD7 -> 0 | BK7: =BH7-BI7-BJ7 -> 10590866 | BL7: ="PKR "&TEXT(BK7,"#,##0")&" only" -> PKR 10,590,866 only | BM7: =SUMIFS('T10'!$AK$3:$AK$1500,'T10'!$V$3:$V$1500,G7) -> 10590866 | BN7: =BK7-BM7 -> 0 | BO7: =IF(BF7>0,TEXT(I7,"mmm-yyyy")&" sales tax return","N/A") -> Oct-2024 sales tax return | BP7: Credit 15 days | BQ7: =J7+15 -> 45611 | BR7: =BQ7 -> 45611 | BS7: IBFT | BT7: High | BU7: N/A | BV7: No | BW7: {=_xlfn.TEXTJOIN(", ",TRUE,_xlfn.UNIQUE(_xlfn._xlws.FILTER('T10'!$A$3:$A$1500,'T10'!$V$3:$V$1500=G7,"None")))} -> PV-0001 | BX7: Hassan Raza - 01-Nov-2024 | BY7: Sana Iqbal - 02-Nov-2024
A8: SUP-002 Indus Valley Cement (Pvt) Ltd (NTN 3398761-2) | B8: IVC/INV/2410/306 | C8: DRY-00005 | D8: 45597.458 | E8: Yes - SMS & email | F8: =IF(S8="Paid","Completed","Pending payment") -> Completed | G8: BB-0005 | H8: Goods purchase (cement) | I8: 45596 | J8: 45596 | K8: =TEXT(I8,"mmm-yyyy") -> Oct-2024 | L8: PKR | M8: 1 | N8: Steelstone Building Materials (Pvt) Ltd | O8: Supplier plant - direct dispatch | P8: CC-SALES-LHR | Q8: N/A | R8: 01-Nov-2024 - Email | S8: =IF(BN8<1,"Paid",IF(BM8>0,"Partially paid",IF(ISNUMBER(SEARCH("hold",BU8)),"On hold",IF(BQ8<TODAY(),"Overdue","Approved - unpaid")))) -> Paid | T8: Manufacturer / supplier | U8: SUP-002 - Indus Valley Cement (Pvt) Ltd | V8: 3398761-2 | W8: Active Filer | X8: No | Y8: Rizwan Akhtar - 0302-4418823 | Z8: MCB Bank Ltd - 0876-5501234401 | AA8: Credit 15 days | AB8: 0 | AC8: PO-2410-2 | AD8: 12-Oct-2024 / PKR 1452000 (approx.) | AE8: SA-SUP-002-2024 | AF8: 1 | AG8: CEM-SLG-B50 | AH8: Slag Cement - 50 kg bag | AI8: Bag (50 kg) | AJ8: 900 | AK8: 900 | AL8: 1240 | AM8: =AK8*AL8 -> 1116000 | AN8: =AM8 -> 1116000 | AO8: =_xlfn.XLOOKUP(AG8,'T13'!$A$3:$A$1500,'T13'!$O$3:$O$1500) -> 0.18 | AP8: =AK8*IF(AI8="MT",1000,IF(AI8="Jumbo bag (1.5 MT)",1500,IF(AI8="Bag (40 kg)",40,50)))*3 -> 135000 | AQ8: =SUMIFS($AN$3:$AN$1500,$G$3:$G$1500,G8) -> 1116000 | AR8: =SUMIFS($AP$3:$AP$1500,$G$3:$G$1500,G8) -> 135000 | AS8: 153(1)(a) goods - 5% | AT8: =ROUND(BH8*0.05,0) -> 72594 | AU8: No | AV8: {=SUMPRODUCT(($G$3:$G$1500=G8)*$AN$3:$AN$1500*$AO$3:$AO$1500)+AR8} -> 335880 | AW8: =AT8 -> 72594 | AX8: =TEXT(EOMONTH(I8,0)+15,"dd-mmm-yyyy")&" / "&IF(BM8>0,"CPR-IT-"&TEXT(I8,"yymm")&"-"&RIGHT(G8,4),"Pending payment") -> 15-Nov-2024 / CPR-IT-2410-0005 | AY8: =IF(BM8>0,"Issued","Not yet") -> Issued | AZ8: 0 | BA8: 0 | BB8: 0 | BC8: 0 | BD8: 0 | BE8: =AQ8 -> 1116000 | BF8: =AV8 -> 335880 | BG8: =AZ8 -> 0 | BH8: =BE8+BF8+BG8 -> 1451880 | BI8: =AW8 -> 72594 | BJ8: =BA8+BB8+BC8+BD8 -> 0 | BK8: =BH8-BI8-BJ8 -> 1379286 | BL8: ="PKR "&TEXT(BK8,"#,##0")&" only" -> PKR 1,379,286 only | BM8: =SUMIFS('T10'!$AK$3:$AK$1500,'T10'!$V$3:$V$1500,G8) -> 1379286 | BN8: =BK8-BM8 -> 0 | BO8: =IF(BF8>0,TEXT(I8,"mmm-yyyy")&" sales tax return","N/A") -> Oct-2024 sales tax return | BP8: Credit 15 days | BQ8: =J8+15 -> 45611 | BR8: =BQ8 -> 45611 | BS8: IBFT | BT8: High | BU8: N/A | BV8: No | BW8: {=_xlfn.TEXTJOIN(", ",TRUE,_xlfn.UNIQUE(_xlfn._xlws.FILTER('T10'!$A$3:$A$1500,'T10'!$V$3:$V$1500=G8,"None")))} -> PV-0004 | BX8: Hassan Raza - 01-Nov-2024 | BY8: Sana Iqbal - 02-Nov-2024
A9: TRN-003 Punjab Bulk Carriers (AOP) (NTN 4098877-2) | B9: FB-TRN003-2410 | C9: DRY-00006 | D9: 45598.583 | E9: Yes - SMS & email | F9: =IF(S9="Paid","Completed","Pending payment") -> Completed | G9: BB-0006 | H9: Freight / transport | I9: 45599 | J9: 45597 | K9: =TEXT(I9,"mmm-yyyy") -> Nov-2024 | L9: PKR | M9: 1 | N9: Steelstone Building Materials (Pvt) Ltd | O9: Head office - Lahore | P9: CC-LOG | Q9: N/A | R9: 02-Nov-2024 - By hand | S9: =IF(BN9<1,"Paid",IF(BM9>0,"Partially paid",IF(ISNUMBER(SEARCH("hold",BU9)),"On hold",IF(BQ9<TODAY(),"Overdue","Approved - unpaid")))) -> Paid | T9: Transporter | U9: TRN-003 - Punjab Bulk Carriers (AOP) | V9: 4098877-2 | W9: Inactive / Non-filer | X9: No | Y9: Sajjad Hussain - 0333-4128876 | Z9: United Bank Ltd - 0900-2201456 | AA9: Credit 30 days | AB9: 0 | AC9: N/A | AD9: N/A | AE9: TC-TRN-003-2024 | AF9: 1 | AG9: SRV-FRT-BLK | AH9: Freight - bulker per trip | AI9: Trip | AJ9: =COUNTIFS('T14'!$AQ$3:$AQ$1500,B9,'T14'!$Z$3:$Z$1500,1,'T14'!$F$3:$F$1500,"Bulker") -> 6 | AK9: =AJ9 -> 6 | AL9: 55000 | AM9: =AK9*AL9 -> 330000 | AN9: =AM9 -> 330000 | AO9: =_xlfn.XLOOKUP(AG9,'T13'!$A$3:$A$1500,'T13'!$O$3:$O$1500) -> 0.16 | AP9: 0 | AQ9: =SUMIFS($AN$3:$AN$1500,$G$3:$G$1500,G9) -> 330000 | AR9: =SUMIFS($AP$3:$AP$1500,$G$3:$G$1500,G9) -> 0 | AS9: 153(1)(b) transport - 8% (non-filer) | AT9: =ROUND(BH9*0.08,0) -> 30624 | AU9: No | AV9: {=SUMPRODUCT(($G$3:$G$1500=G9)*$AN$3:$AN$1500*$AO$3:$AO$1500)+AR9} -> 52800 | AW9: =AT9 -> 30624 | AX9: =TEXT(EOMONTH(I9,0)+15,"dd-mmm-yyyy")&" / "&IF(BM9>0,"CPR-IT-"&TEXT(I9,"yymm")&"-"&RIGHT(G9,4),"Pending payment") -> 15-Dec-2024 / CPR-IT-2411-0006 | AY9: =IF(BM9>0,"Issued","Not yet") -> Issued | AZ9: 0 | BA9: 5000 | BB9: 0 | BC9: 0 | BD9: 0 | BE9: =AQ9 -> 330000 | BF9: =AV9 -> 52800 | BG9: =AZ9 -> 0 | BH9: =BE9+BF9+BG9 -> 382800 | BI9: =AW9 -> 30624 | BJ9: =BA9+BB9+BC9+BD9 -> 5000 | BK9: =BH9-BI9-BJ9 -> 347176 | BL9: ="PKR "&TEXT(BK9,"#,##0")&" only" -> PKR 347,176 only | BM9: =SUMIFS('T10'!$AK$3:$AK$1500,'T10'!$V$3:$V$1500,G9) -> 347176 | BN9: =BK9-BM9 -> 0 | BO9: =IF(BF9>0,TEXT(I9,"mmm-yyyy")&" sales tax return","N/A") -> Nov-2024 sales tax return | BP9: Credit 30 days | BQ9: =J9+30 -> 45627 | BR9: =BQ9 -> 45627 | BS9: IBFT | BT9: Normal | BU9: N/A | BV9: No | BW9: {=_xlfn.TEXTJOIN(", ",TRUE,_xlfn.UNIQUE(_xlfn._xlws.FILTER('T10'!$A$3:$A$1500,'T10'!$V$3:$V$1500=G9,"None")))} -> PV-0022 | BX9: Hassan Raza - 04-Nov-2024 | BY9: Sana Iqbal - 05-Nov-2024
A10: TRN-002 Al-Madina Logistics (Pvt) Ltd (NTN 5567123-4) | B10: FB-TRN002-2410 | C10: DRY-00007 | D10: 45598.458 | E10: Yes - SMS & email | F10: =IF(S10="Paid","Completed","Pending payment") -> Completed | G10: BB-0007 | H10: Freight / transport | I10: 45599 | J10: 45597 | K10: =TEXT(I10,"mmm-yyyy") -> Nov-2024 | L10: PKR | M10: 1 | N10: Steelstone Building Materials (Pvt) Ltd | O10: Head office - Lahore | P10: CC-LOG | Q10: N/A | R10: 02-Nov-2024 - By hand | S10: =IF(BN10<1,"Paid",IF(BM10>0,"Partially paid",IF(ISNUMBER(SEARCH("hold",BU10)),"On hold",IF(BQ10<TODAY(),"Overdue","Approved - unpaid")))) -> Paid | T10: Transporter | U10: TRN-002 - Al-Madina Logistics (Pvt) Ltd | V10: 5567123-4 | W10: Active Filer | X10: No | Y10: Tahir Mehmood - 0321-4789012 | Z10: MCB Bank Ltd - 0654-7701122301 | AA10: Credit 30 days | AB10: 0 | AC10: N/A | AD10: N/A | AE10: TC-TRN-002-2024 | AF10: 1 | AG10: SRV-FRT-BAG | AH10: Freight - bagged cement per trip | AI10: Trip | AJ10: =COUNTIFS('T14'!$AQ$3:$AQ$1500,B10,'T14'!$Z$3:$Z$1500,1,'T14'!$F$3:$F$1500,"Bag") -> 6 | AK10: =AJ10 -> 6 | AL10: 38000 | AM10: =AK10*AL10 -> 228000 | AN10: =AM10 -> 228000 | AO10: =_xlfn.XLOOKUP(AG10,'T13'!$A$3:$A$1500,'T13'!$O$3:$O$1500) -> 0.16 | AP10: 0 | AQ10: =SUMIFS($AN$3:$AN$1500,$G$3:$G$1500,G10) -> 228000 | AR10: =SUMIFS($AP$3:$AP$1500,$G$3:$G$1500,G10) -> 0 | AS10: 153(1)(b) transport - 4% | AT10: =ROUND(BH10*0.04,0) -> 10879 | AU10: No | AV10: {=SUMPRODUCT(($G$3:$G$1500=G10)*$AN$3:$AN$1500*$AO$3:$AO$1500)+AR10} -> 36480 | AW10: =AT10 -> 10879 | AX10: =TEXT(EOMONTH(I10,0)+15,"dd-mmm-yyyy")&" / "&IF(BM10>0,"CPR-IT-"&TEXT(I10,"yymm")&"-"&RIGHT(G10,4),"Pending payment") -> 15-Dec-2024 / CPR-IT-2411-0007 | AY10: =IF(BM10>0,"Issued","Not yet") -> Issued | AZ10: 7500 | BA10: 0 | BB10: 0 | BC10: 0 | BD10: 0 | BE10: =AQ10 -> 228000 | BF10: =AV10 -> 36480 | BG10: =AZ10 -> 7500 | BH10: =BE10+BF10+BG10 -> 271980 | BI10: =AW10 -> 10879 | BJ10: =BA10+BB10+BC10+BD10 -> 0 | BK10: =BH10-BI10-BJ10 -> 261101 | BL10: ="PKR "&TEXT(BK10,"#,##0")&" only" -> PKR 261,101 only | BM10: =SUMIFS('T10'!$AK$3:$AK$1500,'T10'!$V$3:$V$1500,G10) -> 261101 | BN10: =BK10-BM10 -> 0 | BO10: =IF(BF10>0,TEXT(I10,"mmm-yyyy")&" sales tax return","N/A") -> Nov-2024 sales tax return | BP10: Credit 30 days | BQ10: =J10+30 -> 45627 | BR10: =BQ10 -> 45627 | BS10: IBFT | BT10: Normal | BU10: N/A | BV10: No | BW10: {=_xlfn.TEXTJOIN(", ",TRUE,_xlfn.UNIQUE(_xlfn._xlws.FILTER('T10'!$A$3:$A$1500,'T10'!$V$3:$V$1500=G10,"None")))} -> PV-0003 | BX10: Hassan Raza - 04-Nov-2024 | BY10: Sana Iqbal - 05-Nov-2024
A11: VEN-104 Nayatel (Pvt) Ltd (NTN 2098765-4) | B11: 104/2411/3182 | C11: DRY-00008 | D11: 45617.458 | E11: Yes - SMS & email | F11: =IF(S11="Paid","Completed","Pending payment") -> Completed | G11: BB-0008 | H11: Utilities | I11: 45618 | J11: 45616 | K11: =TEXT(I11,"mmm-yyyy") -> Nov-2024 | L11: PKR | M11: 1 | N11: Steelstone Building Materials (Pvt) Ltd | O11: Head office - Lahore | P11: CC-ADMIN | Q11: N/A | R11: 21-Nov-2024 - Email | S11: =IF(BN11<1,"Paid",IF(BM11>0,"Partially paid",IF(ISNUMBER(SEARCH("hold",BU11)),"On hold",IF(BQ11<TODAY(),"Overdue","Approved - unpaid")))) -> Paid | T11: Other vendor - Utilities | U11: VEN-104 - Nayatel (Pvt) Ltd | V11: 2098765-4 | W11: Active Filer | X11: No | Y11: Accounts desk - 042-35660073 | Z11: Meezan - 5857-6193451 | AA11: Credit 15 days | AB11: 0 | AC11: N/A | AD11: N/A | AE11: N/A | AF11: 1 | AG11: SRV-INT | AH11: Internet & telephone | AI11: Month | AJ11: 1 | AK11: 1 | AL11: 25100 | AM11: =AK11*AL11 -> 25100 | AN11: =AM11 -> 25100 | AO11: =_xlfn.XLOOKUP(AG11,'T13'!$A$3:$A$1500,'T13'!$O$3:$O$1500) -> 0.16 | AP11: 0 | AQ11: =SUMIFS($AN$3:$AN$1500,$G$3:$G$1500,G11) -> 25100 | AR11: =SUMIFS($AP$3:$AP$1500,$G$3:$G$1500,G11) -> 0 | AS11: N/A - tax collected in bill | AT11: =ROUND(BH11*0,0) -> 0 | AU11: No | AV11: {=SUMPRODUCT(($G$3:$G$1500=G11)*$AN$3:$AN$1500*$AO$3:$AO$1500)+AR11} -> 4016 | AW11: =AT11 -> 0 | AX11: =TEXT(EOMONTH(I11,0)+15,"dd-mmm-yyyy")&" / "&IF(BM11>0,"CPR-IT-"&TEXT(I11,"yymm")&"-"&RIGHT(G11,4),"Pending payment") -> 15-Dec-2024 / CPR-IT-2411-0008 | AY11: =IF(BM11>0,"Issued","Not yet") -> Issued | AZ11: 0 | BA11: 0 | BB11: 0 | BC11: 0 | BD11: 0 | BE11: =AQ11 -> 25100 | BF11: =AV11 -> 4016 | BG11: =AZ11 -> 0 | BH11: =BE11+BF11+BG11 -> 29116 | BI11: =AW11 -> 0 | BJ11: =BA11+BB11+BC11+BD11 -> 0 | BK11: =BH11-BI11-BJ11 -> 29116 | BL11: ="PKR "&TEXT(BK11,"#,##0")&" only" -> PKR 29,116 only | BM11: =SUMIFS('T10'!$AK$3:$AK$1500,'T10'!$V$3:$V$1500,G11) -> 29116 | BN11: =BK11-BM11 -> 0 | BO11: =IF(BF11>0,TEXT(I11,"mmm-yyyy")&" sales tax return","N/A") -> Nov-2024 sales tax return | BP11: Credit 15 days | BQ11: =J11+15 -> 45631 | BR11: =BQ11 -> 45631 | BS11: IBFT | BT11: Normal | BU11: N/A | BV11: No | BW11: {=_xlfn.TEXTJOIN(", ",TRUE,_xlfn.UNIQUE(_xlfn._xlws.FILTER('T10'!$A$3:$A$1500,'T10'!$V$3:$V$1500=G11,"None")))} -> PV-0010 | BX11: Hassan Raza - 23-Nov-2024 | BY11: Sana Iqbal - 24-Nov-2024
A12: VEN-105 Pakistan State Oil - fuel card (NTN 0801523-9) | B12: 105/2411/8337 | C12: DRY-00009 | D12: 45620.625 | E12: Yes - SMS & email | F12: =IF(S12="Paid","Completed","Pending payment") -> Completed | G12: BB-0009 | H12: Goods - fuel | I12: 45620 | J12: 45618 | K12: =TEXT(I12,"mmm-yyyy") -> Nov-2024 | L12: PKR | M12: 1 | N12: Steelstone Building Materials (Pvt) Ltd | O12: Raiwind Road warehouse | P12: CC-LOG | Q12: N/A | R12: 24-Nov-2024 - Email | S12: =IF(BN12<1,"Paid",IF(BM12>0,"Partially paid",IF(ISNUMBER(SEARCH("hold",BU12)),"On hold",IF(BQ12<TODAY(),"Overdue","Approved - unpaid")))) -> Paid | T12: Other vendor - Goods - fuel | U12: VEN-105 - Pakistan State Oil - fuel card | V12: 0801523-9 | W12: Active Filer | X12: No | Y12: Accounts desk - 042-35483071 | Z12: Meezan - 9225-9427766 | AA12: Credit 15 days | AB12: 0 | AC12: N/A | AD12: N/A | AE12: N/A | AF12: 1 | AG12: CON-DSL | AH12: High speed diesel | AI12: Litre | AJ12: 408 | AK12: 408 | AL12: 270 | AM12: =AK12*AL12 -> 110160 | AN12: =AM12 -> 110160 | AO12: =_xlfn.XLOOKUP(AG12,'T13'!$A$3:$A$1500,'T13'!$O$3:$O$1500) -> 0.18 | AP12: 0 | AQ12: =SUMIFS($AN$3:$AN$1500,$G$3:$G$1500,G12) -> 110160 | AR12: =SUMIFS($AP$3:$AP$1500,$G$3:$G$1500,G12) -> 0 | AS12: N/A - petroleum | AT12: =ROUND(BH12*0,0) -> 0 | AU12: No | AV12: {=SUMPRODUCT(($G$3:$G$1500=G12)*$AN$3:$AN$1500*$AO$3:$AO$1500)+AR12} -> 19828.8 | AW12: =AT12 -> 0 | AX12: =TEXT(EOMONTH(I12,0)+15,"dd-mmm-yyyy")&" / "&IF(BM12>0,"CPR-IT-"&TEXT(I12,"yymm")&"-"&RIGHT(G12,4),"Pending payment") -> 15-Dec-2024 / CPR-IT-2411-0009 | AY12: =IF(BM12>0,"Issued","Not yet") -> Issued | AZ12: 0 | BA12: 0 | BB12: 0 | BC12: 0 | BD12: 0 | BE12: =AQ12 -> 110160 | BF12: =AV12 -> 19828.8 | BG12: =AZ12 -> 0 | BH12: =BE12+BF12+BG12 -> 129988.8 | BI12: =AW12 -> 0 | BJ12: =BA12+BB12+BC12+BD12 -> 0 | BK12: =BH12-BI12-BJ12 -> 129988.8 | BL12: ="PKR "&TEXT(BK12,"#,##0")&" only" -> PKR 129,989 only | BM12: =SUMIFS('T10'!$AK$3:$AK$1500,'T10'!$V$3:$V$1500,G12) -> 129988.8 | BN12: =BK12-BM12 -> 0 | BO12: =IF(BF12>0,TEXT(I12,"mmm-yyyy")&" sales tax return","N/A") -> Nov-2024 sales tax return | BP12: Credit 15 days | BQ12: =J12+15 -> 45633 | BR12: =BQ12 -> 45633 | BS12: IBFT | BT12: Normal | BU12: N/A | BV12: No | BW12: {=_xlfn.TEXTJOIN(", ",TRUE,_xlfn.UNIQUE(_xlfn._xlws.FILTER('T10'!$A$3:$A$1500,'T10'!$V$3:$V$1500=G12,"None")))} -> PV-0034 | BX12: Hassan Raza - 25-Nov-2024 | BY12: Sana Iqbal - 26-Nov-2024
A13: SUP-002 Indus Valley Cement (Pvt) Ltd (NTN 3398761-2) | B13: IVC/INV/2411/475 | C13: DRY-00010 | D13: 45628.667 | E13: Yes - SMS & email | F13: =IF(S13="Paid","Completed","Pending payment") -> Completed | G13: BB-0010 | H13: Goods purchase (cement) | I13: 45626 | J13: 45626 | K13: =TEXT(I13,"mmm-yyyy") -> Nov-2024 | L13: PKR | M13: 1 | N13: Steelstone Building Materials (Pvt) Ltd | O13: Supplier plant - direct dispatch | P13: CC-SALES-LHR | Q13: N/A | R13: 02-Dec-2024 - Email | S13: =IF(BN13<1,"Paid",IF(BM13>0,"Partially paid",IF(ISNUMBER(SEARCH("hold",BU13)),"On hold",IF(BQ13<TODAY(),"Overdue","Approved - unpaid")))) -> Paid | T13: Manufacturer / supplier | U13: SUP-002 - Indus Valley Cement (Pvt) Ltd | V13: 3398761-2 | W13: Active Filer | X13: No | Y13: Rizwan Akhtar - 0302-4418823 | Z13: MCB Bank Ltd - 0876-5501234401 | AA13: Credit 15 days | AB13: 0 | AC13: PO-2411-2 | AD13: 09-Nov-2024 / PKR 10153000 (approx.) | AE13: SA-SUP-002-2024 | AF13: 1 | AG13: CEM-SLG-B50 | AH13: Slag Cement - 50 kg bag | AI13: Bag (50 kg) | AJ13: 4300 | AK13: 4300 | AL13: 1245 | AM13: =AK13*AL13 -> 5353500 | AN13: =AM13 -> 5353500 | AO13: =_xlfn.XLOOKUP(AG13,'T13'!$A$3:$A$1500,'T13'!$O$3:$O$1500) -> 0.18 | AP13: =AK13*IF(AI13="MT",1000,IF(AI13="Jumbo bag (1.5 MT)",1500,IF(AI13="Bag (40 kg)",40,50)))*3 -> 645000 | AQ13: =SUMIFS($AN$3:$AN$1500,$G$3:$G$1500,G13) -> 7803500 | AR13: =SUMIFS($AP$3:$AP$1500,$G$3:$G$1500,G13) -> 945000 | AS13: 153(1)(a) goods - 5% | AT13: =ROUND(BH13*0.05,0) -> 507657 | AU13: No | AV13: {=SUMPRODUCT(($G$3:$G$1500=G13)*$AN$3:$AN$1500*$AO$3:$AO$1500)+AR13} -> 2349630 | AW13: =AT13 -> 507657 | AX13: =TEXT(EOMONTH(I13,0)+15,"dd-mmm-yyyy")&" / "&IF(BM13>0,"CPR-IT-"&TEXT(I13,"yymm")&"-"&RIGHT(G13,4),"Pending payment") -> 15-Dec-2024 / CPR-IT-2411-0010 | AY13: =IF(BM13>0,"Issued","Not yet") -> Issued | AZ13: 0 | BA13: 0 | BB13: 0 | BC13: 0 | BD13: 0 | BE13: =AQ13 -> 7803500 | BF13: =AV13 -> 2349630 | BG13: =AZ13 -> 0 | BH13: =BE13+BF13+BG13 -> 10153130 | BI13: =AW13 -> 507657 | BJ13: =BA13+BB13+BC13+BD13 -> 0 | BK13: =BH13-BI13-BJ13 -> 9645473 | BL13: ="PKR "&TEXT(BK13,"#,##0")&" only" -> PKR 9,645,473 only | BM13: =SUMIFS('T10'!$AK$3:$AK$1500,'T10'!$V$3:$V$1500,G13) -> 9645473 | BN13: =BK13-BM13 -> 0 | BO13: =IF(BF13>0,TEXT(I13,"mmm-yyyy")&" sales tax return","N/A") -> Nov-2024 sales tax return | BP13: Credit 15 days | BQ13: =J13+15 -> 45641 | BR13: =BQ13 -> 45641 | BS13: IBFT | BT13: High | BU13: N/A | BV13: No | BW13: {=_xlfn.TEXTJOIN(", ",TRUE,_xlfn.UNIQUE(_xlfn._xlws.FILTER('T10'!$A$3:$A$1500,'T10'!$V$3:$V$1500=G13,"None")))} -> PV-0004 | BX13: Hassan Raza - 01-Dec-2024 | BY13: Sana Iqbal - 02-Dec-2024
A14: SUP-002 Indus Valley Cement (Pvt) Ltd (NTN 3398761-2) | B14: IVC/INV/2411/475 | C14: DRY-00010 | D14: 45628.667 | E14: Yes - SMS & email | F14: =IF(S14="Paid","Completed","Pending payment") -> Completed | G14: BB-0010 | H14: Goods purchase (cement) | I14: 45626 | J14: 45626 | K14: =TEXT(I14,"mmm-yyyy") -> Nov-2024 | L14: PKR | M14: 1 | N14: Steelstone Building Materials (Pvt) Ltd | O14: Supplier plant - direct dispatch | P14: CC-SALES-LHR | Q14: N/A | R14: 02-Dec-2024 - Email | S14: =IF(BN14<1,"Paid",IF(BM14>0,"Partially paid",IF(ISNUMBER(SEARCH("hold",BU14)),"On hold",IF(BQ14<TODAY(),"Overdue","Approved - unpaid")))) -> Paid | T14: Manufacturer / supplier | U14: SUP-002 - Indus Valley Cement (Pvt) Ltd | V14: 3398761-2 | W14: Active Filer | X14: No | Y14: Rizwan Akhtar - 0302-4418823 | Z14: MCB Bank Ltd - 0876-5501234401 | AA14: Credit 15 days | AB14: 0 | AC14: PO-2411-2 | AD14: 07-Nov-2024 / PKR 10153000 (approx.) | AE14: SA-SUP-002-2024 | AF14: 2 | AG14: CEM-PPC-B50 | AH14: Portland Pozzolana Cement - 50 kg bag | AI14: Bag (50 kg) | AJ14: 2000 | AK14: 2000 | AL14: 1225 | AM14: =AK14*AL14 -> 2450000 | AN14: =AM14 -> 2450000 | AO14: =_xlfn.XLOOKUP(AG14,'T13'!$A$3:$A$1500,'T13'!$O$3:$O$1500) -> 0.18 | AP14: =AK14*IF(AI14="MT",1000,IF(AI14="Jumbo bag (1.5 MT)",1500,IF(AI14="Bag (40 kg)",40,50)))*3 -> 300000 | AQ14: =SUMIFS($AN$3:$AN$1500,$G$3:$G$1500,G14) -> 7803500 | AR14: =SUMIFS($AP$3:$AP$1500,$G$3:$G$1500,G14) -> 945000 | AS14: 153(1)(a) goods - 5% | AT14: =ROUND(BH14*0.05,0) -> 507657 | AU14: No | AV14: {=SUMPRODUCT(($G$3:$G$1500=G14)*$AN$3:$AN$1500*$AO$3:$AO$1500)+AR14} -> 2349630 | AW14: =AT14 -> 507657 | AX14: =TEXT(EOMONTH(I14,0)+15,"dd-mmm-yyyy")&" / "&IF(BM14>0,"CPR-IT-"&TEXT(I14,"yymm")&"-"&RIGHT(G14,4),"Pending payment") -> 15-Dec-2024 / CPR-IT-2411-0010 | AY14: =IF(BM14>0,"Issued","Not yet") -> Issued | AZ14: 0 | BA14: 0 | BB14: 0 | BC14: 0 | BD14: 0 | BE14: =AQ14 -> 7803500 | BF14: =AV14 -> 2349630 | BG14: =AZ14 -> 0 | BH14: =BE14+BF14+BG14 -> 10153130 | BI14: =AW14 -> 507657 | BJ14: =BA14+BB14+BC14+BD14 -> 0 | BK14: =BH14-BI14-BJ14 -> 9645473 | BL14: ="PKR "&TEXT(BK14,"#,##0")&" only" -> PKR 9,645,473 only | BM14: =SUMIFS('T10'!$AK$3:$AK$1500,'T10'!$V$3:$V$1500,G14) -> 9645473 | BN14: =BK14-BM14 -> 0 | BO14: =IF(BF14>0,TEXT(I14,"mmm-yyyy")&" sales tax return","N/A") -> Nov-2024 sales tax return | BP14: Credit 15 days | BQ14: =J14+15 -> 45641 | BR14: =BQ14 -> 45641 | BS14: IBFT | BT14: High | BU14: N/A | BV14: No | BW14: {=_xlfn.TEXTJOIN(", ",TRUE,_xlfn.UNIQUE(_xlfn._xlws.FILTER('T10'!$A$3:$A$1500,'T10'!$V$3:$V$1500=G14,"None")))} -> PV-0004 | BX14: Hassan Raza - 01-Dec-2024 | BY14: Sana Iqbal - 02-Dec-2024
A15: SUP-001 Margalla Cement Ltd (NTN 0712345-6) | B15: MCL/INV/2411/182 | C15: DRY-00011 | D15: 45628.417 | E15: Yes - SMS & email | F15: =IF(S15="Paid","Completed","Pending payment") -> Completed | G15: BB-0011 | H15: Goods purchase (cement) | I15: 45626 | J15: 45626 | K15: =TEXT(I15,"mmm-yyyy") -> Nov-2024 | L15: PKR | M15: 1 | N15: Steelstone Building Materials (Pvt) Ltd | O15: Supplier plant - direct dispatch | P15: CC-SALES-LHR | Q15: N/A | R15: 02-Dec-2024 - Email | S15: =IF(BN15<1,"Paid",IF(BM15>0,"Partially paid",IF(ISNUMBER(SEARCH("hold",BU15)),"On hold",IF(BQ15<TODAY(),"Overdue","Approved - unpaid")))) -> Paid | T15: Manufacturer / supplier | U15: SUP-001 - Margalla Cement Ltd | V15: 0712345-6 | W15: Active Filer | X15: No | Y15: Shahid Iqbal - 0300-8451290 | Z15: Habib Bank Ltd - 1234-79001122-03 | AA15: Credit 15 days | AB15: 0 | AC15: PO-2411-1 | AD15: 18-Nov-2024 / PKR 503000 (approx.) | AE15: SA-SUP-001-2024 | AF15: 1 | AG15: CEM-OPC-B50 | AH15: OPC Cement Grade 53 - 50 kg bag | AI15: Bag (50 kg) | AJ15: 300 | AK15: 300 | AL15: 1295 | AM15: =AK15*AL15 -> 388500 | AN15: =AM15 -> 388500 | AO15: =_xlfn.XLOOKUP(AG15,'T13'!$A$3:$A$1500,'T13'!$O$3:$O$1500) -> 0.18 | AP15: =AK15*IF(AI15="MT",1000,IF(AI15="Jumbo bag (1.5 MT)",1500,IF(AI15="Bag (40 kg)",40,50)))*3 -> 45000 | AQ15: =SUMIFS($AN$3:$AN$1500,$G$3:$G$1500,G15) -> 388500 | AR15: =SUMIFS($AP$3:$AP$1500,$G$3:$G$1500,G15) -> 45000 | AS15: 153(1)(a) goods - 5% | AT15: =ROUND(BH15*0.05,0) -> 25172 | AU15: No | AV15: {=SUMPRODUCT(($G$3:$G$1500=G15)*$AN$3:$AN$1500*$AO$3:$AO$1500)+AR15} -> 114930 | AW15: =AT15 -> 25172 | AX15: =TEXT(EOMONTH(I15,0)+15,"dd-mmm-yyyy")&" / "&IF(BM15>0,"CPR-IT-"&TEXT(I15,"yymm")&"-"&RIGHT(G15,4),"Pending payment") -> 15-Dec-2024 / CPR-IT-2411-0011 | AY15: =IF(BM15>0,"Issued","Not yet") -> Issued | AZ15: 0 | BA15: 0 | BB15: 0 | BC15: 0 | BD15: 0 | BE15: =AQ15 -> 388500 | BF15: =AV15 -> 114930 | BG15: =AZ15 -> 0 | BH15: =BE15+BF15+BG15 -> 503430 | BI15: =AW15 -> 25172 | BJ15: =BA15+BB15+BC15+BD15 -> 0 | BK15: =BH15-BI15-BJ15 -> 478258 | BL15: ="PKR "&TEXT(BK15,"#,##0")&" only" -> PKR 478,258 only | BM15: =SUMIFS('T10'!$AK$3:$AK$1500,'T10'!$V$3:$V$1500,G15) -> 478258 | BN15: =BK15-BM15 -> 0 | BO15: =IF(BF15>0,TEXT(I15,"mmm-yyyy")&" sales tax return","N/A") -> Nov-2024 sales tax return | BP15: Credit 15 days | BQ15: =J15+15 -> 45641 | BR15: =BQ15 -> 45641 | BS15: IBFT | BT15: High | BU15: N/A | BV15: No | BW15: {=_xlfn.TEXTJOIN(", ",TRUE,_xlfn.UNIQUE(_xlfn._xlws.FILTER('T10'!$A$3:$A$1500,'T10'!$V$3:$V$1500=G15,"None")))} -> PV-0001 | BX15: Hassan Raza - 01-Dec-2024 | BY15: Sana Iqbal - 02-Dec-2024
A16: TRN-002 Al-Madina Logistics (Pvt) Ltd (NTN 5567123-4) | B16: FB-TRN002-2411 | C16: DRY-00012 | D16: 45629.583 | E16: Yes - SMS & email | F16: =IF(S16="Paid","Completed","Pending payment") -> Completed | G16: BB-0012 | H16: Freight / transport | I16: 45629 | J16: 45627 | K16: =TEXT(I16,"mmm-yyyy") -> Dec-2024 | L16: PKR | M16: 1 | N16: Steelstone Building Materials (Pvt) Ltd | O16: Head office - Lahore | P16: CC-LOG | Q16: N/A | R16: 03-Dec-2024 - By hand | S16: =IF(BN16<1,"Paid",IF(BM16>0,"Partially paid",IF(ISNUMBER(SEARCH("hold",BU16)),"On hold",IF(BQ16<TODAY(),"Overdue","Approved - unpaid")))) -> Paid | T16: Transporter | U16: TRN-002 - Al-Madina Logistics (Pvt) Ltd | V16: 5567123-4 | W16: Active Filer | X16: No | Y16: Tahir Mehmood - 0321-4789012 | Z16: MCB Bank Ltd - 0654-7701122301 | AA16: Credit 30 days | AB16: 0 | AC16: N/A | AD16: N/A | AE16: TC-TRN-002-2024 | AF16: 1 | AG16: SRV-FRT-BAG | AH16: Freight - bagged cement per trip | AI16: Trip | AJ16: =COUNTIFS('T14'!$AQ$3:$AQ$1500,B16,'T14'!$Z$3:$Z$1500,1,'T14'!$F$3:$F$1500,"Bag") -> 5 | AK16: =AJ16 -> 5 | AL16: 38200 | AM16: =AK16*AL16 -> 191000 | AN16: =AM16 -> 191000 | AO16: =_xlfn.XLOOKUP(AG16,'T13'!$A$3:$A$1500,'T13'!$O$3:$O$1500) -> 0.16 | AP16: 0 | AQ16: =SUMIFS($AN$3:$AN$1500,$G$3:$G$1500,G16) -> 191000 | AR16: =SUMIFS($AP$3:$AP$1500,$G$3:$G$1500,G16) -> 0 | AS16: 153(1)(b) transport - 4% | AT16: =ROUND(BH16*0.04,0) -> 9222 | AU16: No | AV16: {=SUMPRODUCT(($G$3:$G$1500=G16)*$AN$3:$AN$1500*$AO$3:$AO$1500)+AR16} -> 30560 | AW16: =AT16 -> 9222 | AX16: =TEXT(EOMONTH(I16,0)+15,"dd-mmm-yyyy")&" / "&IF(BM16>0,"CPR-IT-"&TEXT(I16,"yymm")&"-"&RIGHT(G16,4),"Pending payment") -> 15-Jan-2025 / CPR-IT-2412-0012 | AY16: =IF(BM16>0,"Issued","Not yet") -> Issued | AZ16: 9000 | BA16: 0 | BB16: 0 | BC16: 0 | BD16: 0 | BE16: =AQ16 -> 191000 | BF16: =AV16 -> 30560 | BG16: =AZ16 -> 9000 | BH16: =BE16+BF16+BG16 -> 230560 | BI16: =AW16 -> 9222 | BJ16: =BA16+BB16+BC16+BD16 -> 0 | BK16: =BH16-BI16-BJ16 -> 221338 | BL16: ="PKR "&TEXT(BK16,"#,##0")&" only" -> PKR 221,338 only | BM16: =SUMIFS('T10'!$AK$3:$AK$1500,'T10'!$V$3:$V$1500,G16) -> 221338 | BN16: =BK16-BM16 -> 0 | BO16: =IF(BF16>0,TEXT(I16,"mmm-yyyy")&" sales tax return","N/A") -> Dec-2024 sales tax return | BP16: Credit 30 days | BQ16: =J16+30 -> 45657 | BR16: =BQ16 -> 45657 | BS16: IBFT | BT16: Normal | BU16: N/A | BV16: No | BW16: {=_xlfn.TEXTJOIN(", ",TRUE,_xlfn.UNIQUE(_xlfn._xlws.FILTER('T10'!$A$3:$A$1500,'T10'!$V$3:$V$1500=G16,"None")))} -> PV-0003 | BX16: Hassan Raza - 04-Dec-2024 | BY16: Sana Iqbal - 05-Dec-2024
A17: TRN-001 Khan Goods Transport Co (NTN 17301-5567812-9 (CNIC)) | B17: FB-TRN001-2411 | C17: DRY-00013 | D17: 45628.667 | E17: Yes - SMS & email | F17: =IF(S17="Paid","Completed","Pending payment") -> Completed | G17: BB-0013 | H17: Freight / transport | I17: 45629 | J17: 45627 | K17: =TEXT(I17,"mmm-yyyy") -> Dec-2024 | L17: PKR | M17: 1 | N17: Steelstone Building Materials (Pvt) Ltd | O17: Head office - Lahore | P17: CC-LOG | Q17: N/A | R17: 02-Dec-2024 - By hand | S17: =IF(BN17<1,"Paid",IF(BM17>0,"Partially paid",IF(ISNUMBER(SEARCH("hold",BU17)),"On hold",IF(BQ17<TODAY(),"Overdue","Approved - unpaid")))) -> Paid | T17: Transporter | U17: TRN-001 - Khan Goods Transport Co | V17: 17301-5567812-9 (CNIC) | W17: Active Filer | X17: No | Y17: Gul Khan - 0300-5991287 | Z17: Habib Bank Ltd - 2210-79004455-01 | AA17: Credit 30 days | AB17: 0 | AC17: N/A | AD17: N/A | AE17: TC-TRN-001-2024 | AF17: 1 | AG17: SRV-FRT-BAG | AH17: Freight - bagged cement per trip | AI17: Trip | AJ17: =COUNTIFS('T14'!$AQ$3:$AQ$1500,B17,'T14'!$Z$3:$Z$1500,1,'T14'!$F$3:$F$1500,"Bag") -> 6 | AK17: =AJ17 -> 6 | AL17: 38200 | AM17: =AK17*AL17 -> 229200 | AN17: =AM17 -> 229200 | AO17: =_xlfn.XLOOKUP(AG17,'T13'!$A$3:$A$1500,'T13'!$O$3:$O$1500) -> 0.16 | AP17: 0 | AQ17: =SUMIFS($AN$3:$AN$1500,$G$3:$G$1500,G17) -> 229200 | AR17: =SUMIFS($AP$3:$AP$1500,$G$3:$G$1500,G17) -> 0 | AS17: 153(1)(b) transport - 4% | AT17: =ROUND(BH17*0.04,0) -> 10635 | AU17: No | AV17: {=SUMPRODUCT(($G$3:$G$1500=G17)*$AN$3:$AN$1500*$AO$3:$AO$1500)+AR17} -> 36672 | AW17: =AT17 -> 10635 | AX17: =TEXT(EOMONTH(I17,0)+15,"dd-mmm-yyyy")&" / "&IF(BM17>0,"CPR-IT-"&TEXT(I17,"yymm")&"-"&RIGHT(G17,4),"Pending payment") -> 15-Jan-2025 / CPR-IT-2412-0013 | AY17: =IF(BM17>0,"Issued","Not yet") -> Issued | AZ17: 0 | BA17: 0 | BB17: 0 | BC17: 0 | BD17: 0 | BE17: =AQ17 -> 229200 | BF17: =AV17 -> 36672 | BG17: =AZ17 -> 0 | BH17: =BE17+BF17+BG17 -> 265872 | BI17: =AW17 -> 10635 | BJ17: =BA17+BB17+BC17+BD17 -> 0 | BK17: =BH17-BI17-BJ17 -> 255237 | BL17: ="PKR "&TEXT(BK17,"#,##0")&" only" -> PKR 255,237 only | BM17: =SUMIFS('T10'!$AK$3:$AK$1500,'T10'!$V$3:$V$1500,G17) -> 255237 | BN17: =BK17-BM17 -> 0 | BO17: =IF(BF17>0,TEXT(I17,"mmm-yyyy")&" sales tax return","N/A") -> Dec-2024 sales tax return | BP17: Credit 30 days | BQ17: =J17+30 -> 45657 | BR17: =BQ17 -> 45657 | BS17: IBFT | BT17: Normal | BU17: N/A | BV17: No | BW17: {=_xlfn.TEXTJOIN(", ",TRUE,_xlfn.UNIQUE(_xlfn._xlws.FILTER('T10'!$A$3:$A$1500,'T10'!$V$3:$V$1500=G17,"None")))} -> PV-0005 | BX17: Hassan Raza - 04-Dec-2024 | BY17: Sana Iqbal - 05-Dec-2024
A18: VEN-107 Al-Noor Printers (NTN 35201-9922113-7 (CNIC)) | B18: 107/2412/7414 | C18: DRY-00014 | D18: 45634.375 | E18: Yes - SMS & email | F18: =IF(S18="Paid","Completed","Pending payment") -> Completed | G18: BB-0014 | H18: Goods - stationery | I18: 45635 | J18: 45633 | K18: =TEXT(I18,"mmm-yyyy") -> Dec-2024 | L18: PKR | M18: 1 | N18: Steelstone Building Materials (Pvt) Ltd | O18: Head office - Lahore | P18: CC-ADMIN | Q18: N/A | R18: 08-Dec-2024 - Email | S18: =IF(BN18<1,"Paid",IF(BM18>0,"Partially paid",IF(ISNUMBER(SEARCH("hold",BU18)),"On hold",IF(BQ18<TODAY(),"Overdue","Approved - unpaid")))) -> Paid | T18: Other vendor - Goods - stationery | U18: VEN-107 - Al-Noor Printers | V18: 35201-9922113-7 (CNIC) | W18: Active Filer | X18: No | Y18: Accounts desk - 042-35471673 | Z18: MCB - 5110-1855303 | AA18: Credit 30 days | AB18: 0 | AC18: PO-2412-906 | AD18: 12-Nov-2024 / PKR 18000 (approx.) | AE18: N/A | AF18: 1 | AG18: CON-STN | AH18: Stationery & printed challan books | AI18: Lot | AJ18: 1 | AK18: 1 | AL18: 15120 | AM18: =AK18*AL18 -> 15120 | AN18: =AM18 -> 15120 | AO18: =_xlfn.XLOOKUP(AG18,'T13'!$A$3:$A$1500,'T13'!$O$3:$O$1500) -> 0.18 | AP18: 0 | AQ18: =SUMIFS($AN$3:$AN$1500,$G$3:$G$1500,G18) -> 15120 | AR18: =SUMIFS($AP$3:$AP$1500,$G$3:$G$1500,G18) -> 0 | AS18: 153(1)(a) goods - 5% | AT18: =ROUND(BH18*0.05,0) -> 892 | AU18: No | AV18: {=SUMPRODUCT(($G$3:$G$1500=G18)*$AN$3:$AN$1500*$AO$3:$AO$1500)+AR18} -> 2721.6 | AW18: =AT18 -> 892 | AX18: =TEXT(EOMONTH(I18,0)+15,"dd-mmm-yyyy")&" / "&IF(BM18>0,"CPR-IT-"&TEXT(I18,"yymm")&"-"&RIGHT(G18,4),"Pending payment") -> 15-Jan-2025 / CPR-IT-2412-0014 | AY18: =IF(BM18>0,"Issued","Not yet") -> Issued | AZ18: 0 | BA18: 0 | BB18: 0 | BC18: 0 | BD18: 0 | BE18: =AQ18 -> 15120 | BF18: =AV18 -> 2721.6 | BG18: =AZ18 -> 0 | BH18: =BE18+BF18+BG18 -> 17841.6 | BI18: =AW18 -> 892 | BJ18: =BA18+BB18+BC18+BD18 -> 0 | BK18: =BH18-BI18-BJ18 -> 16949.6 | BL18: ="PKR "&TEXT(BK18,"#,##0")&" only" -> PKR 16,950 only | BM18: =SUMIFS('T10'!$AK$3:$AK$1500,'T10'!$V$3:$V$1500,G18) -> 16949.6 | BN18: =BK18-BM18 -> 0 | BO18: =IF(BF18>0,TEXT(I18,"mmm-yyyy")&" sales tax return","N/A") -> Dec-2024 sales tax return | BP18: Credit 30 days | BQ18: =J18+30 -> 45663 | BR18: =BQ18 -> 45663 | BS18: IBFT | BT18: Normal | BU18: N/A | BV18: No | BW18: {=_xlfn.TEXTJOIN(", ",TRUE,_xlfn.UNIQUE(_xlfn._xlws.FILTER('T10'!$A$3:$A$1500,'T10'!$V$3:$V$1500=G18,"None")))} -> PV-0038 | BX18: Hassan Raza - 10-Dec-2024 | BY18: Sana Iqbal - 11-Dec-2024
A19: VEN-106 Ghani Tyre & Lubricants (NTN 35202-1188776-5 (CNIC)) | B19: 106/2412/3261 | C19: DRY-00015 | D19: 45645.583 | E19: Yes - SMS & email | F19: =IF(S19="Paid","Completed","Pending payment") -> Completed | G19: BB-0015 | H19: Goods - spares | I19: 45645 | J19: 45643 | K19: =TEXT(I19,"mmm-yyyy") -> Dec-2024 | L19: PKR | M19: 1 | N19: Steelstone Building Materials (Pvt) Ltd | O19: Head office - Lahore | P19: CC-LOG | Q19: N/A | R19: 19-Dec-2024 - Email | S19: =IF(BN19<1,"Paid",IF(BM19>0,"Partially paid",IF(ISNUMBER(SEARCH("hold",BU19)),"On hold",IF(BQ19<TODAY(),"Overdue","Approved - unpaid")))) -> Paid | T19: Other vendor - Goods - spares | U19: VEN-106 - Ghani Tyre & Lubricants | V19: 35202-1188776-5 (CNIC) | W19: Active Filer | X19: No | Y19: Accounts desk - 042-35386602 | Z19: UBL - 6713-9542407 | AA19: Credit 30 days | AB19: 0 | AC19: PO-2412-905 | AD19: 29-Nov-2024 / PKR 525000 (approx.) | AE19: N/A | AF19: 1 | AG19: SPR-TYR | AH19: Truck tyre 1000-20 (18 ply) | AI19: Each | AJ19: 6 | AK19: 6 | AL19: 68540 | AM19: =AK19*AL19 -> 411240 | AN19: =AM19 -> 411240 | AO19: =_xlfn.XLOOKUP(AG19,'T13'!$A$3:$A$1500,'T13'!$O$3:$O$1500) -> 0.18 | AP19: 0 | AQ19: =SUMIFS($AN$3:$AN$1500,$G$3:$G$1500,G19) -> 444500 | AR19: =SUMIFS($AP$3:$AP$1500,$G$3:$G$1500,G19) -> 0 | AS19: 153(1)(a) goods - 5% | AT19: =ROUND(BH19*0.05,0) -> 26226 | AU19: No | AV19: {=SUMPRODUCT(($G$3:$G$1500=G19)*$AN$3:$AN$1500*$AO$3:$AO$1500)+AR19} -> 80010 | AW19: =AT19 -> 26226 | AX19: =TEXT(EOMONTH(I19,0)+15,"dd-mmm-yyyy")&" / "&IF(BM19>0,"CPR-IT-"&TEXT(I19,"yymm")&"-"&RIGHT(G19,4),"Pending payment") -> 15-Jan-2025 / CPR-IT-2412-0015 | AY19: =IF(BM19>0,"Issued","Not yet") -> Issued | AZ19: 0 | BA19: 0 | BB19: 0 | BC19: 0 | BD19: 0 | BE19: =AQ19 -> 444500 | BF19: =AV19 -> 80010 | BG19: =AZ19 -> 0 | BH19: =BE19+BF19+BG19 -> 524510 | BI19: =AW19 -> 26226 | BJ19: =BA19+BB19+BC19+BD19 -> 0 | BK19: =BH19-BI19-BJ19 -> 498284 | BL19: ="PKR "&TEXT(BK19,"#,##0")&" only" -> PKR 498,284 only | BM19: =SUMIFS('T10'!$AK$3:$AK$1500,'T10'!$V$3:$V$1500,G19) -> 498284 | BN19: =BK19-BM19 -> 0 | BO19: =IF(BF19>0,TEXT(I19,"mmm-yyyy")&" sales tax return","N/A") -> Dec-2024 sales tax return | BP19: Credit 30 days | BQ19: =J19+30 -> 45673 | BR19: =BQ19 -> 45673 | BS19: IBFT | BT19: Normal | BU19: N/A | BV19: No | BW19: {=_xlfn.TEXTJOIN(", ",TRUE,_xlfn.UNIQUE(_xlfn._xlws.FILTER('T10'!$A$3:$A$1500,'T10'!$V$3:$V$1500=G19,"None")))} -> PV-0039 | BX19: Hassan Raza - 20-Dec-2024 | BY19: Sana Iqbal - 21-Dec-2024
A20: VEN-106 Ghani Tyre & Lubricants (NTN 35202-1188776-5 (CNIC)) | B20: 106/2412/3261 | C20: DRY-00015 | D20: 45645.583 | E20: Yes - SMS & email | F20: =IF(S20="Paid","Completed","Pending payment") -> Completed | G20: BB-0015 | H20: Goods - spares | I20: 45645 | J20: 45643 | K20: =TEXT(I20,"mmm-yyyy") -> Dec-2024 | L20: PKR | M20: 1 | N20: Steelstone Building Materials (Pvt) Ltd | O20: Head office - Lahore | P20: CC-LOG | Q20: N/A | R20: 19-Dec-2024 - Email | S20: =IF(BN20<1,"Paid",IF(BM20>0,"Partially paid",IF(ISNUMBER(SEARCH("hold",BU20)),"On hold",IF(BQ20<TODAY(),"Overdue","Approved - unpaid")))) -> Paid | T20: Other vendor - Goods - spares | U20: VEN-106 - Ghani Tyre & Lubricants | V20: 35202-1188776-5 (CNIC) | W20: Active Filer | X20: No | Y20: Accounts desk - 042-35386602 | Z20: UBL - 6713-9542407 | AA20: Credit 30 days | AB20: 0 | AC20: PO-2412-905 | AD20: 04-Dec-2024 / PKR 525000 (approx.) | AE20: N/A | AF20: 2 | AG20: SPR-OIL | AH20: Engine oil 15W-40 - 20 L can | AI20: Can | AJ20: 2 | AK20: 2 | AL20: 16630 | AM20: =AK20*AL20 -> 33260 | AN20: =AM20 -> 33260 | AO20: =_xlfn.XLOOKUP(AG20,'T13'!$A$3:$A$1500,'T13'!$O$3:$O$1500) -> 0.18 | AP20: 0 | AQ20: =SUMIFS($AN$3:$AN$1500,$G$3:$G$1500,G20) -> 444500 | AR20: =SUMIFS($AP$3:$AP$1500,$G$3:$G$1500,G20) -> 0 | AS20: 153(1)(a) goods - 5% | AT20: =ROUND(BH20*0.05,0) -> 26226 | AU20: No | AV20: {=SUMPRODUCT(($G$3:$G$1500=G20)*$AN$3:$AN$1500*$AO$3:$AO$1500)+AR20} -> 80010 | AW20: =AT20 -> 26226 | AX20: =TEXT(EOMONTH(I20,0)+15,"dd-mmm-yyyy")&" / "&IF(BM20>0,"CPR-IT-"&TEXT(I20,"yymm")&"-"&RIGHT(G20,4),"Pending payment") -> 15-Jan-2025 / CPR-IT-2412-0015 | AY20: =IF(BM20>0,"Issued","Not yet") -> Issued | AZ20: 0 | BA20: 0 | BB20: 0 | BC20: 0 | BD20: 0 | BE20: =AQ20 -> 444500 | BF20: =AV20 -> 80010 | BG20: =AZ20 -> 0 | BH20: =BE20+BF20+BG20 -> 524510 | BI20: =AW20 -> 26226 | BJ20: =BA20+BB20+BC20+BD20 -> 0 | BK20: =BH20-BI20-BJ20 -> 498284 | BL20: ="PKR "&TEXT(BK20,"#,##0")&" only" -> PKR 498,284 only | BM20: =SUMIFS('T10'!$AK$3:$AK$1500,'T10'!$V$3:$V$1500,G20) -> 498284 | BN20: =BK20-BM20 -> 0 | BO20: =IF(BF20>0,TEXT(I20,"mmm-yyyy")&" sales tax return","N/A") -> Dec-2024 sales tax return | BP20: Credit 30 days | BQ20: =J20+30 -> 45673 | BR20: =BQ20 -> 45673 | BS20: IBFT | BT20: Normal | BU20: N/A | BV20: No | BW20: {=_xlfn.TEXTJOIN(", ",TRUE,_xlfn.UNIQUE(_xlfn._xlws.FILTER('T10'!$A$3:$A$1500,'T10'!$V$3:$V$1500=G20,"None")))} -> PV-0039 | BX20: Hassan Raza - 20-Dec-2024 | BY20: Sana Iqbal - 21-Dec-2024
A21: VEN-108 Punjab Timber Works (NTN 6612098-1) | B21: 108/2412/6671 | C21: DRY-00016 | D21: 45646.708 | E21: Yes - SMS & email | F21: =IF(S21="Paid","Completed","Pending payment") -> Completed | G21: BB-0016 | H21: Goods - consumables | I21: 45647 | J21: 45645 | K21: =TEXT(I21,"mmm-yyyy") -> Dec-2024 | L21: PKR | M21: 1 | N21: Steelstone Building Materials (Pvt) Ltd | O21: Raiwind Road warehouse | P21: CC-WH | Q21: N/A | R21: 20-Dec-2024 - Email | S21: =IF(BN21<1,"Paid",IF(BM21>0,"Partially paid",IF(ISNUMBER(SEARCH("hold",BU21)),"On hold",IF(BQ21<TODAY(),"Overdue","Approved - unpaid")))) -> Paid | T21: Other vendor - Goods - consumables | U21: VEN-108 - Punjab Timber Works | V21: 6612098-1 | W21: Active Filer | X21: No | Y21: Accounts desk - 042-35231500 | Z21: Meezan - 3873-3050891 | AA21: Credit 30 days | AB21: 0 | AC21: PO-2412-907 | AD21: 05-Dec-2024 / PKR 105000 (approx.) | AE21: N/A | AF21: 1 | AG21: CON-PAL | AH21: Wooden pallet 1200 x 1000 mm | AI21: Each | AJ21: 22 | AK21: 22 | AL21: 2820 | AM21: =AK21*AL21 -> 62040 | AN21: =AM21 -> 62040 | AO21: =_xlfn.XLOOKUP(AG21,'T13'!$A$3:$A$1500,'T13'!$O$3:$O$1500) -> 0.18 | AP21: 0 | AQ21: =SUMIFS($AN$3:$AN$1500,$G$3:$G$1500,G21) -> 89040 | AR21: =SUMIFS($AP$3:$AP$1500,$G$3:$G$1500,G21) -> 0 | AS21: 153(1)(a) goods - 5% | AT21: =ROUND(BH21*0.05,0) -> 5253 | AU21: No | AV21: {=SUMPRODUCT(($G$3:$G$1500=G21)*$AN$3:$AN$1500*$AO$3:$AO$1500)+AR21} -> 16027.2 | AW21: =AT21 -> 5253 | AX21: =TEXT(EOMONTH(I21,0)+15,"dd-mmm-yyyy")&" / "&IF(BM21>0,"CPR-IT-"&TEXT(I21,"yymm")&"-"&RIGHT(G21,4),"Pending payment") -> 15-Jan-2025 / CPR-IT-2412-0016 | AY21: =IF(BM21>0,"Issued","Not yet") -> Issued | AZ21: 0 | BA21: 0 | BB21: 0 | BC21: 0 | BD21: 0 | BE21: =AQ21 -> 89040 | BF21: =AV21 -> 16027.2 | BG21: =AZ21 -> 0 | BH21: =BE21+BF21+BG21 -> 105067.2 | BI21: =AW21 -> 5253 | BJ21: =BA21+BB21+BC21+BD21 -> 0 | BK21: =BH21-BI21-BJ21 -> 99814.2 | BL21: ="PKR "&TEXT(BK21,"#,##0")&" only" -> PKR 99,814 only | BM21: =SUMIFS('T10'!$AK$3:$AK$1500,'T10'!$V$3:$V$1500,G21) -> 99814.2 | BN21: =BK21-BM21 -> 0 | BO21: =IF(BF21>0,TEXT(I21,"mmm-yyyy")&" sales tax return","N/A") -> Dec-2024 sales tax return | BP21: Credit 30 days | BQ21: =J21+30 -> 45675 | BR21: =BQ21 -> 45675 | BS21: IBFT | BT21: Normal | BU21: N/A | BV21: No | BW21: {=_xlfn.TEXTJOIN(", ",TRUE,_xlfn.UNIQUE(_xlfn._xlws.FILTER('T10'!$A$3:$A$1500,'T10'!$V$3:$V$1500=G21,"None")))} -> PV-0044 | BX21: Hassan Raza - 22-Dec-2024 | BY21: Sana Iqbal - 23-Dec-2024
A22: VEN-108 Punjab Timber Works (NTN 6612098-1) | B22: 108/2412/6671 | C22: DRY-00016 | D22: 45646.708 | E22: Yes - SMS & email | F22: =IF(S22="Paid","Completed","Pending payment") -> Completed | G22: BB-0016 | H22: Goods - consumables | I22: 45647 | J22: 45645 | K22: =TEXT(I22,"mmm-yyyy") -> Dec-2024 | L22: PKR | M22: 1 | N22: Steelstone Building Materials (Pvt) Ltd | O22: Raiwind Road warehouse | P22: CC-WH | Q22: N/A | R22: 20-Dec-2024 - Email | S22: =IF(BN22<1,"Paid",IF(BM22>0,"Partially paid",IF(ISNUMBER(SEARCH("hold",BU22)),"On hold",IF(BQ22<TODAY(),"Overdue","Approved - unpaid")))) -> Paid | T22: Other vendor - Goods - consumables | U22: VEN-108 - Punjab Timber Works | V22: 6612098-1 | W22: Active Filer | X22: No | Y22: Accounts desk - 042-35231500 | Z22: Meezan - 3873-3050891 | AA22: Credit 30 days | AB22: 0 | AC22: PO-2412-907 | AD22: 06-Dec-2024 / PKR 105000 (approx.) | AE22: N/A | AF22: 2 | AG22: CON-TARP | AH22: Tarpaulin sheet 20 x 30 ft | AI22: Each | AJ22: 6 | AK22: 6 | AL22: 4500 | AM22: =AK22*AL22 -> 27000 | AN22: =AM22 -> 27000 | AO22: =_xlfn.XLOOKUP(AG22,'T13'!$A$3:$A$1500,'T13'!$O$3:$O$1500) -> 0.18 | AP22: 0 | AQ22: =SUMIFS($AN$3:$AN$1500,$G$3:$G$1500,G22) -> 89040 | AR22: =SUMIFS($AP$3:$AP$1500,$G$3:$G$1500,G22) -> 0 | AS22: 153(1)(a) goods - 5% | AT22: =ROUND(BH22*0.05,0) -> 5253 | AU22: No | AV22: {=SUMPRODUCT(($G$3:$G$1500=G22)*$AN$3:$AN$1500*$AO$3:$AO$1500)+AR22} -> 16027.2 | AW22: =AT22 -> 5253 | AX22: =TEXT(EOMONTH(I22,0)+15,"dd-mmm-yyyy")&" / "&IF(BM22>0,"CPR-IT-"&TEXT(I22,"yymm")&"-"&RIGHT(G22,4),"Pending payment") -> 15-Jan-2025 / CPR-IT-2412-0016 | AY22: =IF(BM22>0,"Issued","Not yet") -> Issued | AZ22: 0 | BA22: 0 | BB22: 0 | BC22: 0 | BD22: 0 | BE22: =AQ22 -> 89040 | BF22: =AV22 -> 16027.2 | BG22: =AZ22 -> 0 | BH22: =BE22+BF22+BG22 -> 105067.2 | BI22: =AW22 -> 5253 | BJ22: =BA22+BB22+BC22+BD22 -> 0 | BK22: =BH22-BI22-BJ22 -> 99814.2 | BL22: ="PKR "&TEXT(BK22,"#,##0")&" only" -> PKR 99,814 only | BM22: =SUMIFS('T10'!$AK$3:$AK$1500,'T10'!$V$3:$V$1500,G22) -> 99814.2 | BN22: =BK22-BM22 -> 0 | BO22: =IF(BF22>0,TEXT(I22,"mmm-yyyy")&" sales tax return","N/A") -> Dec-2024 sales tax return | BP22: Credit 30 days | BQ22: =J22+30 -> 45675 | BR22: =BQ22 -> 45675 | BS22: IBFT | BT22: Normal | BU22: N/A | BV22: No | BW22: {=_xlfn.TEXTJOIN(", ",TRUE,_xlfn.UNIQUE(_xlfn._xlws.FILTER('T10'!$A$3:$A$1500,'T10'!$V$3:$V$1500=G22,"None")))} -> PV-0044 | BX22: Hassan Raza - 22-Dec-2024 | BY22: Sana Iqbal - 23-Dec-2024
A23: SUP-001 Margalla Cement Ltd (NTN 0712345-6) | B23: MCL/INV/2412/277 | C23: DRY-00017 | D23: 45658.375 | E23: Yes - SMS & email | F23: =IF(S23="Paid","Completed","Pending payment") -> Completed | G23: BB-0017 | H23: Goods purchase (cement) | I23: 45657 | J23: 45657 | K23: =TEXT(I23,"mmm-yyyy") -> Dec-2024 | L23: PKR | M23: 1 | N23: Steelstone Building Materials (Pvt) Ltd | O23: Supplier plant - direct dispatch | P23: CC-SALES-LHR | Q23: N/A | R23: 01-Jan-2025 - Email | S23: =IF(BN23<1,"Paid",IF(BM23>0,"Partially paid",IF(ISNUMBER(SEARCH("hold",BU23)),"On hold",IF(BQ23<TODAY(),"Overdue","Approved - unpaid")))) -> Paid | T23: Manufacturer / supplier | U23: SUP-001 - Margalla Cement Ltd | V23: 0712345-6 | W23: Active Filer | X23: No | Y23: Shahid Iqbal - 0300-8451290 | Z23: Habib Bank Ltd - 1234-79001122-03 | AA23: Credit 15 days | AB23: 0 | AC23: PO-2412-1 | AD23: 13-Dec-2024 / PKR 7814000 (approx.) | AE23: SA-SUP-001-2024 | AF23: 1 | AG23: CEM-OPC-BLK | AH23: OPC Cement Grade 53 - bulk | AI23: MT | AJ23: 240 | AK23: 240 | AL23: 25050 | AM23: =AK23*AL23 -> 6012000 | AN23: =AM23 -> 6012000 | AO23: =_xlfn.XLOOKUP(AG23,'T13'!$A$3:$A$1500,'T13'!$O$3:$O$1500) -> 0.18 | AP23: =AK23*IF(AI23="MT",1000,IF(AI23="Jumbo bag (1.5 MT)",1500,IF(AI23="Bag (40 kg)",40,50)))*3 -> 720000 | AQ23: =SUMIFS($AN$3:$AN$1500,$G$3:$G$1500,G23) -> 6012000 | AR23: =SUMIFS($AP$3:$AP$1500,$G$3:$G$1500,G23) -> 720000 | AS23: 153(1)(a) goods - 5% | AT23: =ROUND(BH23*0.05,0) -> 390708 | AU23: No | AV23: {=SUMPRODUCT(($G$3:$G$1500=G23)*$AN$3:$AN$1500*$AO$3:$AO$1500)+AR23} -> 1802160 | AW23: =AT23 -> 390708 | AX23: =TEXT(EOMONTH(I23,0)+15,"dd-mmm-yyyy")&" / "&IF(BM23>0,"CPR-IT-"&TEXT(I23,"yymm")&"-"&RIGHT(G23,4),"Pending payment") -> 15-Jan-2025 / CPR-IT-2412-0017 | AY23: =IF(BM23>0,"Issued","Not yet") -> Issued | AZ23: 0 | BA23: 0 | BB23: 0 | BC23: 0 | BD23: 0 | BE23: =AQ23 -> 6012000 | BF23: =AV23 -> 1802160 | BG23: =AZ23 -> 0 | BH23: =BE23+BF23+BG23 -> 7814160 | BI23: =AW23 -> 390708 | BJ23: =BA23+BB23+BC23+BD23 -> 0 | BK23: =BH23-BI23-BJ23 -> 7423452 | BL23: ="PKR "&TEXT(BK23,"#,##0")&" only" -> PKR 7,423,452 only | BM23: =SUMIFS('T10'!$AK$3:$AK$1500,'T10'!$V$3:$V$1500,G23) -> 7423452 | BN23: =BK23-BM23 -> 0 | BO23: =IF(BF23>0,TEXT(I23,"mmm-yyyy")&" sales tax return","N/A") -> Dec-2024 sales tax return | BP23: Credit 15 days | BQ23: =J23+15 -> 45672 | BR23: =BQ23 -> 45672 | BS23: IBFT | BT23: High | BU23: N/A | BV23: No | BW23: {=_xlfn.TEXTJOIN(", ",TRUE,_xlfn.UNIQUE(_xlfn._xlws.FILTER('T10'!$A$3:$A$1500,'T10'!$V$3:$V$1500=G23,"None")))} -> PV-0001 | BX23: Hassan Raza - 01-Jan-2025 | BY23: Sana Iqbal - 02-Jan-2025
A24: TRN-003 Punjab Bulk Carriers (AOP) (NTN 4098877-2) | B24: FB-TRN003-2412 | C24: DRY-00018 | D24: 45659.667 | E24: Yes - SMS & email | F24: =IF(S24="Paid","Completed","Pending payment") -> Completed | G24: BB-0018 | H24: Freight / transport | I24: 45660 | J24: 45658 | K24: =TEXT(I24,"mmm-yyyy") -> Jan-2025 | L24: PKR | M24: 1 | N24: Steelstone Building Materials (Pvt) Ltd | O24: Head office - Lahore | P24: CC-LOG | Q24: N/A | R24: 02-Jan-2025 - By hand | S24: =IF(BN24<1,"Paid",IF(BM24>0,"Partially paid",IF(ISNUMBER(SEARCH("hold",BU24)),"On hold",IF(BQ24<TODAY(),"Overdue","Approved - unpaid")))) -> Paid | T24: Transporter | U24: TRN-003 - Punjab Bulk Carriers (AOP) | V24: 4098877-2 | W24: Inactive / Non-filer | X24: No | Y24: Sajjad Hussain - 0333-4128876 | Z24: United Bank Ltd - 0900-2201456 | AA24: Credit 30 days | AB24: 0 | AC24: N/A | AD24: N/A | AE24: TC-TRN-003-2024 | AF24: 1 | AG24: SRV-FRT-BLK | AH24: Freight - bulker per trip | AI24: Trip | AJ24: =COUNTIFS('T14'!$AQ$3:$AQ$1500,B24,'T14'!$Z$3:$Z$1500,1,'T14'!$F$3:$F$1500,"Bulker") -> 7 | AK24: =AJ24 -> 7 | AL24: 55600 | AM24: =AK24*AL24 -> 389200 | AN24: =AM24 -> 389200 | AO24: =_xlfn.XLOOKUP(AG24,'T13'!$A$3:$A$1500,'T13'!$O$3:$O$1500) -> 0.16 | AP24: 0 | AQ24: =SUMIFS($AN$3:$AN$1500,$G$3:$G$1500,G24) -> 389200 | AR24: =SUMIFS($AP$3:$AP$1500,$G$3:$G$1500,G24) -> 0 | AS24: 153(1)(b) transport - 8% (non-filer) | AT24: =ROUND(BH24*0.08,0) -> 36118 | AU24: No | AV24: {=SUMPRODUCT(($G$3:$G$1500=G24)*$AN$3:$AN$1500*$AO$3:$AO$1500)+AR24} -> 62272 | AW24: =AT24 -> 36118 | AX24: =TEXT(EOMONTH(I24,0)+15,"dd-mmm-yyyy")&" / "&IF(BM24>0,"CPR-IT-"&TEXT(I24,"yymm")&"-"&RIGHT(G24,4),"Pending payment") -> 15-Feb-2025 / CPR-IT-2501-0018 | AY24: =IF(BM24>0,"Issued","Not yet") -> Issued | AZ24: 0 | BA24: 0 | BB24: 0 | BC24: 0 | BD24: 0 | BE24: =AQ24 -> 389200 | BF24: =AV24 -> 62272 | BG24: =AZ24 -> 0 | BH24: =BE24+BF24+BG24 -> 451472 | BI24: =AW24 -> 36118 | BJ24: =BA24+BB24+BC24+BD24 -> 0 | BK24: =BH24-BI24-BJ24 -> 415354 | BL24: ="PKR "&TEXT(BK24,"#,##0")&" only" -> PKR 415,354 only | BM24: =SUMIFS('T10'!$AK$3:$AK$1500,'T10'!$V$3:$V$1500,G24) -> 415354 | BN24: =BK24-BM24 -> 0 | BO24: =IF(BF24>0,TEXT(I24,"mmm-yyyy")&" sales tax return","N/A") -> Jan-2025 sales tax return | BP24: Credit 30 days | BQ24: =J24+30 -> 45688 | BR24: =BQ24 -> 45688 | BS24: IBFT | BT24: Normal | BU24: N/A | BV24: No | BW24: {=_xlfn.TEXTJOIN(", ",TRUE,_xlfn.UNIQUE(_xlfn._xlws.FILTER('T10'!$A$3:$A$1500,'T10'!$V$3:$V$1500=G24,"None")))} -> PV-0022 | BX24: Hassan Raza - 04-Jan-2025 | BY24: Sana Iqbal - 05-Jan-2025
A25: VEN-102 Lahore Electric Supply Co (LESCO) (NTN 1234567-0) | B25: 102/2501/9863 | C25: DRY-00019 | D25: 45668.583 | E25: Yes - SMS & email | F25: =IF(S25="Paid","Completed","Pending payment") -> Completed | G25: BB-0019 | H25: Utilities | I25: 45668 | J25: 45666 | K25: =TEXT(I25,"mmm-yyyy") -> Jan-2025 | L25: PKR | M25: 1 | N25: Steelstone Building Materials (Pvt) Ltd | O25: Head office - Lahore | P25: CC-ADMIN | Q25: N/A | R25: 11-Jan-2025 - Email | S25: =IF(BN25<1,"Paid",IF(BM25>0,"Partially paid",IF(ISNUMBER(SEARCH("hold",BU25)),"On hold",IF(BQ25<TODAY(),"Overdue","Approved - unpaid")))) -> Paid | T25: Other vendor - Utilities | U25: VEN-102 - Lahore Electric Supply Co (LESCO) | V25: 1234567-0 | W25: Active Filer | X25: No | Y25: Accounts desk - 042-35960143 | Z25: HBL - 5983-5300965 | AA25: Credit 10 days | AB25: 0 | AC25: N/A | AD25: N/A | AE25: N/A | AF25: 1 | AG25: SRV-UTL | AH25: Electricity - LESCO | AI25: Month | AJ25: 1 | AK25: 1 | AL25: 86020 | AM25: =AK25*AL25 -> 86020 | AN25: =AM25 -> 86020 | AO25: =_xlfn.XLOOKUP(AG25,'T13'!$A$3:$A$1500,'T13'!$O$3:$O$1500) -> 0.18 | AP25: 0 | AQ25: =SUMIFS($AN$3:$AN$1500,$G$3:$G$1500,G25) -> 86020 | AR25: =SUMIFS($AP$3:$AP$1500,$G$3:$G$1500,G25) -> 0 | AS25: N/A - tax collected in bill | AT25: =ROUND(BH25*0,0) -> 0 | AU25: No | AV25: {=SUMPRODUCT(($G$3:$G$1500=G25)*$AN$3:$AN$1500*$AO$3:$AO$1500)+AR25} -> 15483.6 | AW25: =AT25 -> 0 | AX25: =TEXT(EOMONTH(I25,0)+15,"dd-mmm-yyyy")&" / "&IF(BM25>0,"CPR-IT-"&TEXT(I25,"yymm")&"-"&RIGHT(G25,4),"Pending payment") -> 15-Feb-2025 / CPR-IT-2501-0019 | AY25: =IF(BM25>0,"Issued","Not yet") -> Issued | AZ25: 0 | BA25: 0 | BB25: 0 | BC25: 0 | BD25: 0 | BE25: =AQ25 -> 86020 | BF25: =AV25 -> 15483.6 | BG25: =AZ25 -> 0 | BH25: =BE25+BF25+BG25 -> 101503.6 | BI25: =AW25 -> 0 | BJ25: =BA25+BB25+BC25+BD25 -> 0 | BK25: =BH25-BI25-BJ25 -> 101503.6 | BL25: ="PKR "&TEXT(BK25,"#,##0")&" only" -> PKR 101,504 only | BM25: =SUMIFS('T10'!$AK$3:$AK$1500,'T10'!$V$3:$V$1500,G25) -> 101503.6 | BN25: =BK25-BM25 -> 0 | BO25: =IF(BF25>0,TEXT(I25,"mmm-yyyy")&" sales tax return","N/A") -> Jan-2025 sales tax return | BP25: Credit 10 days | BQ25: =J25+10 -> 45676 | BR25: =BQ25 -> 45676 | BS25: IBFT | BT25: Normal | BU25: N/A | BV25: No | BW25: {=_xlfn.TEXTJOIN(", ",TRUE,_xlfn.UNIQUE(_xlfn._xlws.FILTER('T10'!$A$3:$A$1500,'T10'!$V$3:$V$1500=G25,"None")))} -> PV-0006 | BX25: Hassan Raza - 12-Jan-2025 | BY25: Sana Iqbal - 13-Jan-2025
A26: VEN-110 Quick Fix Auto Workshop (NTN 35202-5566443-1 (CNIC)) | B26: 110/2501/1229 | C26: DRY-00020 | D26: 45681.5 | E26: Yes - SMS & email | F26: =IF(S26="Paid","Completed","Pending payment") -> Completed | G26: BB-0020 | H26: Services | I26: 45681 | J26: 45679 | K26: =TEXT(I26,"mmm-yyyy") -> Jan-2025 | L26: PKR | M26: 1 | N26: Steelstone Building Materials (Pvt) Ltd | O26: Head office - Lahore | P26: CC-LOG | Q26: N/A | R26: 24-Jan-2025 - Email | S26: =IF(BN26<1,"Paid",IF(BM26>0,"Partially paid",IF(ISNUMBER(SEARCH("hold",BU26)),"On hold",IF(BQ26<TODAY(),"Overdue","Approved - unpaid")))) -> Paid | T26: Other vendor - Services | U26: VEN-110 - Quick Fix Auto Workshop | V26: 35202-5566443-1 (CNIC) | W26: Active Filer | X26: No | Y26: Accounts desk - 042-35925976 | Z26: Meezan - 9420-1341943 | AA26: Credit 30 days | AB26: 0 | AC26: N/A | AD26: N/A | AE26: N/A | AF26: 1 | AG26: SRV-MNT | AH26: Vehicle maintenance & repair service | AI26: Job | AJ26: 1 | AK26: 1 | AL26: 35420 | AM26: =AK26*AL26 -> 35420 | AN26: =AM26 -> 35420 | AO26: =_xlfn.XLOOKUP(AG26,'T13'!$A$3:$A$1500,'T13'!$O$3:$O$1500) -> 0.16 | AP26: 0 | AQ26: =SUMIFS($AN$3:$AN$1500,$G$3:$G$1500,G26) -> 35420 | AR26: =SUMIFS($AP$3:$AP$1500,$G$3:$G$1500,G26) -> 0 | AS26: 153(1)(b) services - 11% | AT26: =ROUND(BH26*0.11,0) -> 4520 | AU26: No | AV26: {=SUMPRODUCT(($G$3:$G$1500=G26)*$AN$3:$AN$1500*$AO$3:$AO$1500)+AR26} -> 5667.2 | AW26: =AT26 -> 4520 | AX26: =TEXT(EOMONTH(I26,0)+15,"dd-mmm-yyyy")&" / "&IF(BM26>0,"CPR-IT-"&TEXT(I26,"yymm")&"-"&RIGHT(G26,4),"Pending payment") -> 15-Feb-2025 / CPR-IT-2501-0020 | AY26: =IF(BM26>0,"Issued","Not yet") -> Issued | AZ26: 0 | BA26: 0 | BB26: 0 | BC26: 0 | BD26: 0 | BE26: =AQ26 -> 35420 | BF26: =AV26 -> 5667.2 | BG26: =AZ26 -> 0 | BH26: =BE26+BF26+BG26 -> 41087.2 | BI26: =AW26 -> 4520 | BJ26: =BA26+BB26+BC26+BD26 -> 0 | BK26: =BH26-BI26-BJ26 -> 36567.2 | BL26: ="PKR "&TEXT(BK26,"#,##0")&" only" -> PKR 36,567 only | BM26: =SUMIFS('T10'!$AK$3:$AK$1500,'T10'!$V$3:$V$1500,G26) -> 36567.2 | BN26: =BK26-BM26 -> 0 | BO26: =IF(BF26>0,TEXT(I26,"mmm-yyyy")&" sales tax return","N/A") -> Jan-2025 sales tax return | BP26: Credit 30 days | BQ26: =J26+30 -> 45709 | BR26: =BQ26 -> 45709 | BS26: IBFT | BT26: Normal | BU26: N/A | BV26: No | BW26: {=_xlfn.TEXTJOIN(", ",TRUE,_xlfn.UNIQUE(_xlfn._xlws.FILTER('T10'!$A$3:$A$1500,'T10'!$V$3:$V$1500=G26,"None")))} -> PV-0071 | BX26: Hassan Raza - 25-Jan-2025 | BY26: Sana Iqbal - 26-Jan-2025
A27: SUP-003 Salt Range White Cement Ltd (NTN 2276540-9) | B27: SRW/INV/2501/234 | C27: DRY-00021 | D27: 45689.625 | E27: Yes - SMS & email | F27: =IF(S27="Paid","Completed","Pending payment") -> Completed | G27: BB-0021 | H27: Goods purchase (cement) | I27: 45688 | J27: 45688 | K27: =TEXT(I27,"mmm-yyyy") -> Jan-2025 | L27: PKR | M27: 1 | N27: Steelstone Building Materials (Pvt) Ltd | O27: Supplier plant - direct dispatch | P27: CC-SALES-LHR | Q27: N/A | R27: 01-Feb-2025 - Email | S27: =IF(BN27<1,"Paid",IF(BM27>0,"Partially paid",IF(ISNUMBER(SEARCH("hold",BU27)),"On hold",IF(BQ27<TODAY(),"Overdue","Approved - unpaid")))) -> Paid | T27: Manufacturer / supplier | U27: SUP-003 - Salt Range White Cement Ltd | V27: 2276540-9 | W27: Active Filer | X27: No | Y27: Ayesha Siddiqui - 0333-4290176 | Z27: Bank Alfalah Ltd - 5501-1004-0098712 | AA27: Credit 15 days | AB27: 0 | AC27: PO-2501-3 | AD27: 18-Jan-2025 / PKR 11492000 (approx.) | AE27: SA-SUP-003-2024 | AF27: 1 | AG27: CEM-LHC-B50 | AH27: Low Heat Cement - 50 kg bag | AI27: Bag (50 kg) | AJ27: 5250 | AK27: 5250 | AL27: 1420 | AM27: =AK27*AL27 -> 7455000 | AN27: =AM27 -> 7455000 | AO27: =_xlfn.XLOOKUP(AG27,'T13'!$A$3:$A$1500,'T13'!$O$3:$O$1500) -> 0.18 | AP27: =AK27*IF(AI27="MT",1000,IF(AI27="Jumbo bag (1.5 MT)",1500,IF(AI27="Bag (40 kg)",40,50)))*3 -> 787500 | AQ27: =SUMIFS($AN$3:$AN$1500,$G$3:$G$1500,G27) -> 9005250 | AR27: =SUMIFS($AP$3:$AP$1500,$G$3:$G$1500,G27) -> 865500 | AS27: 153(1)(a) goods - 5% | AT27: =ROUND(BH27*0.05,0) -> 574585 | AU27: No | AV27: {=SUMPRODUCT(($G$3:$G$1500=G27)*$AN$3:$AN$1500*$AO$3:$AO$1500)+AR27} -> 2486445 | AW27: =AT27 -> 574585 | AX27: =TEXT(EOMONTH(I27,0)+15,"dd-mmm-yyyy")&" / "&IF(BM27>0,"CPR-IT-"&TEXT(I27,"yymm")&"-"&RIGHT(G27,4),"Pending payment") -> 15-Feb-2025 / CPR-IT-2501-0021 | AY27: =IF(BM27>0,"Issued","Not yet") -> Issued | AZ27: 0 | BA27: 0 | BB27: 0 | BC27: 0 | BD27: 0 | BE27: =AQ27 -> 9005250 | BF27: =AV27 -> 2486445 | BG27: =AZ27 -> 0 | BH27: =BE27+BF27+BG27 -> 11491695 | BI27: =AW27 -> 574585 | BJ27: =BA27+BB27+BC27+BD27 -> 0 | BK27: =BH27-BI27-BJ27 -> 10917110 | BL27: ="PKR "&TEXT(BK27,"#,##0")&" only" -> PKR 10,917,110 only | BM27: =SUMIFS('T10'!$AK$3:$AK$1500,'T10'!$V$3:$V$1500,G27) -> 10917110 | BN27: =BK27-BM27 -> 0 | BO27: =IF(BF27>0,TEXT(I27,"mmm-yyyy")&" sales tax return","N/A") -> Jan-2025 sales tax return | BP27: Credit 15 days | BQ27: =J27+15 -> 45703 | BR27: =BQ27 -> 45703 | BS27: IBFT | BT27: High | BU27: N/A | BV27: No | BW27: {=_xlfn.TEXTJOIN(", ",TRUE,_xlfn.UNIQUE(_xlfn._xlws.FILTER('T10'!$A$3:$A$1500,'T10'!$V$3:$V$1500=G27,"None")))} -> PV-0009 | BX27: Hassan Raza - 01-Feb-2025 | BY27: Sana Iqbal - 02-Feb-2025
A28: SUP-003 Salt Range White Cement Ltd (NTN 2276540-9) | B28: SRW/INV/2501/234 | C28: DRY-00021 | D28: 45689.625 | E28: Yes - SMS & email | F28: =IF(S28="Paid","Completed","Pending payment") -> Completed | G28: BB-0021 | H28: Goods purchase (cement) | I28: 45688 | J28: 45688 | K28: =TEXT(I28,"mmm-yyyy") -> Jan-2025 | L28: PKR | M28: 1 | N28: Steelstone Building Materials (Pvt) Ltd | O28: Supplier plant - direct dispatch | P28: CC-SALES-LHR | Q28: N/A | R28: 01-Feb-2025 - Email | S28: =IF(BN28<1,"Paid",IF(BM28>0,"Partially paid",IF(ISNUMBER(SEARCH("hold",BU28)),"On hold",IF(BQ28<TODAY(),"Overdue","Approved - unpaid")))) -> Paid | T28: Manufacturer / supplier | U28: SUP-003 - Salt Range White Cement Ltd | V28: 2276540-9 | W28: Active Filer | X28: No | Y28: Ayesha Siddiqui - 0333-4290176 | Z28: Bank Alfalah Ltd - 5501-1004-0098712 | AA28: Credit 15 days | AB28: 0 | AC28: PO-2501-3 | AD28: 06-Jan-2025 / PKR 11492000 (approx.) | AE28: SA-SUP-003-2024 | AF28: 2 | AG28: CEM-WHT-B40 | AH28: White Cement - 40 kg bag | AI28: Bag (40 kg) | AJ28: 650 | AK28: 650 | AL28: 2385 | AM28: =AK28*AL28 -> 1550250 | AN28: =AM28 -> 1550250 | AO28: =_xlfn.XLOOKUP(AG28,'T13'!$A$3:$A$1500,'T13'!$O$3:$O$1500) -> 0.18 | AP28: =AK28*IF(AI28="MT",1000,IF(AI28="Jumbo bag (1.5 MT)",1500,IF(AI28="Bag (40 kg)",40,50)))*3 -> 78000 | AQ28: =SUMIFS($AN$3:$AN$1500,$G$3:$G$1500,G28) -> 9005250 | AR28: =SUMIFS($AP$3:$AP$1500,$G$3:$G$1500,G28) -> 865500 | AS28: 153(1)(a) goods - 5% | AT28: =ROUND(BH28*0.05,0) -> 574585 | AU28: No | AV28: {=SUMPRODUCT(($G$3:$G$1500=G28)*$AN$3:$AN$1500*$AO$3:$AO$1500)+AR28} -> 2486445 | AW28: =AT28 -> 574585 | AX28: =TEXT(EOMONTH(I28,0)+15,"dd-mmm-yyyy")&" / "&IF(BM28>0,"CPR-IT-"&TEXT(I28,"yymm")&"-"&RIGHT(G28,4),"Pending payment") -> 15-Feb-2025 / CPR-IT-2501-0021 | AY28: =IF(BM28>0,"Issued","Not yet") -> Issued | AZ28: 0 | BA28: 0 | BB28: 0 | BC28: 0 | BD28: 0 | BE28: =AQ28 -> 9005250 | BF28: =AV28 -> 2486445 | BG28: =AZ28 -> 0 | BH28: =BE28+BF28+BG28 -> 11491695 | BI28: =AW28 -> 574585 | BJ28: =BA28+BB28+BC28+BD28 -> 0 | BK28: =BH28-BI28-BJ28 -> 10917110 | BL28: ="PKR "&TEXT(BK28,"#,##0")&" only" -> PKR 10,917,110 only | BM28: =SUMIFS('T10'!$AK$3:$AK$1500,'T10'!$V$3:$V$1500,G28) -> 10917110 | BN28: =BK28-BM28 -> 0 | BO28: =IF(BF28>0,TEXT(I28,"mmm-yyyy")&" sales tax return","N/A") -> Jan-2025 sales tax return | BP28: Credit 15 days | BQ28: =J28+15 -> 45703 | BR28: =BQ28 -> 45703 | BS28: IBFT | BT28: High | BU28: N/A | BV28: No | BW28: {=_xlfn.TEXTJOIN(", ",TRUE,_xlfn.UNIQUE(_xlfn._xlws.FILTER('T10'!$A$3:$A$1500,'T10'!$V$3:$V$1500=G28,"None")))} -> PV-0009 | BX28: Hassan Raza - 01-Feb-2025 | BY28: Sana Iqbal - 02-Feb-2025
A29: TRN-001 Khan Goods Transport Co (NTN 17301-5567812-9 (CNIC)) | B29: FB-TRN001-2501 | C29: DRY-00022 | D29: 45690.625 | E29: Yes - SMS & email | F29: =IF(S29="Paid","Completed","Pending payment") -> Completed | G29: BB-0022 | H29: Freight / transport | I29: 45691 | J29: 45689 | K29: =TEXT(I29,"mmm-yyyy") -> Feb-2025 | L29: PKR | M29: 1 | N29: Steelstone Building Materials (Pvt) Ltd | O29: Head office - Lahore | P29: CC-LOG | Q29: N/A | R29: 02-Feb-2025 - By hand | S29: =IF(BN29<1,"Paid",IF(BM29>0,"Partially paid",IF(ISNUMBER(SEARCH("hold",BU29)),"On hold",IF(BQ29<TODAY(),"Overdue","Approved - unpaid")))) -> Paid | T29: Transporter | U29: TRN-001 - Khan Goods Transport Co | V29: 17301-5567812-9 (CNIC) | W29: Active Filer | X29: No | Y29: Gul Khan - 0300-5991287 | Z29: Habib Bank Ltd - 2210-79004455-01 | AA29: Credit 30 days | AB29: 0 | AC29: N/A | AD29: N/A | AE29: TC-TRN-001-2024 | AF29: 1 | AG29: SRV-FRT-BAG | AH29: Freight - bagged cement per trip | AI29: Trip | AJ29: =COUNTIFS('T14'!$AQ$3:$AQ$1500,B29,'T14'!$Z$3:$Z$1500,1,'T14'!$F$3:$F$1500,"Bag") -> 8 | AK29: =AJ29 -> 8 | AL29: 38600 | AM29: =AK29*AL29 -> 308800 | AN29: =AM29 -> 308800 | AO29: =_xlfn.XLOOKUP(AG29,'T13'!$A$3:$A$1500,'T13'!$O$3:$O$1500) -> 0.16 | AP29: 0 | AQ29: =SUMIFS($AN$3:$AN$1500,$G$3:$G$1500,G29) -> 308800 | AR29: =SUMIFS($AP$3:$AP$1500,$G$3:$G$1500,G29) -> 0 | AS29: 153(1)(b) transport - 4% | AT29: =ROUND(BH29*0.04,0) -> 14688 | AU29: No | AV29: {=SUMPRODUCT(($G$3:$G$1500=G29)*$AN$3:$AN$1500*$AO$3:$AO$1500)+AR29} -> 49408 | AW29: =AT29 -> 14688 | AX29: =TEXT(EOMONTH(I29,0)+15,"dd-mmm-yyyy")&" / "&IF(BM29>0,"CPR-IT-"&TEXT(I29,"yymm")&"-"&RIGHT(G29,4),"Pending payment") -> 15-Mar-2025 / CPR-IT-2502-0022 | AY29: =IF(BM29>0,"Issued","Not yet") -> Issued | AZ29: 9000 | BA29: 0 | BB29: 0 | BC29: 0 | BD29: 0 | BE29: =AQ29 -> 308800 | BF29: =AV29 -> 49408 | BG29: =AZ29 -> 9000 | BH29: =BE29+BF29+BG29 -> 367208 | BI29: =AW29 -> 14688 | BJ29: =BA29+BB29+BC29+BD29 -> 0 | BK29: =BH29-BI29-BJ29 -> 352520 | BL29: ="PKR "&TEXT(BK29,"#,##0")&" only" -> PKR 352,520 only | BM29: =SUMIFS('T10'!$AK$3:$AK$1500,'T10'!$V$3:$V$1500,G29) -> 352520 | BN29: =BK29-BM29 -> 0 | BO29: =IF(BF29>0,TEXT(I29,"mmm-yyyy")&" sales tax return","N/A") -> Feb-2025 sales tax return | BP29: Credit 30 days | BQ29: =J29+30 -> 45719 | BR29: =BQ29 -> 45719 | BS29: IBFT | BT29: Normal | BU29: N/A | BV29: No | BW29: {=_xlfn.TEXTJOIN(", ",TRUE,_xlfn.UNIQUE(_xlfn._xlws.FILTER('T10'!$A$3:$A$1500,'T10'!$V$3:$V$1500=G29,"None")))} -> PV-0005 | BX29: Hassan Raza - 04-Feb-2025 | BY29: Sana Iqbal - 05-Feb-2025
A30: TRN-002 Al-Madina Logistics (Pvt) Ltd (NTN 5567123-4) | B30: FB-TRN002-2501 | C30: DRY-00023 | D30: 45690.667 | E30: Yes - SMS & email | F30: =IF(S30="Paid","Completed","Pending payment") -> Completed | G30: BB-0023 | H30: Freight / transport | I30: 45691 | J30: 45689 | K30: =TEXT(I30,"mmm-yyyy") -> Feb-2025 | L30: PKR | M30: 1 | N30: Steelstone Building Materials (Pvt) Ltd | O30: Head office - Lahore | P30: CC-LOG | Q30: N/A | R30: 02-Feb-2025 - By hand | S30: =IF(BN30<1,"Paid",IF(BM30>0,"Partially paid",IF(ISNUMBER(SEARCH("hold",BU30)),"On hold",IF(BQ30<TODAY(),"Overdue","Approved - unpaid")))) -> Paid | T30: Transporter | U30: TRN-002 - Al-Madina Logistics (Pvt) Ltd | V30: 5567123-4 | W30: Active Filer | X30: No | Y30: Tahir Mehmood - 0321-4789012 | Z30: MCB Bank Ltd - 0654-7701122301 | AA30: Credit 30 days | AB30: 0 | AC30: N/A | AD30: N/A | AE30: TC-TRN-002-2024 | AF30: 1 | AG30: SRV-FRT-BAG | AH30: Freight - bagged cement per trip | AI30: Trip | AJ30: =COUNTIFS('T14'!$AQ$3:$AQ$1500,B30,'T14'!$Z$3:$Z$1500,1,'T14'!$F$3:$F$1500,"Bag") -> 3 | AK30: =AJ30 -> 3 | AL30: 38600 | AM30: =AK30*AL30 -> 115800 | AN30: =AM30 -> 115800 | AO30: =_xlfn.XLOOKUP(AG30,'T13'!$A$3:$A$1500,'T13'!$O$3:$O$1500) -> 0.16 | AP30: 0 | AQ30: =SUMIFS($AN$3:$AN$1500,$G$3:$G$1500,G30) -> 115800 | AR30: =SUMIFS($AP$3:$AP$1500,$G$3:$G$1500,G30) -> 0 | AS30: 153(1)(b) transport - 4% | AT30: =ROUND(BH30*0.04,0) -> 5373 | AU30: No | AV30: {=SUMPRODUCT(($G$3:$G$1500=G30)*$AN$3:$AN$1500*$AO$3:$AO$1500)+AR30} -> 18528 | AW30: =AT30 -> 5373 | AX30: =TEXT(EOMONTH(I30,0)+15,"dd-mmm-yyyy")&" / "&IF(BM30>0,"CPR-IT-"&TEXT(I30,"yymm")&"-"&RIGHT(G30,4),"Pending payment") -> 15-Mar-2025 / CPR-IT-2502-0023 | AY30: =IF(BM30>0,"Issued","Not yet") -> Issued | AZ30: 0 | BA30: 5000 | BB30: 0 | BC30: 0 | BD30: 0 | BE30: =AQ30 -> 115800 | BF30: =AV30 -> 18528 | BG30: =AZ30 -> 0 | BH30: =BE30+BF30+BG30 -> 134328 | BI30: =AW30 -> 5373 | BJ30: =BA30+BB30+BC30+BD30 -> 5000 | BK30: =BH30-BI30-BJ30 -> 123955 | BL30: ="PKR "&TEXT(BK30,"#,##0")&" only" -> PKR 123,955 only | BM30: =SUMIFS('T10'!$AK$3:$AK$1500,'T10'!$V$3:$V$1500,G30) -> 123955 | BN30: =BK30-BM30 -> 0 | BO30: =IF(BF30>0,TEXT(I30,"mmm-yyyy")&" sales tax return","N/A") -> Feb-2025 sales tax return | BP30: Credit 30 days | BQ30: =J30+30 -> 45719 | BR30: =BQ30 -> 45719 | BS30: IBFT | BT30: Normal | BU30: N/A | BV30: No | BW30: {=_xlfn.TEXTJOIN(", ",TRUE,_xlfn.UNIQUE(_xlfn._xlws.FILTER('T10'!$A$3:$A$1500,'T10'!$V$3:$V$1500=G30,"None")))} -> PV-0003 | BX30: Hassan Raza - 04-Feb-2025 | BY30: Sana Iqbal - 05-Feb-2025
A31: VEN-103 Shield Security Services (Pvt) Ltd (NTN 4567812-3) | B31: 103/2502/6684 | C31: DRY-00024 | D31: 45701.583 | E31: Yes - SMS & email | F31: =IF(S31="Paid","Completed","Pending payment") -> Completed | G31: BB-0024 | H31: Services | I31: 45701 | J31: 45699 | K31: =TEXT(I31,"mmm-yyyy") -> Feb-2025 | L31: PKR | M31: 1 | N31: Steelstone Building Materials (Pvt) Ltd | O31: Head office - Lahore | P31: CC-ADMIN | Q31: N/A | R31: 13-Feb-2025 - Email | S31: =IF(BN31<1,"Paid",IF(BM31>0,"Partially paid",IF(ISNUMBER(SEARCH("hold",BU31)),"On hold",IF(BQ31<TODAY(),"Overdue","Approved - unpaid")))) -> Paid | T31: Other vendor - Services | U31: VEN-103 - Shield Security Services (Pvt) Ltd | V31: 4567812-3 | W31: Active Filer | X31: No | Y31: Accounts desk - 042-35813307 | Z31: MCB - 9830-6278689 | AA31: Credit 30 days | AB31: 0 | AC31: N/A | AD31: N/A | AE31: N/A | AF31: 1 | AG31: SRV-SEC | AH31: Security guard services | AI31: Month | AJ31: 1 | AK31: 1 | AL31: 182880 | AM31: =AK31*AL31 -> 182880 | AN31: =AM31 -> 182880 | AO31: =_xlfn.XLOOKUP(AG31,'T13'!$A$3:$A$1500,'T13'!$O$3:$O$1500) -> 0.16 | AP31: 0 | AQ31: =SUMIFS($AN$3:$AN$1500,$G$3:$G$1500,G31) -> 182880 | AR31: =SUMIFS($AP$3:$AP$1500,$G$3:$G$1500,G31) -> 0 | AS31: 153(1)(b) services - 11% | AT31: =ROUND(BH31*0.11,0) -> 23335 | AU31: No | AV31: {=SUMPRODUCT(($G$3:$G$1500=G31)*$AN$3:$AN$1500*$AO$3:$AO$1500)+AR31} -> 29260.8 | AW31: =AT31 -> 23335 | AX31: =TEXT(EOMONTH(I31,0)+15,"dd-mmm-yyyy")&" / "&IF(BM31>0,"CPR-IT-"&TEXT(I31,"yymm")&"-"&RIGHT(G31,4),"Pending payment") -> 15-Mar-2025 / CPR-IT-2502-0024 | AY31: =IF(BM31>0,"Issued","Not yet") -> Issued | AZ31: 0 | BA31: 0 | BB31: 0 | BC31: 0 | BD31: 0 | BE31: =AQ31 -> 182880 | BF31: =AV31 -> 29260.8 | BG31: =AZ31 -> 0 | BH31: =BE31+BF31+BG31 -> 212140.8 | BI31: =AW31 -> 23335 | BJ31: =BA31+BB31+BC31+BD31 -> 0 | BK31: =BH31-BI31-BJ31 -> 188805.8 | BL31: ="PKR "&TEXT(BK31,"#,##0")&" only" -> PKR 188,806 only | BM31: =SUMIFS('T10'!$AK$3:$AK$1500,'T10'!$V$3:$V$1500,G31) -> 188805.8 | BN31: =BK31-BM31 -> 0 | BO31: =IF(BF31>0,TEXT(I31,"mmm-yyyy")&" sales tax return","N/A") -> Feb-2025 sales tax return | BP31: Credit 30 days | BQ31: =J31+30 -> 45729 | BR31: =BQ31 -> 45729 | BS31: IBFT | BT31: Normal | BU31: N/A | BV31: No | BW31: {=_xlfn.TEXTJOIN(", ",TRUE,_xlfn.UNIQUE(_xlfn._xlws.FILTER('T10'!$A$3:$A$1500,'T10'!$V$3:$V$1500=G31,"None")))} -> PV-0007 | BX31: Hassan Raza - 14-Feb-2025 | BY31: Sana Iqbal - 15-Feb-2025
A32: VEN-104 Nayatel (Pvt) Ltd (NTN 2098765-4) | B32: 104/2502/6643 | C32: DRY-00025 | D32: 45704.417 | E32: Yes - SMS & email | F32: =IF(S32="Paid","Completed","Pending payment") -> Completed | G32: BB-0025 | H32: Utilities | I32: 45704 | J32: 45702 | K32: =TEXT(I32,"mmm-yyyy") -> Feb-2025 | L32: PKR | M32: 1 | N32: Steelstone Building Materials (Pvt) Ltd | O32: Head office - Lahore | P32: CC-ADMIN | Q32: N/A | R32: 16-Feb-2025 - Email | S32: =IF(BN32<1,"Paid",IF(BM32>0,"Partially paid",IF(ISNUMBER(SEARCH("hold",BU32)),"On hold",IF(BQ32<TODAY(),"Overdue","Approved - unpaid")))) -> Paid | T32: Other vendor - Utilities | U32: VEN-104 - Nayatel (Pvt) Ltd | V32: 2098765-4 | W32: Active Filer | X32: No | Y32: Accounts desk - 042-35660073 | Z32: Meezan - 5857-6193451 | AA32: Credit 15 days | AB32: 0 | AC32: N/A | AD32: N/A | AE32: N/A | AF32: 1 | AG32: SRV-INT | AH32: Internet & telephone | AI32: Month | AJ32: 1 | AK32: 1 | AL32: 25400 | AM32: =AK32*AL32 -> 25400 | AN32: =AM32 -> 25400 | AO32: =_xlfn.XLOOKUP(AG32,'T13'!$A$3:$A$1500,'T13'!$O$3:$O$1500) -> 0.16 | AP32: 0 | AQ32: =SUMIFS($AN$3:$AN$1500,$G$3:$G$1500,G32) -> 25400 | AR32: =SUMIFS($AP$3:$AP$1500,$G$3:$G$1500,G32) -> 0 | AS32: N/A - tax collected in bill | AT32: =ROUND(BH32*0,0) -> 0 | AU32: No | AV32: {=SUMPRODUCT(($G$3:$G$1500=G32)*$AN$3:$AN$1500*$AO$3:$AO$1500)+AR32} -> 4064 | AW32: =AT32 -> 0 | AX32: =TEXT(EOMONTH(I32,0)+15,"dd-mmm-yyyy")&" / "&IF(BM32>0,"CPR-IT-"&TEXT(I32,"yymm")&"-"&RIGHT(G32,4),"Pending payment") -> 15-Mar-2025 / CPR-IT-2502-0025 | AY32: =IF(BM32>0,"Issued","Not yet") -> Issued | AZ32: 0 | BA32: 0 | BB32: 0 | BC32: 0 | BD32: 0 | BE32: =AQ32 -> 25400 | BF32: =AV32 -> 4064 | BG32: =AZ32 -> 0 | BH32: =BE32+BF32+BG32 -> 29464 | BI32: =AW32 -> 0 | BJ32: =BA32+BB32+BC32+BD32 -> 0 | BK32: =BH32-BI32-BJ32 -> 29464 | BL32: ="PKR "&TEXT(BK32,"#,##0")&" only" -> PKR 29,464 only | BM32: =SUMIFS('T10'!$AK$3:$AK$1500,'T10'!$V$3:$V$1500,G32) -> 29464 | BN32: =BK32-BM32 -> 0 | BO32: =IF(BF32>0,TEXT(I32,"mmm-yyyy")&" sales tax return","N/A") -> Feb-2025 sales tax return | BP32: Credit 15 days | BQ32: =J32+15 -> 45717 | BR32: =BQ32 -> 45717 | BS32: IBFT | BT32: Normal | BU32: N/A | BV32: No | BW32: {=_xlfn.TEXTJOIN(", ",TRUE,_xlfn.UNIQUE(_xlfn._xlws.FILTER('T10'!$A$3:$A$1500,'T10'!$V$3:$V$1500=G32,"None")))} -> PV-0010 | BX32: Hassan Raza - 17-Feb-2025 | BY32: Sana Iqbal - 18-Feb-2025
A33: VEN-101 Sundar Estate Properties (Pvt) Ltd (NTN 3345120-7) | B33: 101/2502/5559 | C33: DRY-00026 | D33: 45710.458 | E33: Yes - SMS & email | F33: =IF(S33="Paid","Completed","Pending payment") -> Completed | G33: BB-0026 | H33: Rent | I33: 45710 | J33: 45708 | K33: =TEXT(I33,"mmm-yyyy") -> Feb-2025 | L33: PKR | M33: 1 | N33: Steelstone Building Materials (Pvt) Ltd | O33: Raiwind Road warehouse | P33: CC-WH | Q33: N/A | R33: 22-Feb-2025 - Email | S33: =IF(BN33<1,"Paid",IF(BM33>0,"Partially paid",IF(ISNUMBER(SEARCH("hold",BU33)),"On hold",IF(BQ33<TODAY(),"Overdue","Approved - unpaid")))) -> Paid | T33: Other vendor - Rent | U33: VEN-101 - Sundar Estate Properties (Pvt) Ltd | V33: 3345120-7 | W33: Active Filer | X33: No | Y33: Accounts desk - 042-35006081 | Z33: HBL - 1948-4340372 | AA33: Advance (quarterly) | AB33: 0 | AC33: N/A | AD33: N/A | AE33: Lease LA-2024-07 | AF33: 1 | AG33: SRV-RENT | AH33: Warehouse rent - Sundar Estate | AI33: Month | AJ33: 3 | AK33: 3 | AL33: 355600 | AM33: =AK33*AL33 -> 1066800 | AN33: =AM33 -> 1066800 | AO33: =_xlfn.XLOOKUP(AG33,'T13'!$A$3:$A$1500,'T13'!$O$3:$O$1500) -> 0 | AP33: 0 | AQ33: =SUMIFS($AN$3:$AN$1500,$G$3:$G$1500,G33) -> 1066800 | AR33: =SUMIFS($AP$3:$AP$1500,$G$3:$G$1500,G33) -> 0 | AS33: 155 rent - 15% | AT33: =ROUND(BH33*0.15,0) -> 160020 | AU33: No | AV33: {=SUMPRODUCT(($G$3:$G$1500=G33)*$AN$3:$AN$1500*$AO$3:$AO$1500)+AR33} -> 0 | AW33: =AT33 -> 160020 | AX33: =TEXT(EOMONTH(I33,0)+15,"dd-mmm-yyyy")&" / "&IF(BM33>0,"CPR-IT-"&TEXT(I33,"yymm")&"-"&RIGHT(G33,4),"Pending payment") -> 15-Mar-2025 / CPR-IT-2502-0026 | AY33: =IF(BM33>0,"Issued","Not yet") -> Issued | AZ33: 0 | BA33: 0 | BB33: 0 | BC33: 0 | BD33: 0 | BE33: =AQ33 -> 1066800 | BF33: =AV33 -> 0 | BG33: =AZ33 -> 0 | BH33: =BE33+BF33+BG33 -> 1066800 | BI33: =AW33 -> 160020 | BJ33: =BA33+BB33+BC33+BD33 -> 0 | BK33: =BH33-BI33-BJ33 -> 906780 | BL33: ="PKR "&TEXT(BK33,"#,##0")&" only" -> PKR 906,780 only | BM33: =SUMIFS('T10'!$AK$3:$AK$1500,'T10'!$V$3:$V$1500,G33) -> 906780 | BN33: =BK33-BM33 -> 0 | BO33: =IF(BF33>0,TEXT(I33,"mmm-yyyy")&" sales tax return","N/A") -> N/A | BP33: Advance (quarterly) | BQ33: =J33+7 -> 45715 | BR33: =BQ33 -> 45715 | BS33: IBFT | BT33: Normal | BU33: N/A | BV33: No | BW33: {=_xlfn.TEXTJOIN(", ",TRUE,_xlfn.UNIQUE(_xlfn._xlws.FILTER('T10'!$A$3:$A$1500,'T10'!$V$3:$V$1500=G33,"None")))} -> PV-0025 | BX33: Hassan Raza - 23-Feb-2025 | BY33: Sana Iqbal - 24-Feb-2025
A34: SUP-001 Margalla Cement Ltd (NTN 0712345-6) | B34: MCL/INV/2502/509 | C34: DRY-00027 | D34: 45718.667 | E34: Yes - SMS & email | F34: =IF(S34="Paid","Completed","Pending payment") -> Completed | G34: BB-0027 | H34: Goods purchase (cement) | I34: 45716 | J34: 45716 | K34: =TEXT(I34,"mmm-yyyy") -> Feb-2025 | L34: PKR | M34: 1 | N34: Steelstone Building Materials (Pvt) Ltd | O34: Supplier plant - direct dispatch | P34: CC-SALES-LHR | Q34: N/A | R34: 02-Mar-2025 - Email | S34: =IF(BN34<1,"Paid",IF(BM34>0,"Partially paid",IF(ISNUMBER(SEARCH("hold",BU34)),"On hold",IF(BQ34<TODAY(),"Overdue","Approved - unpaid")))) -> Paid | T34: Manufacturer / supplier | U34: SUP-001 - Margalla Cement Ltd | V34: 0712345-6 | W34: Active Filer | X34: No | Y34: Shahid Iqbal - 0300-8451290 | Z34: Habib Bank Ltd - 1234-79001122-03 | AA34: Credit 15 days | AB34: 0 | AC34: PO-2502-1 | AD34: 07-Feb-2025 / PKR 9481000 (approx.) | AE34: SA-SUP-001-2024 | AF34: 1 | AG34: CEM-OPC-B50 | AH34: OPC Cement Grade 53 - 50 kg bag | AI34: Bag (50 kg) | AJ34: 3900 | AK34: 3900 | AL34: 1315 | AM34: =AK34*AL34 -> 5128500 | AN34: =AM34 -> 5128500 | AO34: =_xlfn.XLOOKUP(AG34,'T13'!$A$3:$A$1500,'T13'!$O$3:$O$1500) -> 0.18 | AP34: =AK34*IF(AI34="MT",1000,IF(AI34="Jumbo bag (1.5 MT)",1500,IF(AI34="Bag (40 kg)",40,50)))*3 -> 585000 | AQ34: =SUMIFS($AN$3:$AN$1500,$G$3:$G$1500,G34) -> 7336190 | AR34: =SUMIFS($AP$3:$AP$1500,$G$3:$G$1500,G34) -> 824100 | AS34: 153(1)(a) goods - 5% | AT34: =ROUND(BH34*0.05,0) -> 474040 | AU34: No | AV34: {=SUMPRODUCT(($G$3:$G$1500=G34)*$AN$3:$AN$1500*$AO$3:$AO$1500)+AR34} -> 2144614.2 | AW34: =AT34 -> 474040 | AX34: =TEXT(EOMONTH(I34,0)+15,"dd-mmm-yyyy")&" / "&IF(BM34>0,"CPR-IT-"&TEXT(I34,"yymm")&"-"&RIGHT(G34,4),"Pending payment") -> 15-Mar-2025 / CPR-IT-2502-0027 | AY34: =IF(BM34>0,"Issued","Not yet") -> Issued | AZ34: 0 | BA34: 0 | BB34: 0 | BC34: 0 | BD34: 0 | BE34: =AQ34 -> 7336190 | BF34: =AV34 -> 2144614.2 | BG34: =AZ34 -> 0 | BH34: =BE34+BF34+BG34 -> 9480804.2 | BI34: =AW34 -> 474040 | BJ34: =BA34+BB34+BC34+BD34 -> 0 | BK34: =BH34-BI34-BJ34 -> 9006764.2 | BL34: ="PKR "&TEXT(BK34,"#,##0")&" only" -> PKR 9,006,764 only | BM34: =SUMIFS('T10'!$AK$3:$AK$1500,'T10'!$V$3:$V$1500,G34) -> 9006764.2 | BN34: =BK34-BM34 -> 0 | BO34: =IF(BF34>0,TEXT(I34,"mmm-yyyy")&" sales tax return","N/A") -> Feb-2025 sales tax return | BP34: Credit 15 days | BQ34: =J34+15 -> 45731 | BR34: =BQ34 -> 45731 | BS34: IBFT | BT34: High | BU34: N/A | BV34: No | BW34: {=_xlfn.TEXTJOIN(", ",TRUE,_xlfn.UNIQUE(_xlfn._xlws.FILTER('T10'!$A$3:$A$1500,'T10'!$V$3:$V$1500=G34,"None")))} -> PV-0001 | BX34: Hassan Raza - 01-Mar-2025 | BY34: Sana Iqbal - 02-Mar-2025
A35: SUP-001 Margalla Cement Ltd (NTN 0712345-6) | B35: MCL/INV/2502/509 | C35: DRY-00027 | D35: 45718.667 | E35: Yes - SMS & email | F35: =IF(S35="Paid","Completed","Pending payment") -> Completed | G35: BB-0027 | H35: Goods purchase (cement) | I35: 45716 | J35: 45716 | K35: =TEXT(I35,"mmm-yyyy") -> Feb-2025 | L35: PKR | M35: 1 | N35: Steelstone Building Materials (Pvt) Ltd | O35: Supplier plant - direct dispatch | P35: CC-SALES-LHR | Q35: N/A | R35: 02-Mar-2025 - Email | S35: =IF(BN35<1,"Paid",IF(BM35>0,"Partially paid",IF(ISNUMBER(SEARCH("hold",BU35)),"On hold",IF(BQ35<TODAY(),"Overdue","Approved - unpaid")))) -> Paid | T35: Manufacturer / supplier | U35: SUP-001 - Margalla Cement Ltd | V35: 0712345-6 | W35: Active Filer | X35: No | Y35: Shahid Iqbal - 0300-8451290 | Z35: Habib Bank Ltd - 1234-79001122-03 | AA35: Credit 15 days | AB35: 0 | AC35: PO-2502-1 | AD35: 05-Feb-2025 / PKR 9481000 (approx.) | AE35: SA-SUP-001-2024 | AF35: 2 | AG35: CEM-SRC-B50 | AH35: Sulphate Resistant Cement - 50 kg bag | AI35: Bag (50 kg) | AJ35: 1600 | AK35: 1594 | AL35: 1385 | AM35: =AK35*AL35 -> 2207690 | AN35: =AM35 -> 2207690 | AO35: =_xlfn.XLOOKUP(AG35,'T13'!$A$3:$A$1500,'T13'!$O$3:$O$1500) -> 0.18 | AP35: =AK35*IF(AI35="MT",1000,IF(AI35="Jumbo bag (1.5 MT)",1500,IF(AI35="Bag (40 kg)",40,50)))*3 -> 239100 | AQ35: =SUMIFS($AN$3:$AN$1500,$G$3:$G$1500,G35) -> 7336190 | AR35: =SUMIFS($AP$3:$AP$1500,$G$3:$G$1500,G35) -> 824100 | AS35: 153(1)(a) goods - 5% | AT35: =ROUND(BH35*0.05,0) -> 474040 | AU35: No | AV35: {=SUMPRODUCT(($G$3:$G$1500=G35)*$AN$3:$AN$1500*$AO$3:$AO$1500)+AR35} -> 2144614.2 | AW35: =AT35 -> 474040 | AX35: =TEXT(EOMONTH(I35,0)+15,"dd-mmm-yyyy")&" / "&IF(BM35>0,"CPR-IT-"&TEXT(I35,"yymm")&"-"&RIGHT(G35,4),"Pending payment") -> 15-Mar-2025 / CPR-IT-2502-0027 | AY35: =IF(BM35>0,"Issued","Not yet") -> Issued | AZ35: 0 | BA35: 0 | BB35: 0 | BC35: 0 | BD35: 0 | BE35: =AQ35 -> 7336190 | BF35: =AV35 -> 2144614.2 | BG35: =AZ35 -> 0 | BH35: =BE35+BF35+BG35 -> 9480804.2 | BI35: =AW35 -> 474040 | BJ35: =BA35+BB35+BC35+BD35 -> 0 | BK35: =BH35-BI35-BJ35 -> 9006764.2 | BL35: ="PKR "&TEXT(BK35,"#,##0")&" only" -> PKR 9,006,764 only | BM35: =SUMIFS('T10'!$AK$3:$AK$1500,'T10'!$V$3:$V$1500,G35) -> 9006764.2 | BN35: =BK35-BM35 -> 0 | BO35: =IF(BF35>0,TEXT(I35,"mmm-yyyy")&" sales tax return","N/A") -> Feb-2025 sales tax return | BP35: Credit 15 days | BQ35: =J35+15 -> 45731 | BR35: =BQ35 -> 45731 | BS35: IBFT | BT35: High | BU35: N/A | BV35: No | BW35: {=_xlfn.TEXTJOIN(", ",TRUE,_xlfn.UNIQUE(_xlfn._xlws.FILTER('T10'!$A$3:$A$1500,'T10'!$V$3:$V$1500=G35,"None")))} -> PV-0001 | BX35: Hassan Raza - 01-Mar-2025 | BY35: Sana Iqbal - 02-Mar-2025
A36: SUP-002 Indus Valley Cement (Pvt) Ltd (NTN 3398761-2) | B36: IVC/INV/2502/112 | C36: DRY-00028 | D36: 45718.375 | E36: Yes - SMS & email | F36: =IF(S36="Paid","Completed","Pending payment") -> Completed | G36: BB-0028 | H36: Goods purchase (cement) | I36: 45716 | J36: 45716 | K36: =TEXT(I36,"mmm-yyyy") -> Feb-2025 | L36: PKR | M36: 1 | N36: Steelstone Building Materials (Pvt) Ltd | O36: Supplier plant - direct dispatch | P36: CC-SALES-LHR | Q36: N/A | R36: 02-Mar-2025 - Email | S36: =IF(BN36<1,"Paid",IF(BM36>0,"Partially paid",IF(ISNUMBER(SEARCH("hold",BU36)),"On hold",IF(BQ36<TODAY(),"Overdue","Approved - unpaid")))) -> Paid | T36: Manufacturer / supplier | U36: SUP-002 - Indus Valley Cement (Pvt) Ltd | V36: 3398761-2 | W36: Active Filer | X36: No | Y36: Rizwan Akhtar - 0302-4418823 | Z36: MCB Bank Ltd - 0876-5501234401 | AA36: Credit 15 days | AB36: 0 | AC36: PO-2502-2 | AD36: 03-Feb-2025 / PKR 2119000 (approx.) | AE36: SA-SUP-002-2024 | AF36: 1 | AG36: CEM-SLG-B50 | AH36: Slag Cement - 50 kg bag | AI36: Bag (50 kg) | AJ36: 1300 | AK36: 1290 | AL36: 1265 | AM36: =AK36*AL36 -> 1631850 | AN36: =AM36 -> 1631850 | AO36: =_xlfn.XLOOKUP(AG36,'T13'!$A$3:$A$1500,'T13'!$O$3:$O$1500) -> 0.18 | AP36: =AK36*IF(AI36="MT",1000,IF(AI36="Jumbo bag (1.5 MT)",1500,IF(AI36="Bag (40 kg)",40,50)))*3 -> 193500 | AQ36: =SUMIFS($AN$3:$AN$1500,$G$3:$G$1500,G36) -> 1631850 | AR36: =SUMIFS($AP$3:$AP$1500,$G$3:$G$1500,G36) -> 193500 | AS36: 153(1)(a) goods - 5% | AT36: =ROUND(BH36*0.05,0) -> 105954 | AU36: No | AV36: {=SUMPRODUCT(($G$3:$G$1500=G36)*$AN$3:$AN$1500*$AO$3:$AO$1500)+AR36} -> 487233 | AW36: =AT36 -> 105954 | AX36: =TEXT(EOMONTH(I36,0)+15,"dd-mmm-yyyy")&" / "&IF(BM36>0,"CPR-IT-"&TEXT(I36,"yymm")&"-"&RIGHT(G36,4),"Pending payment") -> 15-Mar-2025 / CPR-IT-2502-0028 | AY36: =IF(BM36>0,"Issued","Not yet") -> Issued | AZ36: 0 | BA36: 0 | BB36: 0 | BC36: 0 | BD36: 0 | BE36: =AQ36 -> 1631850 | BF36: =AV36 -> 487233 | BG36: =AZ36 -> 0 | BH36: =BE36+BF36+BG36 -> 2119083 | BI36: =AW36 -> 105954 | BJ36: =BA36+BB36+BC36+BD36 -> 0 | BK36: =BH36-BI36-BJ36 -> 2013129 | BL36: ="PKR "&TEXT(BK36,"#,##0")&" only" -> PKR 2,013,129 only | BM36: =SUMIFS('T10'!$AK$3:$AK$1500,'T10'!$V$3:$V$1500,G36) -> 2013129 | BN36: =BK36-BM36 -> 0 | BO36: =IF(BF36>0,TEXT(I36,"mmm-yyyy")&" sales tax return","N/A") -> Feb-2025 sales tax return | BP36: Credit 15 days | BQ36: =J36+15 -> 45731 | BR36: =BQ36 -> 45731 | BS36: IBFT | BT36: High | BU36: N/A | BV36: No | BW36: {=_xlfn.TEXTJOIN(", ",TRUE,_xlfn.UNIQUE(_xlfn._xlws.FILTER('T10'!$A$3:$A$1500,'T10'!$V$3:$V$1500=G36,"None")))} -> PV-0004 | BX36: Hassan Raza - 01-Mar-2025 | BY36: Sana Iqbal - 02-Mar-2025
A37: TRN-001 Khan Goods Transport Co (NTN 17301-5567812-9 (CNIC)) | B37: FB-TRN001-2502 | C37: DRY-00029 | D37: 45718.5 | E37: Yes - SMS & email | F37: =IF(S37="Paid","Completed","Pending payment") -> Completed | G37: BB-0029 | H37: Freight / transport | I37: 45719 | J37: 45717 | K37: =TEXT(I37,"mmm-yyyy") -> Mar-2025 | L37: PKR | M37: 1 | N37: Steelstone Building Materials (Pvt) Ltd | O37: Head office - Lahore | P37: CC-LOG | Q37: N/A | R37: 02-Mar-2025 - By hand | S37: =IF(BN37<1,"Paid",IF(BM37>0,"Partially paid",IF(ISNUMBER(SEARCH("hold",BU37)),"On hold",IF(BQ37<TODAY(),"Overdue","Approved - unpaid")))) -> Paid | T37: Transporter | U37: TRN-001 - Khan Goods Transport Co | V37: 17301-5567812-9 (CNIC) | W37: Active Filer | X37: No | Y37: Gul Khan - 0300-5991287 | Z37: Habib Bank Ltd - 2210-79004455-01 | AA37: Credit 30 days | AB37: 0 | AC37: N/A | AD37: N/A | AE37: TC-TRN-001-2024 | AF37: 1 | AG37: SRV-FRT-BAG | AH37: Freight - bagged cement per trip | AI37: Trip | AJ37: =COUNTIFS('T14'!$AQ$3:$AQ$1500,B37,'T14'!$Z$3:$Z$1500,1,'T14'!$F$3:$F$1500,"Bag") -> 4 | AK37: =AJ37 -> 4 | AL37: 38800 | AM37: =AK37*AL37 -> 155200 | AN37: =AM37 -> 155200 | AO37: =_xlfn.XLOOKUP(AG37,'T13'!$A$3:$A$1500,'T13'!$O$3:$O$1500) -> 0.16 | AP37: 0 | AQ37: =SUMIFS($AN$3:$AN$1500,$G$3:$G$1500,G37) -> 155200 | AR37: =SUMIFS($AP$3:$AP$1500,$G$3:$G$1500,G37) -> 0 | AS37: 153(1)(b) transport - 4% | AT37: =ROUND(BH37*0.04,0) -> 7201 | AU37: No | AV37: {=SUMPRODUCT(($G$3:$G$1500=G37)*$AN$3:$AN$1500*$AO$3:$AO$1500)+AR37} -> 24832 | AW37: =AT37 -> 7201 | AX37: =TEXT(EOMONTH(I37,0)+15,"dd-mmm-yyyy")&" / "&IF(BM37>0,"CPR-IT-"&TEXT(I37,"yymm")&"-"&RIGHT(G37,4),"Pending payment") -> 15-Apr-2025 / CPR-IT-2503-0029 | AY37: =IF(BM37>0,"Issued","Not yet") -> Issued | AZ37: 0 | BA37: 0 | BB37: 0 | BC37: 0 | BD37: 0 | BE37: =AQ37 -> 155200 | BF37: =AV37 -> 24832 | BG37: =AZ37 -> 0 | BH37: =BE37+BF37+BG37 -> 180032 | BI37: =AW37 -> 7201 | BJ37: =BA37+BB37+BC37+BD37 -> 0 | BK37: =BH37-BI37-BJ37 -> 172831 | BL37: ="PKR "&TEXT(BK37,"#,##0")&" only" -> PKR 172,831 only | BM37: =SUMIFS('T10'!$AK$3:$AK$1500,'T10'!$V$3:$V$1500,G37) -> 172831 | BN37: =BK37-BM37 -> 0 | BO37: =IF(BF37>0,TEXT(I37,"mmm-yyyy")&" sales tax return","N/A") -> Mar-2025 sales tax return | BP37: Credit 30 days | BQ37: =J37+30 -> 45747 | BR37: =BQ37 -> 45747 | BS37: IBFT | BT37: Normal | BU37: N/A | BV37: No | BW37: {=_xlfn.TEXTJOIN(", ",TRUE,_xlfn.UNIQUE(_xlfn._xlws.FILTER('T10'!$A$3:$A$1500,'T10'!$V$3:$V$1500=G37,"None")))} -> PV-0005 | BX37: Hassan Raza - 04-Mar-2025 | BY37: Sana Iqbal - 05-Mar-2025
A38: TRN-002 Al-Madina Logistics (Pvt) Ltd (NTN 5567123-4) | B38: FB-TRN002-2502 | C38: DRY-00030 | D38: 45718.458 | E38: Yes - SMS & email | F38: =IF(S38="Paid","Completed","Pending payment") -> Completed | G38: BB-0030 | H38: Freight / transport | I38: 45719 | J38: 45717 | K38: =TEXT(I38,"mmm-yyyy") -> Mar-2025 | L38: PKR | M38: 1 | N38: Steelstone Building Materials (Pvt) Ltd | O38: Head office - Lahore | P38: CC-LOG | Q38: N/A | R38: 02-Mar-2025 - By hand | S38: =IF(BN38<1,"Paid",IF(BM38>0,"Partially paid",IF(ISNUMBER(SEARCH("hold",BU38)),"On hold",IF(BQ38<TODAY(),"Overdue","Approved - unpaid")))) -> Paid | T38: Transporter | U38: TRN-002 - Al-Madina Logistics (Pvt) Ltd | V38: 5567123-4 | W38: Active Filer | X38: No | Y38: Tahir Mehmood - 0321-4789012 | Z38: MCB Bank Ltd - 0654-7701122301 | AA38: Credit 30 days | AB38: 0 | AC38: N/A | AD38: N/A | AE38: TC-TRN-002-2024 | AF38: 1 | AG38: SRV-FRT-BAG | AH38: Freight - bagged cement per trip | AI38: Trip | AJ38: =COUNTIFS('T14'!$AQ$3:$AQ$1500,B38,'T14'!$Z$3:$Z$1500,1,'T14'!$F$3:$F$1500,"Bag") -> 8 | AK38: =AJ38 -> 8 | AL38: 38800 | AM38: =AK38*AL38 -> 310400 | AN38: =AM38 -> 310400 | AO38: =_xlfn.XLOOKUP(AG38,'T13'!$A$3:$A$1500,'T13'!$O$3:$O$1500) -> 0.16 | AP38: 0 | AQ38: =SUMIFS($AN$3:$AN$1500,$G$3:$G$1500,G38) -> 310400 | AR38: =SUMIFS($AP$3:$AP$1500,$G$3:$G$1500,G38) -> 0 | AS38: 153(1)(b) transport - 4% | AT38: =ROUND(BH38*0.04,0) -> 14403 | AU38: No | AV38: {=SUMPRODUCT(($G$3:$G$1500=G38)*$AN$3:$AN$1500*$AO$3:$AO$1500)+AR38} -> 49664 | AW38: =AT38 -> 14403 | AX38: =TEXT(EOMONTH(I38,0)+15,"dd-mmm-yyyy")&" / "&IF(BM38>0,"CPR-IT-"&TEXT(I38,"yymm")&"-"&RIGHT(G38,4),"Pending payment") -> 15-Apr-2025 / CPR-IT-2503-0030 | AY38: =IF(BM38>0,"Issued","Not yet") -> Issued | AZ38: 0 | BA38: 0 | BB38: 0 | BC38: 0 | BD38: 0 | BE38: =AQ38 -> 310400 | BF38: =AV38 -> 49664 | BG38: =AZ38 -> 0 | BH38: =BE38+BF38+BG38 -> 360064 | BI38: =AW38 -> 14403 | BJ38: =BA38+BB38+BC38+BD38 -> 0 | BK38: =BH38-BI38-BJ38 -> 345661 | BL38: ="PKR "&TEXT(BK38,"#,##0")&" only" -> PKR 345,661 only | BM38: =SUMIFS('T10'!$AK$3:$AK$1500,'T10'!$V$3:$V$1500,G38) -> 345661 | BN38: =BK38-BM38 -> 0 | BO38: =IF(BF38>0,TEXT(I38,"mmm-yyyy")&" sales tax return","N/A") -> Mar-2025 sales tax return | BP38: Credit 30 days | BQ38: =J38+30 -> 45747 | BR38: =BQ38 -> 45747 | BS38: IBFT | BT38: Normal | BU38: N/A | BV38: No | BW38: {=_xlfn.TEXTJOIN(", ",TRUE,_xlfn.UNIQUE(_xlfn._xlws.FILTER('T10'!$A$3:$A$1500,'T10'!$V$3:$V$1500=G38,"None")))} -> PV-0003 | BX38: Hassan Raza - 04-Mar-2025 | BY38: Sana Iqbal - 05-Mar-2025
A39: VEN-103 Shield Security Services (Pvt) Ltd (NTN 4567812-3) | B39: 103/2503/8179 | C39: DRY-00031 | D39: 45723.375 | E39: Yes - SMS & email | F39: =IF(S39="Paid","Completed","Pending payment") -> Completed | G39: BB-0031 | H39: Services | I39: 45723 | J39: 45721 | K39: =TEXT(I39,"mmm-yyyy") -> Mar-2025 | L39: PKR | M39: 1 | N39: Steelstone Building Materials (Pvt) Ltd | O39: Head office - Lahore | P39: CC-ADMIN | Q39: N/A | R39: 07-Mar-2025 - Email | S39: =IF(BN39<1,"Paid",IF(BM39>0,"Partially paid",IF(ISNUMBER(SEARCH("hold",BU39)),"On hold",IF(BQ39<TODAY(),"Overdue","Approved - unpaid")))) -> Paid | T39: Other vendor - Services | U39: VEN-103 - Shield Security Services (Pvt) Ltd | V39: 4567812-3 | W39: Active Filer | X39: No | Y39: Accounts desk - 042-35813307 | Z39: MCB - 9830-6278689 | AA39: Credit 30 days | AB39: 0 | AC39: N/A | AD39: N/A | AE39: N/A | AF39: 1 | AG39: SRV-SEC | AH39: Security guard services | AI39: Month | AJ39: 1 | AK39: 1 | AL39: 183600 | AM39: =AK39*AL39 -> 183600 | AN39: =AM39 -> 183600 | AO39: =_xlfn.XLOOKUP(AG39,'T13'!$A$3:$A$1500,'T13'!$O$3:$O$1500) -> 0.16 | AP39: 0 | AQ39: =SUMIFS($AN$3:$AN$1500,$G$3:$G$1500,G39) -> 183600 | AR39: =SUMIFS($AP$3:$AP$1500,$G$3:$G$1500,G39) -> 0 | AS39: 153(1)(b) services - 11% | AT39: =ROUND(BH39*0.11,0) -> 23427 | AU39: No | AV39: {=SUMPRODUCT(($G$3:$G$1500=G39)*$AN$3:$AN$1500*$AO$3:$AO$1500)+AR39} -> 29376 | AW39: =AT39 -> 23427 | AX39: =TEXT(EOMONTH(I39,0)+15,"dd-mmm-yyyy")&" / "&IF(BM39>0,"CPR-IT-"&TEXT(I39,"yymm")&"-"&RIGHT(G39,4),"Pending payment") -> 15-Apr-2025 / CPR-IT-2503-0031 | AY39: =IF(BM39>0,"Issued","Not yet") -> Issued | AZ39: 0 | BA39: 0 | BB39: 0 | BC39: 0 | BD39: 0 | BE39: =AQ39 -> 183600 | BF39: =AV39 -> 29376 | BG39: =AZ39 -> 0 | BH39: =BE39+BF39+BG39 -> 212976 | BI39: =AW39 -> 23427 | BJ39: =BA39+BB39+BC39+BD39 -> 0 | BK39: =BH39-BI39-BJ39 -> 189549 | BL39: ="PKR "&TEXT(BK39,"#,##0")&" only" -> PKR 189,549 only | BM39: =SUMIFS('T10'!$AK$3:$AK$1500,'T10'!$V$3:$V$1500,G39) -> 189549 | BN39: =BK39-BM39 -> 0 | BO39: =IF(BF39>0,TEXT(I39,"mmm-yyyy")&" sales tax return","N/A") -> Mar-2025 sales tax return | BP39: Credit 30 days | BQ39: =J39+30 -> 45751 | BR39: =BQ39 -> 45751 | BS39: IBFT | BT39: Normal | BU39: N/A | BV39: No | BW39: {=_xlfn.TEXTJOIN(", ",TRUE,_xlfn.UNIQUE(_xlfn._xlws.FILTER('T10'!$A$3:$A$1500,'T10'!$V$3:$V$1500=G39,"None")))} -> PV-0007 | BX39: Hassan Raza - 08-Mar-2025 | BY39: Sana Iqbal - 09-Mar-2025
A40: VEN-102 Lahore Electric Supply Co (LESCO) (NTN 1234567-0) | B40: 102/2503/5338 | C40: DRY-00032 | D40: 45741.417 | E40: Yes - SMS & email | F40: =IF(S40="Paid","Completed","Pending payment") -> Completed | G40: BB-0032 | H40: Utilities | I40: 45741 | J40: 45739 | K40: =TEXT(I40,"mmm-yyyy") -> Mar-2025 | L40: PKR | M40: 1 | N40: Steelstone Building Materials (Pvt) Ltd | O40: Head office - Lahore | P40: CC-ADMIN | Q40: N/A | R40: 25-Mar-2025 - Email | S40: =IF(BN40<1,"Paid",IF(BM40>0,"Partially paid",IF(ISNUMBER(SEARCH("hold",BU40)),"On hold",IF(BQ40<TODAY(),"Overdue","Approved - unpaid")))) -> Paid | T40: Other vendor - Utilities | U40: VEN-102 - Lahore Electric Supply Co (LESCO) | V40: 1234567-0 | W40: Active Filer | X40: No | Y40: Accounts desk - 042-35960143 | Z40: HBL - 5983-5300965 | AA40: Credit 10 days | AB40: 0 | AC40: N/A | AD40: N/A | AE40: N/A | AF40: 1 | AG40: SRV-UTL | AH40: Electricity - LESCO | AI40: Month | AJ40: 1 | AK40: 1 | AL40: 86700 | AM40: =AK40*AL40 -> 86700 | AN40: =AM40 -> 86700 | AO40: =_xlfn.XLOOKUP(AG40,'T13'!$A$3:$A$1500,'T13'!$O$3:$O$1500) -> 0.18 | AP40: 0 | AQ40: =SUMIFS($AN$3:$AN$1500,$G$3:$G$1500,G40) -> 86700 | AR40: =SUMIFS($AP$3:$AP$1500,$G$3:$G$1500,G40) -> 0 | AS40: N/A - tax collected in bill | AT40: =ROUND(BH40*0,0) -> 0 | AU40: No | AV40: {=SUMPRODUCT(($G$3:$G$1500=G40)*$AN$3:$AN$1500*$AO$3:$AO$1500)+AR40} -> 15606 | AW40: =AT40 -> 0 | AX40: =TEXT(EOMONTH(I40,0)+15,"dd-mmm-yyyy")&" / "&IF(BM40>0,"CPR-IT-"&TEXT(I40,"yymm")&"-"&RIGHT(G40,4),"Pending payment") -> 15-Apr-2025 / CPR-IT-2503-0032 | AY40: =IF(BM40>0,"Issued","Not yet") -> Issued | AZ40: 0 | BA40: 0 | BB40: 0 | BC40: 0 | BD40: 0 | BE40: =AQ40 -> 86700 | BF40: =AV40 -> 15606 | BG40: =AZ40 -> 0 | BH40: =BE40+BF40+BG40 -> 102306 | BI40: =AW40 -> 0 | BJ40: =BA40+BB40+BC40+BD40 -> 0 | BK40: =BH40-BI40-BJ40 -> 102306 | BL40: ="PKR "&TEXT(BK40,"#,##0")&" only" -> PKR 102,306 only | BM40: =SUMIFS('T10'!$AK$3:$AK$1500,'T10'!$V$3:$V$1500,G40) -> 102306 | BN40: =BK40-BM40 -> 0 | BO40: =IF(BF40>0,TEXT(I40,"mmm-yyyy")&" sales tax return","N/A") -> Mar-2025 sales tax return | BP40: Credit 10 days | BQ40: =J40+10 -> 45749 | BR40: =BQ40 -> 45749 | BS40: IBFT | BT40: Normal | BU40: N/A | BV40: No | BW40: {=_xlfn.TEXTJOIN(", ",TRUE,_xlfn.UNIQUE(_xlfn._xlws.FILTER('T10'!$A$3:$A$1500,'T10'!$V$3:$V$1500=G40,"None")))} -> PV-0006 | BX40: Hassan Raza - 26-Mar-2025 | BY40: Sana Iqbal - 27-Mar-2025
A41: SUP-001 Margalla Cement Ltd (NTN 0712345-6) | B41: MCL/INV/2503/899 | C41: DRY-00033 | D41: 45748.5 | E41: Yes - SMS & email | F41: =IF(S41="Paid","Completed","Pending payment") -> Completed | G41: BB-0033 | H41: Goods purchase (cement) | I41: 45747 | J41: 45747 | K41: =TEXT(I41,"mmm-yyyy") -> Mar-2025 | L41: PKR | M41: 1 | N41: Steelstone Building Materials (Pvt) Ltd | O41: Supplier plant - direct dispatch | P41: CC-SALES-LHR | Q41: N/A | R41: 01-Apr-2025 - Email | S41: =IF(BN41<1,"Paid",IF(BM41>0,"Partially paid",IF(ISNUMBER(SEARCH("hold",BU41)),"On hold",IF(BQ41<TODAY(),"Overdue","Approved - unpaid")))) -> Paid | T41: Manufacturer / supplier | U41: SUP-001 - Margalla Cement Ltd | V41: 0712345-6 | W41: Active Filer | X41: No | Y41: Shahid Iqbal - 0300-8451290 | Z41: Habib Bank Ltd - 1234-79001122-03 | AA41: Credit 15 days | AB41: 600000 | AC41: PO-2503-1 | AD41: 21-Mar-2025 / PKR 1964000 (approx.) | AE41: SA-SUP-001-2024 (advance PV-0002) | AF41: 1 | AG41: CEM-OPC-B50 | AH41: OPC Cement Grade 53 - 50 kg bag | AI41: Bag (50 kg) | AJ41: 1150 | AK41: 1150 | AL41: 1320 | AM41: =AK41*AL41 -> 1518000 | AN41: =AM41 -> 1518000 | AO41: =_xlfn.XLOOKUP(AG41,'T13'!$A$3:$A$1500,'T13'!$O$3:$O$1500) -> 0.18 | AP41: =AK41*IF(AI41="MT",1000,IF(AI41="Jumbo bag (1.5 MT)",1500,IF(AI41="Bag (40 kg)",40,50)))*3 -> 172500 | AQ41: =SUMIFS($AN$3:$AN$1500,$G$3:$G$1500,G41) -> 1518000 | AR41: =SUMIFS($AP$3:$AP$1500,$G$3:$G$1500,G41) -> 172500 | AS41: 153(1)(a) goods - 5% | AT41: =ROUND(BH41*0.05,0) -> 98187 | AU41: No | AV41: {=SUMPRODUCT(($G$3:$G$1500=G41)*$AN$3:$AN$1500*$AO$3:$AO$1500)+AR41} -> 445740 | AW41: =AT41 -> 98187 | AX41: =TEXT(EOMONTH(I41,0)+15,"dd-mmm-yyyy")&" / "&IF(BM41>0,"CPR-IT-"&TEXT(I41,"yymm")&"-"&RIGHT(G41,4),"Pending payment") -> 15-Apr-2025 / CPR-IT-2503-0033 | AY41: =IF(BM41>0,"Issued","Not yet") -> Issued | AZ41: 0 | BA41: 0 | BB41: 600000 | BC41: 0 | BD41: 0 | BE41: =AQ41 -> 1518000 | BF41: =AV41 -> 445740 | BG41: =AZ41 -> 0 | BH41: =BE41+BF41+BG41 -> 1963740 | BI41: =AW41 -> 98187 | BJ41: =BA41+BB41+BC41+BD41 -> 600000 | BK41: =BH41-BI41-BJ41 -> 1265553 | BL41: ="PKR "&TEXT(BK41,"#,##0")&" only" -> PKR 1,265,553 only | BM41: =SUMIFS('T10'!$AK$3:$AK$1500,'T10'!$V$3:$V$1500,G41) -> 1265553 | BN41: =BK41-BM41 -> 0 | BO41: =IF(BF41>0,TEXT(I41,"mmm-yyyy")&" sales tax return","N/A") -> Mar-2025 sales tax return | BP41: Credit 15 days | BQ41: =J41+15 -> 45762 | BR41: =BQ41 -> 45762 | BS41: IBFT | BT41: High | BU41: N/A | BV41: No | BW41: {=_xlfn.TEXTJOIN(", ",TRUE,_xlfn.UNIQUE(_xlfn._xlws.FILTER('T10'!$A$3:$A$1500,'T10'!$V$3:$V$1500=G41,"None")))} -> PV-0016 | BX41: Hassan Raza - 01-Apr-2025 | BY41: Sana Iqbal - 02-Apr-2025
A42: SUP-002 Indus Valley Cement (Pvt) Ltd (NTN 3398761-2) | B42: IVC/INV/2503/814 | C42: DRY-00034 | D42: 45749.667 | E42: Yes - SMS & email | F42: =IF(S42="Paid","Completed","Pending payment") -> Completed | G42: BB-0034 | H42: Goods purchase (cement) | I42: 45747 | J42: 45747 | K42: =TEXT(I42,"mmm-yyyy") -> Mar-2025 | L42: PKR | M42: 1 | N42: Steelstone Building Materials (Pvt) Ltd | O42: Supplier plant - direct dispatch | P42: CC-SALES-LHR | Q42: N/A | R42: 02-Apr-2025 - Email | S42: =IF(BN42<1,"Paid",IF(BM42>0,"Partially paid",IF(ISNUMBER(SEARCH("hold",BU42)),"On hold",IF(BQ42<TODAY(),"Overdue","Approved - unpaid")))) -> Paid | T42: Manufacturer / supplier | U42: SUP-002 - Indus Valley Cement (Pvt) Ltd | V42: 3398761-2 | W42: Active Filer | X42: No | Y42: Rizwan Akhtar - 0302-4418823 | Z42: MCB Bank Ltd - 0876-5501234401 | AA42: Credit 15 days | AB42: 0 | AC42: PO-2503-2 | AD42: 06-Mar-2025 / PKR 3623000 (approx.) | AE42: SA-SUP-002-2024 | AF42: 1 | AG42: CEM-SLG-B50 | AH42: Slag Cement - 50 kg bag | AI42: Bag (50 kg) | AJ42: 2050 | AK42: 2050 | AL42: 1270 | AM42: =AK42*AL42 -> 2603500 | AN42: =AM42 -> 2603500 | AO42: =_xlfn.XLOOKUP(AG42,'T13'!$A$3:$A$1500,'T13'!$O$3:$O$1500) -> 0.18 | AP42: =AK42*IF(AI42="MT",1000,IF(AI42="Jumbo bag (1.5 MT)",1500,IF(AI42="Bag (40 kg)",40,50)))*3 -> 307500 | AQ42: =SUMIFS($AN$3:$AN$1500,$G$3:$G$1500,G42) -> 2791000 | AR42: =SUMIFS($AP$3:$AP$1500,$G$3:$G$1500,G42) -> 330000 | AS42: 153(1)(a) goods - 5% | AT42: =ROUND(BH42*0.05,0) -> 181169 | AU42: No | AV42: {=SUMPRODUCT(($G$3:$G$1500=G42)*$AN$3:$AN$1500*$AO$3:$AO$1500)+AR42} -> 832380 | AW42: =AT42 -> 181169 | AX42: =TEXT(EOMONTH(I42,0)+15,"dd-mmm-yyyy")&" / "&IF(BM42>0,"CPR-IT-"&TEXT(I42,"yymm")&"-"&RIGHT(G42,4),"Pending payment") -> 15-Apr-2025 / CPR-IT-2503-0034 | AY42: =IF(BM42>0,"Issued","Not yet") -> Issued | AZ42: 0 | BA42: 0 | BB42: 0 | BC42: 0 | BD42: 0 | BE42: =AQ42 -> 2791000 | BF42: =AV42 -> 832380 | BG42: =AZ42 -> 0 | BH42: =BE42+BF42+BG42 -> 3623380 | BI42: =AW42 -> 181169 | BJ42: =BA42+BB42+BC42+BD42 -> 0 | BK42: =BH42-BI42-BJ42 -> 3442211 | BL42: ="PKR "&TEXT(BK42,"#,##0")&" only" -> PKR 3,442,211 only | BM42: =SUMIFS('T10'!$AK$3:$AK$1500,'T10'!$V$3:$V$1500,G42) -> 3442211 | BN42: =BK42-BM42 -> 0 | BO42: =IF(BF42>0,TEXT(I42,"mmm-yyyy")&" sales tax return","N/A") -> Mar-2025 sales tax return | BP42: Credit 15 days | BQ42: =J42+15 -> 45762 | BR42: =BQ42 -> 45762 | BS42: IBFT | BT42: High | BU42: N/A | BV42: No | BW42: {=_xlfn.TEXTJOIN(", ",TRUE,_xlfn.UNIQUE(_xlfn._xlws.FILTER('T10'!$A$3:$A$1500,'T10'!$V$3:$V$1500=G42,"None")))} -> PV-0004 | BX42: Hassan Raza - 01-Apr-2025 | BY42: Sana Iqbal - 02-Apr-2025
A43: SUP-002 Indus Valley Cement (Pvt) Ltd (NTN 3398761-2) | B43: IVC/INV/2503/814 | C43: DRY-00034 | D43: 45749.667 | E43: Yes - SMS & email | F43: =IF(S43="Paid","Completed","Pending payment") -> Completed | G43: BB-0034 | H43: Goods purchase (cement) | I43: 45747 | J43: 45747 | K43: =TEXT(I43,"mmm-yyyy") -> Mar-2025 | L43: PKR | M43: 1 | N43: Steelstone Building Materials (Pvt) Ltd | O43: Supplier plant - direct dispatch | P43: CC-SALES-LHR | Q43: N/A | R43: 02-Apr-2025 - Email | S43: =IF(BN43<1,"Paid",IF(BM43>0,"Partially paid",IF(ISNUMBER(SEARCH("hold",BU43)),"On hold",IF(BQ43<TODAY(),"Overdue","Approved - unpaid")))) -> Paid | T43: Manufacturer / supplier | U43: SUP-002 - Indus Valley Cement (Pvt) Ltd | V43: 3398761-2 | W43: Active Filer | X43: No | Y43: Rizwan Akhtar - 0302-4418823 | Z43: MCB Bank Ltd - 0876-5501234401 | AA43: Credit 15 days | AB43: 0 | AC43: PO-2503-2 | AD43: 10-Mar-2025 / PKR 3623000 (approx.) | AE43: SA-SUP-002-2024 | AF43: 2 | AG43: CEM-PPC-B50 | AH43: Portland Pozzolana Cement - 50 kg bag | AI43: Bag (50 kg) | AJ43: 150 | AK43: 150 | AL43: 1250 | AM43: =AK43*AL43 -> 187500 | AN43: =AM43 -> 187500 | AO43: =_xlfn.XLOOKUP(AG43,'T13'!$A$3:$A$1500,'T13'!$O$3:$O$1500) -> 0.18 | AP43: =AK43*IF(AI43="MT",1000,IF(AI43="Jumbo bag (1.5 MT)",1500,IF(AI43="Bag (40 kg)",40,50)))*3 -> 22500 | AQ43: =SUMIFS($AN$3:$AN$1500,$G$3:$G$1500,G43) -> 2791000 | AR43: =SUMIFS($AP$3:$AP$1500,$G$3:$G$1500,G43) -> 330000 | AS43: 153(1)(a) goods - 5% | AT43: =ROUND(BH43*0.05,0) -> 181169 | AU43: No | AV43: {=SUMPRODUCT(($G$3:$G$1500=G43)*$AN$3:$AN$1500*$AO$3:$AO$1500)+AR43} -> 832380 | AW43: =AT43 -> 181169 | AX43: =TEXT(EOMONTH(I43,0)+15,"dd-mmm-yyyy")&" / "&IF(BM43>0,"CPR-IT-"&TEXT(I43,"yymm")&"-"&RIGHT(G43,4),"Pending payment") -> 15-Apr-2025 / CPR-IT-2503-0034 | AY43: =IF(BM43>0,"Issued","Not yet") -> Issued | AZ43: 0 | BA43: 0 | BB43: 0 | BC43: 0 | BD43: 0 | BE43: =AQ43 -> 2791000 | BF43: =AV43 -> 832380 | BG43: =AZ43 -> 0 | BH43: =BE43+BF43+BG43 -> 3623380 | BI43: =AW43 -> 181169 | BJ43: =BA43+BB43+BC43+BD43 -> 0 | BK43: =BH43-BI43-BJ43 -> 3442211 | BL43: ="PKR "&TEXT(BK43,"#,##0")&" only" -> PKR 3,442,211 only | BM43: =SUMIFS('T10'!$AK$3:$AK$1500,'T10'!$V$3:$V$1500,G43) -> 3442211 | BN43: =BK43-BM43 -> 0 | BO43: =IF(BF43>0,TEXT(I43,"mmm-yyyy")&" sales tax return","N/A") -> Mar-2025 sales tax return | BP43: Credit 15 days | BQ43: =J43+15 -> 45762 | BR43: =BQ43 -> 45762 | BS43: IBFT | BT43: High | BU43: N/A | BV43: No | BW43: {=_xlfn.TEXTJOIN(", ",TRUE,_xlfn.UNIQUE(_xlfn._xlws.FILTER('T10'!$A$3:$A$1500,'T10'!$V$3:$V$1500=G43,"None")))} -> PV-0004 | BX43: Hassan Raza - 01-Apr-2025 | BY43: Sana Iqbal - 02-Apr-2025
A44: TRN-002 Al-Madina Logistics (Pvt) Ltd (NTN 5567123-4) | B44: FB-TRN002-2503 | C44: DRY-00035 | D44: 45750.583 | E44: Yes - SMS & email | F44: =IF(S44="Paid","Completed","Pending payment") -> Completed | G44: BB-0035 | H44: Freight / transport | I44: 45750 | J44: 45748 | K44: =TEXT(I44,"mmm-yyyy") -> Apr-2025 | L44: PKR | M44: 1 | N44: Steelstone Building Materials (Pvt) Ltd | O44: Head office - Lahore | P44: CC-LOG | Q44: N/A | R44: 03-Apr-2025 - By hand | S44: =IF(BN44<1,"Paid",IF(BM44>0,"Partially paid",IF(ISNUMBER(SEARCH("hold",BU44)),"On hold",IF(BQ44<TODAY(),"Overdue","Approved - unpaid")))) -> Paid | T44: Transporter | U44: TRN-002 - Al-Madina Logistics (Pvt) Ltd | V44: 5567123-4 | W44: Active Filer | X44: No | Y44: Tahir Mehmood - 0321-4789012 | Z44: MCB Bank Ltd - 0654-7701122301 | AA44: Credit 30 days | AB44: 0 | AC44: N/A | AD44: N/A | AE44: TC-TRN-002-2024 | AF44: 1 | AG44: SRV-FRT-BAG | AH44: Freight - bagged cement per trip | AI44: Trip | AJ44: =COUNTIFS('T14'!$AQ$3:$AQ$1500,B44,'T14'!$Z$3:$Z$1500,1,'T14'!$F$3:$F$1500,"Bag") -> 3 | AK44: =AJ44 -> 3 | AL44: 39000 | AM44: =AK44*AL44 -> 117000 | AN44: =AM44 -> 117000 | AO44: =_xlfn.XLOOKUP(AG44,'T13'!$A$3:$A$1500,'T13'!$O$3:$O$1500) -> 0.16 | AP44: 0 | AQ44: =SUMIFS($AN$3:$AN$1500,$G$3:$G$1500,G44) -> 117000 | AR44: =SUMIFS($AP$3:$AP$1500,$G$3:$G$1500,G44) -> 0 | AS44: 153(1)(b) transport - 4% | AT44: =ROUND(BH44*0.04,0) -> 5429 | AU44: No | AV44: {=SUMPRODUCT(($G$3:$G$1500=G44)*$AN$3:$AN$1500*$AO$3:$AO$1500)+AR44} -> 18720 | AW44: =AT44 -> 5429 | AX44: =TEXT(EOMONTH(I44,0)+15,"dd-mmm-yyyy")&" / "&IF(BM44>0,"CPR-IT-"&TEXT(I44,"yymm")&"-"&RIGHT(G44,4),"Pending payment") -> 15-May-2025 / CPR-IT-2504-0035 | AY44: =IF(BM44>0,"Issued","Not yet") -> Issued | AZ44: 0 | BA44: 0 | BB44: 0 | BC44: 0 | BD44: 0 | BE44: =AQ44 -> 117000 | BF44: =AV44 -> 18720 | BG44: =AZ44 -> 0 | BH44: =BE44+BF44+BG44 -> 135720 | BI44: =AW44 -> 5429 | BJ44: =BA44+BB44+BC44+BD44 -> 0 | BK44: =BH44-BI44-BJ44 -> 130291 | BL44: ="PKR "&TEXT(BK44,"#,##0")&" only" -> PKR 130,291 only | BM44: =SUMIFS('T10'!$AK$3:$AK$1500,'T10'!$V$3:$V$1500,G44) -> 130291 | BN44: =BK44-BM44 -> 0 | BO44: =IF(BF44>0,TEXT(I44,"mmm-yyyy")&" sales tax return","N/A") -> Apr-2025 sales tax return | BP44: Credit 30 days | BQ44: =J44+30 -> 45778 | BR44: =BQ44 -> 45778 | BS44: IBFT | BT44: Normal | BU44: N/A | BV44: No | BW44: {=_xlfn.TEXTJOIN(", ",TRUE,_xlfn.UNIQUE(_xlfn._xlws.FILTER('T10'!$A$3:$A$1500,'T10'!$V$3:$V$1500=G44,"None")))} -> PV-0012 | BX44: Hassan Raza - 04-Apr-2025 | BY44: Sana Iqbal - 05-Apr-2025
A45: TRN-001 Khan Goods Transport Co (NTN 17301-5567812-9 (CNIC)) | B45: FB-TRN001-2503 | C45: DRY-00036 | D45: 45750.458 | E45: Yes - SMS & email | F45: =IF(S45="Paid","Completed","Pending payment") -> Completed | G45: BB-0036 | H45: Freight / transport | I45: 45750 | J45: 45748 | K45: =TEXT(I45,"mmm-yyyy") -> Apr-2025 | L45: PKR | M45: 1 | N45: Steelstone Building Materials (Pvt) Ltd | O45: Head office - Lahore | P45: CC-LOG | Q45: N/A | R45: 03-Apr-2025 - By hand | S45: =IF(BN45<1,"Paid",IF(BM45>0,"Partially paid",IF(ISNUMBER(SEARCH("hold",BU45)),"On hold",IF(BQ45<TODAY(),"Overdue","Approved - unpaid")))) -> Paid | T45: Transporter | U45: TRN-001 - Khan Goods Transport Co | V45: 17301-5567812-9 (CNIC) | W45: Active Filer | X45: No | Y45: Gul Khan - 0300-5991287 | Z45: Habib Bank Ltd - 2210-79004455-01 | AA45: Credit 30 days | AB45: 0 | AC45: N/A | AD45: N/A | AE45: TC-TRN-001-2024 | AF45: 1 | AG45: SRV-FRT-BAG | AH45: Freight - bagged cement per trip | AI45: Trip | AJ45: =COUNTIFS('T14'!$AQ$3:$AQ$1500,B45,'T14'!$Z$3:$Z$1500,1,'T14'!$F$3:$F$1500,"Bag") -> 3 | AK45: =AJ45 -> 3 | AL45: 39000 | AM45: =AK45*AL45 -> 117000 | AN45: =AM45 -> 117000 | AO45: =_xlfn.XLOOKUP(AG45,'T13'!$A$3:$A$1500,'T13'!$O$3:$O$1500) -> 0.16 | AP45: 0 | AQ45: =SUMIFS($AN$3:$AN$1500,$G$3:$G$1500,G45) -> 117000 | AR45: =SUMIFS($AP$3:$AP$1500,$G$3:$G$1500,G45) -> 0 | AS45: 153(1)(b) transport - 4% | AT45: =ROUND(BH45*0.04,0) -> 5429 | AU45: No | AV45: {=SUMPRODUCT(($G$3:$G$1500=G45)*$AN$3:$AN$1500*$AO$3:$AO$1500)+AR45} -> 18720 | AW45: =AT45 -> 5429 | AX45: =TEXT(EOMONTH(I45,0)+15,"dd-mmm-yyyy")&" / "&IF(BM45>0,"CPR-IT-"&TEXT(I45,"yymm")&"-"&RIGHT(G45,4),"Pending payment") -> 15-May-2025 / CPR-IT-2504-0036 | AY45: =IF(BM45>0,"Issued","Not yet") -> Issued | AZ45: 0 | BA45: 0 | BB45: 0 | BC45: 0 | BD45: 0 | BE45: =AQ45 -> 117000 | BF45: =AV45 -> 18720 | BG45: =AZ45 -> 0 | BH45: =BE45+BF45+BG45 -> 135720 | BI45: =AW45 -> 5429 | BJ45: =BA45+BB45+BC45+BD45 -> 0 | BK45: =BH45-BI45-BJ45 -> 130291 | BL45: ="PKR "&TEXT(BK45,"#,##0")&" only" -> PKR 130,291 only | BM45: =SUMIFS('T10'!$AK$3:$AK$1500,'T10'!$V$3:$V$1500,G45) -> 130291 | BN45: =BK45-BM45 -> 0 | BO45: =IF(BF45>0,TEXT(I45,"mmm-yyyy")&" sales tax return","N/A") -> Apr-2025 sales tax return | BP45: Credit 30 days | BQ45: =J45+30 -> 45778 | BR45: =BQ45 -> 45778 | BS45: IBFT | BT45: Normal | BU45: N/A | BV45: No | BW45: {=_xlfn.TEXTJOIN(", ",TRUE,_xlfn.UNIQUE(_xlfn._xlws.FILTER('T10'!$A$3:$A$1500,'T10'!$V$3:$V$1500=G45,"None")))} -> PV-0005 | BX45: Hassan Raza - 04-Apr-2025 | BY45: Sana Iqbal - 05-Apr-2025
A46: VEN-105 Pakistan State Oil - fuel card (NTN 0801523-9) | B46: 105/2504/2575 | C46: DRY-00037 | D46: 45750.583 | E46: Yes - SMS & email | F46: =IF(S46="Paid","Completed","Pending payment") -> Completed | G46: BB-0037 | H46: Goods - fuel | I46: 45751 | J46: 45749 | K46: =TEXT(I46,"mmm-yyyy") -> Apr-2025 | L46: PKR | M46: 1 | N46: Steelstone Building Materials (Pvt) Ltd | O46: Raiwind Road warehouse | P46: CC-LOG | Q46: N/A | R46: 03-Apr-2025 - Email | S46: =IF(BN46<1,"Paid",IF(BM46>0,"Partially paid",IF(ISNUMBER(SEARCH("hold",BU46)),"On hold",IF(BQ46<TODAY(),"Overdue","Approved - unpaid")))) -> Paid | T46: Other vendor - Goods - fuel | U46: VEN-105 - Pakistan State Oil - fuel card | V46: 0801523-9 | W46: Active Filer | X46: No | Y46: Accounts desk - 042-35483071 | Z46: Meezan - 9225-9427766 | AA46: Credit 15 days | AB46: 0 | AC46: N/A | AD46: N/A | AE46: N/A | AF46: 1 | AG46: CON-DSL | AH46: High speed diesel | AI46: Litre | AJ46: 430 | AK46: 430 | AL46: 280 | AM46: =AK46*AL46 -> 120400 | AN46: =AM46 -> 120400 | AO46: =_xlfn.XLOOKUP(AG46,'T13'!$A$3:$A$1500,'T13'!$O$3:$O$1500) -> 0.18 | AP46: 0 | AQ46: =SUMIFS($AN$3:$AN$1500,$G$3:$G$1500,G46) -> 120400 | AR46: =SUMIFS($AP$3:$AP$1500,$G$3:$G$1500,G46) -> 0 | AS46: N/A - petroleum | AT46: =ROUND(BH46*0,0) -> 0 | AU46: No | AV46: {=SUMPRODUCT(($G$3:$G$1500=G46)*$AN$3:$AN$1500*$AO$3:$AO$1500)+AR46} -> 21672 | AW46: =AT46 -> 0 | AX46: =TEXT(EOMONTH(I46,0)+15,"dd-mmm-yyyy")&" / "&IF(BM46>0,"CPR-IT-"&TEXT(I46,"yymm")&"-"&RIGHT(G46,4),"Pending payment") -> 15-May-2025 / CPR-IT-2504-0037 | AY46: =IF(BM46>0,"Issued","Not yet") -> Issued | AZ46: 0 | BA46: 0 | BB46: 0 | BC46: 0 | BD46: 0 | BE46: =AQ46 -> 120400 | BF46: =AV46 -> 21672 | BG46: =AZ46 -> 0 | BH46: =BE46+BF46+BG46 -> 142072 | BI46: =AW46 -> 0 | BJ46: =BA46+BB46+BC46+BD46 -> 0 | BK46: =BH46-BI46-BJ46 -> 142072 | BL46: ="PKR "&TEXT(BK46,"#,##0")&" only" -> PKR 142,072 only | BM46: =SUMIFS('T10'!$AK$3:$AK$1500,'T10'!$V$3:$V$1500,G46) -> 142072 | BN46: =BK46-BM46 -> 0 | BO46: =IF(BF46>0,TEXT(I46,"mmm-yyyy")&" sales tax return","N/A") -> Apr-2025 sales tax return | BP46: Credit 15 days | BQ46: =J46+15 -> 45764 | BR46: =BQ46 -> 45764 | BS46: IBFT | BT46: Normal | BU46: N/A | BV46: No | BW46: {=_xlfn.TEXTJOIN(", ",TRUE,_xlfn.UNIQUE(_xlfn._xlws.FILTER('T10'!$A$3:$A$1500,'T10'!$V$3:$V$1500=G46,"None")))} -> PV-0034 | BX46: Hassan Raza - 05-Apr-2025 | BY46: Sana Iqbal - 06-Apr-2025
A47: VEN-104 Nayatel (Pvt) Ltd (NTN 2098765-4) | B47: 104/2504/9825 | C47: DRY-00038 | D47: 45762.667 | E47: Yes - SMS & email | F47: =IF(S47="Paid","Completed","Pending payment") -> Completed | G47: BB-0038 | H47: Utilities | I47: 45762 | J47: 45760 | K47: =TEXT(I47,"mmm-yyyy") -> Apr-2025 | L47: PKR | M47: 1 | N47: Steelstone Building Materials (Pvt) Ltd | O47: Head office - Lahore | P47: CC-ADMIN | Q47: N/A | R47: 15-Apr-2025 - Email | S47: =IF(BN47<1,"Paid",IF(BM47>0,"Partially paid",IF(ISNUMBER(SEARCH("hold",BU47)),"On hold",IF(BQ47<TODAY(),"Overdue","Approved - unpaid")))) -> Paid | T47: Other vendor - Utilities | U47: VEN-104 - Nayatel (Pvt) Ltd | V47: 2098765-4 | W47: Active Filer | X47: No | Y47: Accounts desk - 042-35660073 | Z47: Meezan - 5857-6193451 | AA47: Credit 15 days | AB47: 0 | AC47: N/A | AD47: N/A | AE47: N/A | AF47: 1 | AG47: SRV-INT | AH47: Internet & telephone | AI47: Month | AJ47: 1 | AK47: 1 | AL47: 25600 | AM47: =AK47*AL47 -> 25600 | AN47: =AM47 -> 25600 | AO47: =_xlfn.XLOOKUP(AG47,'T13'!$A$3:$A$1500,'T13'!$O$3:$O$1500) -> 0.16 | AP47: 0 | AQ47: =SUMIFS($AN$3:$AN$1500,$G$3:$G$1500,G47) -> 25600 | AR47: =SUMIFS($AP$3:$AP$1500,$G$3:$G$1500,G47) -> 0 | AS47: N/A - tax collected in bill | AT47: =ROUND(BH47*0,0) -> 0 | AU47: No | AV47: {=SUMPRODUCT(($G$3:$G$1500=G47)*$AN$3:$AN$1500*$AO$3:$AO$1500)+AR47} -> 4096 | AW47: =AT47 -> 0 | AX47: =TEXT(EOMONTH(I47,0)+15,"dd-mmm-yyyy")&" / "&IF(BM47>0,"CPR-IT-"&TEXT(I47,"yymm")&"-"&RIGHT(G47,4),"Pending payment") -> 15-May-2025 / CPR-IT-2504-0038 | AY47: =IF(BM47>0,"Issued","Not yet") -> Issued | AZ47: 0 | BA47: 0 | BB47: 0 | BC47: 0 | BD47: 0 | BE47: =AQ47 -> 25600 | BF47: =AV47 -> 4096 | BG47: =AZ47 -> 0 | BH47: =BE47+BF47+BG47 -> 29696 | BI47: =AW47 -> 0 | BJ47: =BA47+BB47+BC47+BD47 -> 0 | BK47: =BH47-BI47-BJ47 -> 29696 | BL47: ="PKR "&TEXT(BK47,"#,##0")&" only" -> PKR 29,696 only | BM47: =SUMIFS('T10'!$AK$3:$AK$1500,'T10'!$V$3:$V$1500,G47) -> 29696 | BN47: =BK47-BM47 -> 0 | BO47: =IF(BF47>0,TEXT(I47,"mmm-yyyy")&" sales tax return","N/A") -> Apr-2025 sales tax return | BP47: Credit 15 days | BQ47: =J47+15 -> 45775 | BR47: =BQ47 -> 45775 | BS47: IBFT | BT47: Normal | BU47: N/A | BV47: No | BW47: {=_xlfn.TEXTJOIN(", ",TRUE,_xlfn.UNIQUE(_xlfn._xlws.FILTER('T10'!$A$3:$A$1500,'T10'!$V$3:$V$1500=G47,"None")))} -> PV-0010 | BX47: Hassan Raza - 16-Apr-2025 | BY47: Sana Iqbal - 17-Apr-2025
A48: VEN-106 Ghani Tyre & Lubricants (NTN 35202-1188776-5 (CNIC)) | B48: 106/2504/7213 | C48: DRY-00039 | D48: 45768.542 | E48: Yes - SMS & email | F48: =IF(S48="Paid","Completed","Pending payment") -> Completed | G48: BB-0039 | H48: Goods - spares | I48: 45769 | J48: 45767 | K48: =TEXT(I48,"mmm-yyyy") -> Apr-2025 | L48: PKR | M48: 1 | N48: Steelstone Building Materials (Pvt) Ltd | O48: Head office - Lahore | P48: CC-LOG | Q48: N/A | R48: 21-Apr-2025 - Email | S48: =IF(BN48<1,"Paid",IF(BM48>0,"Partially paid",IF(ISNUMBER(SEARCH("hold",BU48)),"On hold",IF(BQ48<TODAY(),"Overdue","Approved - unpaid")))) -> Paid | T48: Other vendor - Goods - spares | U48: VEN-106 - Ghani Tyre & Lubricants | V48: 35202-1188776-5 (CNIC) | W48: Active Filer | X48: No | Y48: Accounts desk - 042-35386602 | Z48: UBL - 6713-9542407 | AA48: Credit 30 days | AB48: 0 | AC48: PO-2504-917 | AD48: 07-Apr-2025 / PKR 635000 (approx.) | AE48: N/A | AF48: 1 | AG48: SPR-TYR | AH48: Truck tyre 1000-20 (18 ply) | AI48: Each | AJ48: 7 | AK48: 7 | AL48: 69630 | AM48: =AK48*AL48 -> 487410 | AN48: =AM48 -> 487410 | AO48: =_xlfn.XLOOKUP(AG48,'T13'!$A$3:$A$1500,'T13'!$O$3:$O$1500) -> 0.18 | AP48: 0 | AQ48: =SUMIFS($AN$3:$AN$1500,$G$3:$G$1500,G48) -> 538110 | AR48: =SUMIFS($AP$3:$AP$1500,$G$3:$G$1500,G48) -> 0 | AS48: 153(1)(a) goods - 5% | AT48: =ROUND(BH48*0.05,0) -> 31748 | AU48: No | AV48: {=SUMPRODUCT(($G$3:$G$1500=G48)*$AN$3:$AN$1500*$AO$3:$AO$1500)+AR48} -> 96859.8 | AW48: =AT48 -> 31748 | AX48: =TEXT(EOMONTH(I48,0)+15,"dd-mmm-yyyy")&" / "&IF(BM48>0,"CPR-IT-"&TEXT(I48,"yymm")&"-"&RIGHT(G48,4),"Pending payment") -> 15-May-2025 / CPR-IT-2504-0039 | AY48: =IF(BM48>0,"Issued","Not yet") -> Issued | AZ48: 0 | BA48: 0 | BB48: 0 | BC48: 0 | BD48: 0 | BE48: =AQ48 -> 538110 | BF48: =AV48 -> 96859.8 | BG48: =AZ48 -> 0 | BH48: =BE48+BF48+BG48 -> 634969.8 | BI48: =AW48 -> 31748 | BJ48: =BA48+BB48+BC48+BD48 -> 0 | BK48: =BH48-BI48-BJ48 -> 603221.8 | BL48: ="PKR "&TEXT(BK48,"#,##0")&" only" -> PKR 603,222 only | BM48: =SUMIFS('T10'!$AK$3:$AK$1500,'T10'!$V$3:$V$1500,G48) -> 603221.8 | BN48: =BK48-BM48 -> 0 | BO48: =IF(BF48>0,TEXT(I48,"mmm-yyyy")&" sales tax return","N/A") -> Apr-2025 sales tax return | BP48: Credit 30 days | BQ48: =J48+30 -> 45797 | BR48: =BQ48 -> 45797 | BS48: IBFT | BT48: Normal | BU48: N/A | BV48: No | BW48: {=_xlfn.TEXTJOIN(", ",TRUE,_xlfn.UNIQUE(_xlfn._xlws.FILTER('T10'!$A$3:$A$1500,'T10'!$V$3:$V$1500=G48,"None")))} -> PV-0039 | BX48: Hassan Raza - 23-Apr-2025 | BY48: Sana Iqbal - 24-Apr-2025
A49: VEN-106 Ghani Tyre & Lubricants (NTN 35202-1188776-5 (CNIC)) | B49: 106/2504/7213 | C49: DRY-00039 | D49: 45768.542 | E49: Yes - SMS & email | F49: =IF(S49="Paid","Completed","Pending payment") -> Completed | G49: BB-0039 | H49: Goods - spares | I49: 45769 | J49: 45767 | K49: =TEXT(I49,"mmm-yyyy") -> Apr-2025 | L49: PKR | M49: 1 | N49: Steelstone Building Materials (Pvt) Ltd | O49: Head office - Lahore | P49: CC-LOG | Q49: N/A | R49: 21-Apr-2025 - Email | S49: =IF(BN49<1,"Paid",IF(BM49>0,"Partially paid",IF(ISNUMBER(SEARCH("hold",BU49)),"On hold",IF(BQ49<TODAY(),"Overdue","Approved - unpaid")))) -> Paid | T49: Other vendor - Goods - spares | U49: VEN-106 - Ghani Tyre & Lubricants | V49: 35202-1188776-5 (CNIC) | W49: Active Filer | X49: No | Y49: Accounts desk - 042-35386602 | Z49: UBL - 6713-9542407 | AA49: Credit 30 days | AB49: 0 | AC49: PO-2504-917 | AD49: 05-Apr-2025 / PKR 635000 (approx.) | AE49: N/A | AF49: 2 | AG49: SPR-OIL | AH49: Engine oil 15W-40 - 20 L can | AI49: Can | AJ49: 3 | AK49: 3 | AL49: 16900 | AM49: =AK49*AL49 -> 50700 | AN49: =AM49 -> 50700 | AO49: =_xlfn.XLOOKUP(AG49,'T13'!$A$3:$A$1500,'T13'!$O$3:$O$1500) -> 0.18 | AP49: 0 | AQ49: =SUMIFS($AN$3:$AN$1500,$G$3:$G$1500,G49) -> 538110 | AR49: =SUMIFS($AP$3:$AP$1500,$G$3:$G$1500,G49) -> 0 | AS49: 153(1)(a) goods - 5% | AT49: =ROUND(BH49*0.05,0) -> 31748 | AU49: No | AV49: {=SUMPRODUCT(($G$3:$G$1500=G49)*$AN$3:$AN$1500*$AO$3:$AO$1500)+AR49} -> 96859.8 | AW49: =AT49 -> 31748 | AX49: =TEXT(EOMONTH(I49,0)+15,"dd-mmm-yyyy")&" / "&IF(BM49>0,"CPR-IT-"&TEXT(I49,"yymm")&"-"&RIGHT(G49,4),"Pending payment") -> 15-May-2025 / CPR-IT-2504-0039 | AY49: =IF(BM49>0,"Issued","Not yet") -> Issued | AZ49: 0 | BA49: 0 | BB49: 0 | BC49: 0 | BD49: 0 | BE49: =AQ49 -> 538110 | BF49: =AV49 -> 96859.8 | BG49: =AZ49 -> 0 | BH49: =BE49+BF49+BG49 -> 634969.8 | BI49: =AW49 -> 31748 | BJ49: =BA49+BB49+BC49+BD49 -> 0 | BK49: =BH49-BI49-BJ49 -> 603221.8 | BL49: ="PKR "&TEXT(BK49,"#,##0")&" only" -> PKR 603,222 only | BM49: =SUMIFS('T10'!$AK$3:$AK$1500,'T10'!$V$3:$V$1500,G49) -> 603221.8 | BN49: =BK49-BM49 -> 0 | BO49: =IF(BF49>0,TEXT(I49,"mmm-yyyy")&" sales tax return","N/A") -> Apr-2025 sales tax return | BP49: Credit 30 days | BQ49: =J49+30 -> 45797 | BR49: =BQ49 -> 45797 | BS49: IBFT | BT49: Normal | BU49: N/A | BV49: No | BW49: {=_xlfn.TEXTJOIN(", ",TRUE,_xlfn.UNIQUE(_xlfn._xlws.FILTER('T10'!$A$3:$A$1500,'T10'!$V$3:$V$1500=G49,"None")))} -> PV-0039 | BX49: Hassan Raza - 23-Apr-2025 | BY49: Sana Iqbal - 24-Apr-2025
